Workbook
Name ApiHeader: '_api'!$B$2:$BR$2
Name ApiRange: '_api'!$AT$3:$BR$1007
Name SPACER: LAMBDA(range, n, TRANSPOSE(SPLIT(JOIN(REPT(",",n+1),range),",",,0)))
Name FILTER_EMPTY: LAMBDA(range, FILTER(range,INDEX(range,1)<>""))
Name MAPDATA: LAMBDA(id, attr, ARRAYFORMULA(IFNA(VLOOKUP(id,'_api'!$B$3:$BW,MATCH(attr,'_api'!$B$2:$BW$2,0),0)) ))
Name MAPDATA_MODDED: LAMBDA(id, attr, mod, ARRAYFORMULA(IFNA(VLOOKUP(id,'_api'!$B$3:$BX,IFNA(MATCH(attr&"_"&LEFT(mod,2),'_api'!$B$2:$2,0),MATCH(attr,'_api'!$B$2:$2,0)),0)) ))

Sheet Settings
S1: c
B2: List of Poolers | D2: Use | E2: Mappool | F2: Abbreviation | G2: Best of | H2: Bans | I2: NM | J2: HD | K2: HR | L2: DT | M2: FM | N2: EZ | O2: HT | P2: TB | Q2: Sum | R2: Tentative SR
B3: play hd3 | D3: TRUE | E3: Qualifiers | F3: Quals | I3: 4 | J3: 2 | K3: 2 | L3: 2 | Q3: =SUM(I3:P3) -> 10 | R3: 5
B4: purl | D4: FALSE
B5: levica | D5: FALSE
B6: Aizenh | D6: FALSE
B7: shironai14 | D7: TRUE | E7: Round of 32 | F7: RO32 | G7: 9 | H7: 1 | I7: 5 | J7: 2 | K7: 2 | L7: 3 | M7: 2 | P7: 1 | Q7: =SUM(I7:P7) -> 15 | R7: 4.7
B8: sedi__ | D8: TRUE | E8: Round of 16 | F8: RO16 | G8: 9 | H8: 1 | I8: 5 | J8: 2 | K8: 2 | L8: 3 | M8: 2 | P8: 1 | Q8: =SUM(I8:P8) -> 15 | R8: 4.9
B9: matalisfangirl | D9: TRUE | E9: Quarterfinals | F9: QF | G9: 11 | H9: 2 | I9: 6 | J9: 3 | K9: 3 | L9: 3 | M9: 2 | P9: 1 | Q9: =SUM(I9:P9) -> 18 | R9: 5.1
B10: therealdeathmatch | D10: TRUE | E10: Semifinals | F10: SF | G10: 11 | H10: 2 | I10: 6 | J10: 3 | K10: 3 | L10: 3 | M10: 2 | P10: 1 | Q10: =SUM(I10:P10) -> 18 | R10: 5.3
B11: yillow | D11: TRUE | E11: Finals | F11: F | G11: 13 | H11: 2 | I11: 6 | J11: 3 | K11: 3 | L11: 4 | M11: 3 | P11: 1 | Q11: =SUM(I11:P11) -> 20 | R11: 5.5
B12: lunexia | D12: TRUE | E12: Grand Finals | F12: GF | G12: 13 | H12: 2 | I12: 6 | J12: 3 | K12: 3 | L12: 4 | M12: 3 | P12: 1 | Q12: =SUM(I12:P12) -> 20 | R12: 5.7
B13: Fuwub
B14: aoi hinami

Sheet Template
B2: Group Stage | C2: Best of | D2: =IFERROR(VLOOKUP(B2,Settings!E3:H12,3,0),"") | E2: Bans | F2: =IFERROR(VLOOKUP(B2,Settings!E3:H12,4,0),"")
B3: Suggestions | J3: Pool Assembly
B4: Map Link | C4: ID | D4: Mod | E4: Suggestor | F4: Map | H4: Notes | J4: Note | K4: ID | L4: Mod | M4: Map | O4: SR | P4: BPM | Q4: Length | R4: CS | S4: AR | T4: OD | U4: HP | V4: Mapper | W4: ID
F5: {=MAP(C5:C104,LAMBDA(id,IFNA(IMAGE(MAPDATA(id,"cover_url")),"")))} | G5: {=IFNA(HYPERLINK(VLOOKUP(C5:C104,'_api'!B3:BC104,MATCH("url",'_api'!B2:X2,0),0),VLOOKUP(C5:C104,'_api'!B3:BC104,MATCH("string",'_api'!B2:X2,0),0)),"")} | L5: =IFERROR(__xludf.DUMMYFUNCTION("TRANSPOSE(SPLIT(JOIN("","",MAP(TRANSPOSE(Settings!I2:P2),TRANSPOSE(INDEX(Settings!I3:P12,MATCH(B2,Settings!E3:E12,0))),LAMBDA(mod,n,JOIN("","",ARRAYFORMULA(IF(n=0,"""",mod&SEQUENCE(n))))))),"",""))"),"#VALUE!") -> #VALUE! | M5: {=MAP(K5:K104,LAMBDA(id,IFNA(IMAGE(MAPDATA(id,"cover_url")),"")))} | N5: =IFNA(MAPDATA(K5:K104,"string_url"),"") | O5: {=IFNA(MAPDATA_MODDED(K5:K104,{"difficultyrating","bpm","hit_length"},L5:L104),"")} -> #VALUE! | P5: #VALUE! | Q5: #VALUE! | R5: {=IFNA(MAPDATA_MODDED(K5:K104,"diff_"&{"size","approach","overall","drain"},L5:L104),"")} -> #VALUE! | S5: #VALUE! | T5: #VALUE! | U5: #VALUE! | V5: {=IFNA(MAPDATA(K5:K104,{"creator","beatmap_id"}),"")}

Sheet Quals
B2: Qualifiers | C2: Best of | D2: =IFERROR(VLOOKUP(B2,Settings!E3:H12,3,0),"") | E2: Bans | F2: =IFERROR(VLOOKUP(B2,Settings!E3:H12,4,0),"")
B3: Suggestions | J3: Pool Assembly
B4: Map Link | C4: ID | D4: Mod | E4: Suggestor | F4: Map | H4: Notes | J4: Note | K4: ID | L4: Mod | M4: Map | O4: SR | P4: BPM | Q4: Length | R4: CS | S4: AR | T4: OD | U4: Mapper | V4: ID
B5: https://osu.ppy.sh/beatmapsets/1658910#osu/3924030 | C5: =IFERROR(__xludf.DUMMYFUNCTION("ArrayFormula(IFERROR(VALUE(REGEXEXTRACT(B5:B104&"""",""\d+$""))))"),3924030.0) -> 3924030 | D5: NM | E5: shironai14 | F5: {=MAP(C5:C104,LAMBDA(id,IFNA(IMAGE(MAPDATA(id,"cover_url")),"")))} | G5: {=IFNA(HYPERLINK(VLOOKUP(C5:C298,'_api'!B3:BC104,MATCH("url",'_api'!B2:W2,0),0),VLOOKUP(C5:C298,'_api'!B3:BC104,MATCH("string",'_api'!B2:W2,0),0)),"")} -> nonoc - Relive [Insane] | K5: 3924030 | L5: =IFERROR(__xludf.DUMMYFUNCTION("TRANSPOSE(SPLIT(JOIN("","",MAP(TRANSPOSE(Settings!I2:P2),TRANSPOSE(INDEX(Settings!I3:P12,MATCH(B2,Settings!E3:E12,0))),LAMBDA(mod,n,JOIN("","",ARRAYFORMULA(IF(n=0,"""",mod&SEQUENCE(n))))))),"",""))"),"NM1") -> NM1 | M5: {=MAP(K5:K104,LAMBDA(id,IFNA(IMAGE(MAPDATA(id,"cover_url")),"")))} | N5: =IFNA(MAPDATA(K5:K104,"string_url"),"") -> nonoc - Relive [Insane] | O5: {=IFNA(MAPDATA_MODDED(K5:K104,{"difficultyrating","bpm","hit_length"},L5:L104),"")} -> 5.04539 | P5: 196 | Q5: 0.0025347222 | R5: {=IFNA(MAPDATA_MODDED(K5:K104,"diff_"&{"size","approach","overall"},L5:L104),"")} -> 3.5 | S5: 9 | T5: 8 | U5: {=IFNA(MAPDATA(K5:K104,{"creator","beatmap_id"}),"")} -> SkyFlame | V5: 3924030
B6: https://osu.ppy.sh/beatmapsets/1570531#osu/3207049 | C6: =IFERROR(__xludf.DUMMYFUNCTION("""COMPUTED_VALUE"""),3207049.0) -> 3207049 | D6: NM | E6: shironai14 | G6: Trerey-U - ::vexations [::insane] | I6: c | K6: 908887 | L6: =IFERROR(__xludf.DUMMYFUNCTION("""COMPUTED_VALUE"""),"NM2") -> NM2 | N6: void - Crisscrosser [Insane] | O6: 5.06513 | P6: 170 | Q6: 0.0013194444 | R6: 4 | S6: 9 | T6: 8 | U6: ouranhshc | V6: 908887
B7: https://osu.ppy.sh/beatmapsets/1975119#osu/4113699 | C7: =IFERROR(__xludf.DUMMYFUNCTION("""COMPUTED_VALUE"""),4113699.0) -> 4113699 | D7: NM | E7: shironai14 | G7: ATARASHII GAKKO! - OTONABLUE [-ktrihc's the last the fost [Insano waza]] | K7: 3035501 | L7: =IFERROR(__xludf.DUMMYFUNCTION("""COMPUTED_VALUE"""),"NM3") -> NM3 | N7: Sangatsu no Phantasia - Koufuku na Wagamama [Insane] | O7: 4.88183 | P7: 135 | Q7: 0.0024421296 | R7: 4 | S7: 9 | T7: 8 | U7: Jiysea | V7: 3035501
B8: https://osu.ppy.sh/beatmapsets/1544866#osu/3737825 | C8: =IFERROR(__xludf.DUMMYFUNCTION("""COMPUTED_VALUE"""),3737825.0) -> 3737825 | D8: NM | E8: matalisfangirl | G8: PSYQUI - Education [sorciere's Insane] | K8: 3737825 | L8: =IFERROR(__xludf.DUMMYFUNCTION("""COMPUTED_VALUE"""),"NM4") -> NM4 | N8: PSYQUI - Education [sorciere's Insane] | O8: 4.71109 | P8: 180 | Q8: 0.0024884259 | R8: 4 | S8: 9 | T8: 8 | U8: JeZag | V8: 3737825
B9: https://osu.ppy.sh/beatmapsets/1207286#osu/2514122 | C9: =IFERROR(__xludf.DUMMYFUNCTION("""COMPUTED_VALUE"""),2514122.0) -> 2514122 | D9: HD | E9: sedi__ | G9: Wagakki Band - Kagerou Days [Ducky-'s Insane] | K9: 2094462 | L9: =IFERROR(__xludf.DUMMYFUNCTION("""COMPUTED_VALUE"""),"HD1") -> HD1 | N9: Ax feat. Natsukawa Yoko - Sakimori Renka [Insane] | O9: 5.05371 | P9: 170 | Q9: 0.0020023148 | R9: 4.5 | S9: 9 | T9: 8 | U9: Yusomi | V9: 2094462
B10: https://osu.ppy.sh/beatmapsets/1238190#osu/2619929 | C10: =IFERROR(__xludf.DUMMYFUNCTION("""COMPUTED_VALUE"""),2619929.0) -> 2619929 | D10: HD | E10: play hd3 | G10: Amane - BOOZEHOUND [Down's Insane] | H10: hd2 | K10: 2619929 | L10: =IFERROR(__xludf.DUMMYFUNCTION("""COMPUTED_VALUE"""),"HD2") -> HD2 | N10: Amane - BOOZEHOUND [Down's Insane] | O10: 4.61004 | P10: 165 | Q10: 0.0016550926 | R10: 5 | S10: 8 | T10: 7 | U10: Luscent | V10: 2619929
B11: https://osu.ppy.sh/beatmapsets/1918243#osu/3958395 | C11: =IFERROR(__xludf.DUMMYFUNCTION("""COMPUTED_VALUE"""),3958395.0) -> 3958395 | D11: HR | E11: shironai14 | G11: Numakura Manami - Sakebe [Mrgglock's Insane] | H11: hr1 | K11: 2027623 | L11: =IFERROR(__xludf.DUMMYFUNCTION("""COMPUTED_VALUE"""),"HR1") -> HR1 | N11: THE ORAL CIGARETTES - Wagamama de Gomakasanaide [Panda & Melwoine's Insane] | O11: 5.00382 | P11: 142 | Q11: 0.0029166667 | R11: 4.94 | S11: 10 | T11: 10 | U11: DeviousPanda | V11: 2027623
B12: https://osu.ppy.sh/beatmapsets/721320#osu/1523138 | C12: =IFERROR(__xludf.DUMMYFUNCTION("""COMPUTED_VALUE"""),1523138.0) -> 1523138 | D12: HR | E12: yillow | G12: Kajiura Yuki - Sis puella magica! [Tea Party] | H12: hr2 | K12: 1523138 | L12: =IFERROR(__xludf.DUMMYFUNCTION("""COMPUTED_VALUE"""),"HR2") -> HR2 | N12: Kajiura Yuki - Sis puella magica! [Tea Party] | O12: 4.44079 | P12: 155.42 | Q12: 0.0016782407 | R12: 6.5 | S12: 10 | T12: 10 | U12: Asonate | V12: 1523138
B13: https://osu.ppy.sh/beatmapsets/1977605#osu/4105349 | C13: =IFERROR(__xludf.DUMMYFUNCTION("""COMPUTED_VALUE"""),4105349.0) -> 4105349 | D13: DT | E13: shironai14 | G13: ICHIKO - YOU'RE THE ONE [ANDREA & ASUKO'S HARD] | K13: 4105349 | L13: =IFERROR(__xludf.DUMMYFUNCTION("""COMPUTED_VALUE"""),"DT1") -> DT1 | N13: ICHIKO - YOU'RE THE ONE [ANDREA & ASUKO'S HARD] | O13: 5.08077 | P13: 235.5 | Q13: 0.0017052469 | R13: 3.8 | S13: 9.6666667 | T13: 8.4166667 | U13: Andrea | V13: 4105349
B14: https://osu.ppy.sh/beatmapsets/1670325#osu/3411549 | C14: =IFERROR(__xludf.DUMMYFUNCTION("""COMPUTED_VALUE"""),3411549.0) -> 3411549 | D14: DT | E14: shironai14 | G14: Ardolf - Split EX [HARD] | K14: 3533589 | L14: =IFERROR(__xludf.DUMMYFUNCTION("""COMPUTED_VALUE"""),"DT2") -> DT2 | N14: DIANA - Beethoven Virus [Aranel's Hard] | O14: 4.78925 | P14: 234 | Q14: 0.0016512346 | R14: 3.6 | S14: 9 | T14: 8.6833333 | U14: Orkay | V14: 3533589
B15: https://osu.ppy.sh/beatmapsets/1061614#osu/2395972 | C15: =IFERROR(__xludf.DUMMYFUNCTION("""COMPUTED_VALUE"""),2395972.0) -> 2395972 | D15: HD | E15: sedi__ | G15: Hanabusa Sumireko (CV: Arakawa Miho) - Inochi no Karakuri [Insane] | H15: HD1 tapping
B16: https://osu.ppy.sh/beatmapsets/1807986#osu/3720541 | C16: =IFERROR(__xludf.DUMMYFUNCTION("""COMPUTED_VALUE"""),3720541.0) -> 3720541 | D16: HD | E16: sedi__ | G16: SID - Mousou Nikki 2 [Miy's Insane] | H16: HD1
B17: https://osu.ppy.sh/beatmapsets/1496416#osu/3081261 | C17: =IFERROR(__xludf.DUMMYFUNCTION("""COMPUTED_VALUE"""),3081261.0) -> 3081261 | D17: NM | E17: sedi__ | G17: Co shu Nie - Yume o Kin'iro ni Somete [Insane ft. Kujinn] | H17: NM4
B18: https://osu.ppy.sh/beatmapsets/1712992#osu/3684386 | C18: =IFERROR(__xludf.DUMMYFUNCTION("""COMPUTED_VALUE"""),3684386.0) -> 3684386 | D18: HD | E18: shironai14 | G18: S3RL feat. Sara - Dopamine [Insane]
B19: https://osu.ppy.sh/beatmapsets/1841846#osu/3783139 | C19: =IFERROR(__xludf.DUMMYFUNCTION("""COMPUTED_VALUE"""),3783139.0) -> 3783139 | D19: HD | E19: shironai14 | G19: cYsmix - triangles [shime's absolutno another]
B20: https://osu.ppy.sh/beatmapsets/932567#osu/2027623 | C20: =IFERROR(__xludf.DUMMYFUNCTION("""COMPUTED_VALUE"""),2027623.0) -> 2027623 | D20: HR | E20: shironai14 | G20: THE ORAL CIGARETTES - Wagamama de Gomakasanaide [Panda & Melwoine's Insane]
B21: https://osu.ppy.sh/beatmapsets/1089678#osu/2305346 | C21: =IFERROR(__xludf.DUMMYFUNCTION("""COMPUTED_VALUE"""),2305346.0) -> 2305346 | D21: NM | E21: shironai14 | G21: Juggernaut. - Apocaliptix [PaRaDogi's Insane]
B22: https://osu.ppy.sh/beatmapsets/1212359#osu/3310401 | C22: =IFERROR(__xludf.DUMMYFUNCTION("""COMPUTED_VALUE"""),3310401.0) -> 3310401 | D22: NM | E22: shironai14 | G22: siromaru + cranky - conflict [Yoshino's Insane]
B23: https://osu.ppy.sh/beatmaps/4121042 | C23: =IFERROR(__xludf.DUMMYFUNCTION("""COMPUTED_VALUE"""),4121042.0) -> 4121042 | D23: DT | E23: shironai14 | G23: Dance Gavin Dance - Deception [Sebas' Hard]
B24: https://osu.ppy.sh/beatmapsets/357800#osu/908887 | C24: =IFERROR(__xludf.DUMMYFUNCTION("""COMPUTED_VALUE"""),908887.0) -> 908887 | D24: NM | E24: lunexia | G24: void - Crisscrosser [Insane]
B25: https://osu.ppy.sh/beatmapsets/1724615#osu/3533589 | C25: =IFERROR(__xludf.DUMMYFUNCTION("""COMPUTED_VALUE"""),3533589.0) -> 3533589 | D25: DT | G25: DIANA - Beethoven Virus [Aranel's Hard]
B26: https://osu.ppy.sh/beatmapsets/998415#osu/2094462 | C26: =IFERROR(__xludf.DUMMYFUNCTION("""COMPUTED_VALUE"""),2094462.0) -> 2094462 | D26: HD | G26: Ax feat. Natsukawa Yoko - Sakimori Renka [Insane]
B27: https://osu.ppy.sh/beatmapsets/1478828#osu/3035501 | C27: =IFERROR(__xludf.DUMMYFUNCTION("""COMPUTED_VALUE"""),3035501.0) -> 3035501 | D27: NM | G27: Sangatsu no Phantasia - Koufuku na Wagamama [Insane]
D28: HD

Sheet RO32
B2: Round of 32 | C2: Best of | D2: =IFERROR(VLOOKUP(B2,Settings!E3:H12,3,0),"") -> 9 | E2: Bans | F2: =IFERROR(VLOOKUP(B2,Settings!E3:H12,4,0),"") -> 1
B3: Suggestions | J3: Pool Assembly
B4: Map Link | C4: ID | D4: Mod | E4: Suggestor | F4: Map | H4: Notes | J4: Note | K4: ID | L4: Mod | M4: Map | O4: SR | P4: BPM | Q4: Length | R4: CS | S4: AR | T4: OD | U4: Mapper | V4: ID
C5: =IFERROR(__xludf.DUMMYFUNCTION("ArrayFormula(IFERROR(VALUE(REGEXEXTRACT(B5:B104&"""",""\d+$""))))"),"") | D5: NM | E5: play hd3 | F5: {=MAP(C5:C104,LAMBDA(id,IFNA(IMAGE(MAPDATA(id,"cover_url")),"")))} | G5: {=IFNA(HYPERLINK(VLOOKUP(C5:C104,'_api'!B3:BC104,MATCH("url",'_api'!B2:W2,0),0),VLOOKUP(C5:C104,'_api'!B3:BC104,MATCH("string",'_api'!B2:W2,0),0)),"")} | J5: Sedi didn't help | K5: 2277989 | L5: =IFERROR(__xludf.DUMMYFUNCTION("TRANSPOSE(SPLIT(JOIN("","",MAP(TRANSPOSE(Settings!I2:P2),TRANSPOSE(INDEX(Settings!I3:P12,MATCH(B2,Settings!E3:E12,0))),LAMBDA(mod,n,JOIN("","",ARRAYFORMULA(IF(n=0,"""",mod&SEQUENCE(n))))))),"",""))"),"NM1") -> NM1 | M5: {=MAP(K5:K104,LAMBDA(id,IFNA(IMAGE(MAPDATA(id,"cover_url")),"")))} | N5: =IFNA(MAPDATA(K5:K104,"string_url"),"") -> Hazuki - Uso to Shinjitsu [Insane] | O5: {=IFNA(MAPDATA_MODDED(K5:K104,{"difficultyrating","bpm","hit_length"},L5:L104),"")} -> 4.71288 | P5: 190 | Q5: 0.0027430556 | R5: {=IFNA(MAPDATA_MODDED(K5:K104,"diff_"&{"size","approach","overall"},L5:L104),"")} -> 3.8 | S5: 9 | T5: 7.5 | U5: {=IFNA(MAPDATA(K5:K104,{"creator","beatmap_id"}),"")} -> Akitoshi | V5: 2277989
B6: https://osu.ppy.sh/beatmapsets/1859662#osu/3823691 | C6: =IFERROR(__xludf.DUMMYFUNCTION("""COMPUTED_VALUE"""),3823691.0) -> 3823691 | D6: HD | E6: sedi__ | G6: Len - GHOST (feat. Such) [Amateurre's Insane] | H6: HD1 | I6: c | J6: Stream/Burst | K6: 3297107 | L6: =IFERROR(__xludf.DUMMYFUNCTION("""COMPUTED_VALUE"""),"NM2") -> NM2 | N6: Jun Kuroda - Terpsichore [Dancer's Delight] | O6: 4.74275 | P6: 181 | Q6: 0.001412037 | R6: 4 | S6: 9 | T6: 7.6 | U6: Quag | V6: 3297107
B7: https://osu.ppy.sh/beatmapsets/1435157#osu/2995193 | C7: =IFERROR(__xludf.DUMMYFUNCTION("""COMPUTED_VALUE"""),2995193.0) -> 2995193 | D7: NM | E7: sedi__ | G7: Street - Sakura Fubuki [99's Insane] | H7: NM2 | J7: Mixed alt | K7: 2440455 | L7: =IFERROR(__xludf.DUMMYFUNCTION("""COMPUTED_VALUE"""),"NM3") -> NM3 | N7: PUP - Anaphylaxis [Insane] | O7: 4.59244 | P7: 252 | Q7: 0.0019328704 | R7: 4 | S7: 9 | T7: 7.7 | U7: Hobbes2 | V7: 2440455
B8: https://osu.ppy.sh/beatmapsets/932654#osu/2016938 | C8: =IFERROR(__xludf.DUMMYFUNCTION("""COMPUTED_VALUE"""),2016938.0) -> 2016938 | D8: DT | G8: Pastel*Palettes - Happy Synthesizer [Mikan's Hard] | H8: DT3 | J8: Control / Slideraim | K8: 3248876 | L8: =IFERROR(__xludf.DUMMYFUNCTION("""COMPUTED_VALUE"""),"NM4") -> NM4 | N8: ISOMERZ (DJ Raisei + seatrus) - Symmetric [BOUYAAA's Insane] | O8: 4.42076 | P8: 200 | Q8: 0.001412037 | R8: 4 | S8: 9 | T8: 8 | U8: Realazy | V8: 3248876
B9: 2340750 | C9: =IFERROR(__xludf.DUMMYFUNCTION("""COMPUTED_VALUE"""),2340750.0) -> 2340750 | D9: NM | E9: play hd3 | G9: Yorushika - Itte. [Insane] | H9: NM1 aim focus | J9: Lower ar/Alt | K9: 1989991 | L9: =IFERROR(__xludf.DUMMYFUNCTION("""COMPUTED_VALUE"""),"NM5") -> NM5 | N9: Pastel*Palettes - Happy Synthesizer [Insane] | O9: 4.58083 | P9: 127 | Q9: 0.0015393519 | R9: 4 | S9: 8.3 | T9: 7 | U9: ktgster | V9: 1989991
B10: 3297107 | C10: =IFERROR(__xludf.DUMMYFUNCTION("""COMPUTED_VALUE"""),3297107.0) -> 3297107 | D10: NM | E10: lunexia | G10: Jun Kuroda - Terpsichore [Dancer's Delight] | H10: NM2 stream/burst/fingercontrol mix | J10: Awkward aim / Slideraim | K10: 3280686 | L10: =IFERROR(__xludf.DUMMYFUNCTION("""COMPUTED_VALUE"""),"HD1") -> HD1 | N10: Tsumiki - phony [Hatsune Miku's Insane] | O10: 4.75975 | P10: 170 | Q10: 0.0020138889 | R10: 3.3 | S10: 9 | T10: 8 | U10: Ryuusei Aika | V10: 3280686
B11: 2440455 | C11: =IFERROR(__xludf.DUMMYFUNCTION("""COMPUTED_VALUE"""),2440455.0) -> 2440455 | D11: NM | E11: play hd3 | G11: PUP - Anaphylaxis [Insane] | H11: NM3 mixed alt | J11: Aim/Burst | K11: 134141 | L11: =IFERROR(__xludf.DUMMYFUNCTION("""COMPUTED_VALUE"""),"HD2") -> HD2 | N11: P*Light - Poppin' Shower [Hyper] | O11: 4.33398 | P11: 175 | Q11: 0.0012268519 | R11: 4 | S11: 8 | T11: 6 | U11: Reisen Udongein | V11: 134141
B12: 3248876 | C12: =IFERROR(__xludf.DUMMYFUNCTION("""COMPUTED_VALUE"""),3248876.0) -> 3248876 | D12: NM | E12: play hd3 | G12: ISOMERZ (DJ Raisei + seatrus) - Symmetric [BOUYAAA's Insane] | H12: NM4 Fingercontrol and Slideraim mix | J12: Consistency | K12: 2659337 | L12: =IFERROR(__xludf.DUMMYFUNCTION("""COMPUTED_VALUE"""),"HR1") -> HR1 | N12: Omoi - Teo [waji's Insane] | O12: 4.597 | P12: 185 | Q12: 0.0019907407 | R12: 5.2 | S12: 10 | T12: 9.8 | U12: Shmiklak | V12: 2659337
B13: 1989991 | C13: =IFERROR(__xludf.DUMMYFUNCTION("""COMPUTED_VALUE"""),1989991.0) -> 1989991 | D13: NM | E13: play hd3 | G13: Pastel*Palettes - Happy Synthesizer [Insane] | H13: NM5 Alt | J13: Linear AIm | K13: 2110801 | L13: =IFERROR(__xludf.DUMMYFUNCTION("""COMPUTED_VALUE"""),"HR2") -> HR2 | N13: Silentroom - NULCTRL [Pattern 03a "exHRD" LMT] | O13: 4.26034 | P13: 100 | Q13: 0.0016666667 | R13: 6.5 | S13: 10 | T13: 9.8 | U13: Nerova Riuz GX | V13: 2110801
B14: 3280686 | C14: =IFERROR(__xludf.DUMMYFUNCTION("""COMPUTED_VALUE"""),3280686.0) -> 3280686 | D14: HD | E14: play hd3 | G14: Tsumiki - phony [Hatsune Miku's Insane] | H14: HD1 Bit awkward aim bit slideraim | J14: Farm kekw | K14: 2044893 | L14: =IFERROR(__xludf.DUMMYFUNCTION("""COMPUTED_VALUE"""),"DT1") -> DT1 | N14: mafumafu - Moudoku ga Osou [Hard] | O14: 4.67429 | P14: 234 | Q14: 0.0015740741 | R14: 4 | S14: 9.6666667 | T14: 8.4166667 | U14: Namki | V14: 2044893
B15: 3396305 | C15: =IFERROR(__xludf.DUMMYFUNCTION("""COMPUTED_VALUE"""),3396305.0) -> 3396305 | D15: DT | E15: yillow | G15: xi - Mirage Garden [PaRaDogi's Hard] | H15: DT3 Fingercontrol (quite speddie) | J15: "Speed" | K15: 2366848 | L15: =IFERROR(__xludf.DUMMYFUNCTION("""COMPUTED_VALUE"""),"DT2") -> DT2 | N15: ARForest - Aoba [Hard] | O15: 4.72202 | P15: 225 | Q15: 0.0011342593 | R15: 3.5 | S15: 9.6666667 | T15: 8.4166667 | U15: Niva | V15: 2366848
B16: 3446761 | C16: =IFERROR(__xludf.DUMMYFUNCTION("""COMPUTED_VALUE"""),3446761.0) -> 3446761 | D16: TB | E16: lunexia | G16: Ata - Euphoria [Aiq's Insane] | H16: TB Mixed, including an alt section, pooled twice | J16: Finger control | K16: 3396305 | L16: =IFERROR(__xludf.DUMMYFUNCTION("""COMPUTED_VALUE"""),"DT3") -> DT3 | N16: xi - Mirage Garden [PaRaDogi's Hard] | O16: 4.66036 | P16: 234 | Q16: 0.0010570988 | R16: 3.8 | S16: 9.6666667 | T16: 9.0833333 | U16: DeviousPanda | V16: 3396305
B17: 2044893 | C17: =IFERROR(__xludf.DUMMYFUNCTION("""COMPUTED_VALUE"""),2044893.0) -> 2044893 | D17: DT | E17: lunexia | G17: mafumafu - Moudoku ga Osou [Hard] | H17: DT1 Farm YEP | J17: Balanced | K17: 846261 | L17: =IFERROR(__xludf.DUMMYFUNCTION("""COMPUTED_VALUE"""),"FM1") -> FM1 | N17: Shawn Wasabi - Marble Soda [Narcissu's Insane] | O17: 4.40919 | P17: 168 | Q17: 0.001712963 | R17: 4 | S17: 9 | T17: 7.5 | U17: Len | V17: 846261
B18: 3044231 | C18: =IFERROR(__xludf.DUMMYFUNCTION("""COMPUTED_VALUE"""),3044231.0) -> 3044231 | D18: FM | E18: play hd3 | G18: Zekk - Duplication [Insane] | H18: FM1 Techy/Speed | J18: Anti mod | K18: 3743202 | L18: =IFERROR(__xludf.DUMMYFUNCTION("""COMPUTED_VALUE"""),"FM2") -> FM2 | N18: -45 - Total Eclipse of The Sun [Hard] | O18: 3.73927 | P18: 120 | Q18: 0.0015277778 | R18: 5 | S18: 8 | T18: 6 | U18: Matrix | V18: 3743202
B19: 57384 | C19: =IFERROR(__xludf.DUMMYFUNCTION("""COMPUTED_VALUE"""),57384.0) -> 57384 | D19: FM | E19: lunexia | G19: K'naan - Wavin' Flag [Shuna's Flag!] | H19: FM2 Antimod weird mapping | J19: Aim/Stream/Alt | K19: 3446761 | L19: =IFERROR(__xludf.DUMMYFUNCTION("""COMPUTED_VALUE"""),"TB1") -> TB1 | N19: Ata - Euphoria [Aiq's Insane] | O19: 5.07342 | P19: 190 | Q19: 0.0035185185 | R19: 4 | S19: 9.2 | T19: 8.6 | U19: -Cermia | V19: 3446761
B20: 2110801 | C20: =IFERROR(__xludf.DUMMYFUNCTION("""COMPUTED_VALUE"""),2110801.0) -> 2110801 | D20: HR | E20: yillow | G20: Silentroom - NULCTRL [Pattern 03a "exHRD" LMT] | H20: HR2 linear / grid aim
B21: 2366848 | C21: =IFERROR(__xludf.DUMMYFUNCTION("""COMPUTED_VALUE"""),2366848.0) -> 2366848 | D21: DT | E21: play hd3 | G21: ARForest - Aoba [Hard] | H21: DT2 """"Speed""""
B22: 2694599 | C22: =IFERROR(__xludf.DUMMYFUNCTION("""COMPUTED_VALUE"""),2694599.0) -> 2694599 | D22: HD | E22: yillow | G22: Sound Souler - Eternalism 2 [Gibune's Insane] | H22: Slowstream HD2
B23: https://osu.ppy.sh/beatmapsets/42527#osu/134141 | C23: =IFERROR(__xludf.DUMMYFUNCTION("""COMPUTED_VALUE"""),134141.0) -> 134141 | D23: HD | E23: play hd3 | G23: P*Light - Poppin' Shower [Hyper] | H23: HD2 Old-style mirror mapping
B24: https://osu.ppy.sh/beatmapsets/80214#osu/250577 | C24: =IFERROR(__xludf.DUMMYFUNCTION("""COMPUTED_VALUE"""),250577.0) -> 250577 | D24: HR | E24: yillow | G24: Wotamin - Gigantic O.T.N [Hard] | H24: HR1 Old-style gridmapping
B25: 2161153 | C25: =IFERROR(__xludf.DUMMYFUNCTION("""COMPUTED_VALUE"""),2161153.0) -> 2161153 | D25: DT | E25: play hd3 | G25: OISHII - ONIGIRI FREEWAY [HARD] | H25: dt3 if no nm5
B26: 2795818 | C26: =IFERROR(__xludf.DUMMYFUNCTION("""COMPUTED_VALUE"""),2795818.0) -> 2795818 | D26: NM | E26: sedi__ | G26: the peggies - Neverland [Insane] | H26: NM1 aim focus
B27: 3941210 | C27: =IFERROR(__xludf.DUMMYFUNCTION("""COMPUTED_VALUE"""),3941210.0) -> 3941210 | D27: NM | E27: sedi__ | G27: kessoku band - Wasurete Yaranai [Amachama's Insane] | H27: NM2 fingercontrol focus
B28: 3742030 | C28: =IFERROR(__xludf.DUMMYFUNCTION("""COMPUTED_VALUE"""),3742030.0) -> 3742030 | D28: FM | G28: Risa Yuzuki - Cinderella Maker [Mindmaster's Hard]
B29: 846261 | C29: =IFERROR(__xludf.DUMMYFUNCTION("""COMPUTED_VALUE"""),846261.0) -> 846261 | D29: FM | E29: play hd3 | G29: Shawn Wasabi - Marble Soda [Narcissu's Insane]
B30: 2659337 | C30: =IFERROR(__xludf.DUMMYFUNCTION("""COMPUTED_VALUE"""),2659337.0) -> 2659337 | D30: HR | E30: yillow | G30: Omoi - Teo [waji's Insane]
B31: 2277989 | C31: =IFERROR(__xludf.DUMMYFUNCTION("""COMPUTED_VALUE"""),2277989.0) -> 2277989 | D31: NM | E31: play hd3 | G31: Hazuki - Uso to Shinjitsu [Insane]
B32: https://osu.ppy.sh/beatmapsets/1782707#osu/3743202 | C32: =IFERROR(__xludf.DUMMYFUNCTION("""COMPUTED_VALUE"""),3743202.0) -> 3743202 | D32: FM | G32: -45 - Total Eclipse of The Sun [Hard]

Sheet RO16
B2: Round of 16 | C2: Best of | D2: =IFERROR(VLOOKUP(B2,Settings!E3:H12,3,0),"") -> 9 | E2: Bans | F2: =IFERROR(VLOOKUP(B2,Settings!E3:H12,4,0),"") -> 1
B3: Suggestions | J3: Pool Assembly
B4: Map Link | C4: ID | D4: Mod | E4: Suggestor | F4: Map | H4: Notes | J4: Note | K4: ID | L4: Mod | M4: Map | O4: SR | P4: BPM | Q4: Length | R4: CS | S4: AR | T4: OD | U4: Mapper | V4: ID
B5: https://osu.ppy.sh/beatmapsets/111611#osu/306038 | C5: =IFERROR(__xludf.DUMMYFUNCTION("ArrayFormula(IFERROR(VALUE(REGEXEXTRACT(B5:B104&"""",""\d+$""))))"),306038.0) -> 306038 | D5: NM | E5: yillow | F5: {=MAP(C5:C104,LAMBDA(id,IFNA(IMAGE(MAPDATA(id,"cover_url")),"")))} | G5: {=IFNA(HYPERLINK(VLOOKUP(C5:C104,'_api'!B3:BC104,MATCH("url",'_api'!B2:W2,0),0),VLOOKUP(C5:C104,'_api'!B3:BC104,MATCH("string",'_api'!B2:W2,0),0)),"")} -> ZUN - Kobito of the Shining Needle ~ Little Princess [Lunatic] | H5: low bpm streams | J5: Consistency | K5: 2827293 | L5: =IFERROR(__xludf.DUMMYFUNCTION("TRANSPOSE(SPLIT(JOIN("","",MAP(TRANSPOSE(Settings!I2:P2),TRANSPOSE(INDEX(Settings!I3:P12,MATCH(B2,Settings!E3:E12,0))),LAMBDA(mod,n,JOIN("","",ARRAYFORMULA(IF(n=0,"""",mod&SEQUENCE(n))))))),"",""))"),"NM1") -> NM1 | M5: {=MAP(K5:K104,LAMBDA(id,IFNA(IMAGE(MAPDATA(id,"cover_url")),"")))} | N5: =IFNA(MAPDATA(K5:K104,"string_url"),"") -> Yorushika - Thoughtcrime [Akitoshi's Insane] | O5: {=IFNA(MAPDATA_MODDED(K5:K104,{"difficultyrating","bpm","hit_length"},L5:L104),"")} -> 4.88906 | P5: 200 | Q5: 0.0026851852 | R5: {=IFNA(MAPDATA_MODDED(K5:K104,"diff_"&{"size","approach","overall"},L5:L104),"")} -> 3.8 | S5: 9 | T5: 7.8 | U5: {=IFNA(MAPDATA(K5:K104,{"creator","beatmap_id"}),"")} -> Meg | V5: 2827293
B6: https://osu.ppy.sh/beatmapsets/1743257#osu/3563790 | C6: =IFERROR(__xludf.DUMMYFUNCTION("""COMPUTED_VALUE"""),3563790.0) -> 3563790 | D6: NM | E6: sedi__ | G6: Electronic Boutique - Miles [Minimal] | H6: NM3 | I6: c | J6: Stamina/Streams | K6: 2004679 | L6: =IFERROR(__xludf.DUMMYFUNCTION("""COMPUTED_VALUE"""),"NM2") -> NM2 | N6: Fractal Dreamers - Gardens Under A Spring Sky [Hyper] | O6: 4.90416 | P6: 195 | Q6: 0.0014351852 | R6: 4.5 | S6: 9 | T6: 8 | U6: Lasse | V6: 2004679
B7: https://osu.ppy.sh/beatmapsets/1528914#osu/3496410 | C7: =IFERROR(__xludf.DUMMYFUNCTION("""COMPUTED_VALUE"""),3496410.0) -> 3496410 | D7: TB | E7: sedi__ | G7: Shimotsuki Haruka, Chata, Katakiri Rekka - Suishou ni Utsuru Himegimi [Collab Insane] | H7: HD1 | J7: Alt consistency | K7: 3239199 | L7: =IFERROR(__xludf.DUMMYFUNCTION("""COMPUTED_VALUE"""),"NM3") -> NM3 | N7: Tsukuyomi - Dareka no Shinzou ni Nareta nara [too's Insane] | O7: 4.71336 | P7: 143 | Q7: 0.0026273148 | R7: 4 | S7: 9 | T7: 8 | U7: Mononymous | V7: 3239199
B8: https://osu.ppy.sh/beatmapsets/1758376#osu/3887774 | C8: =IFERROR(__xludf.DUMMYFUNCTION("""COMPUTED_VALUE"""),3887774.0) -> 3887774 | D8: HD | E8: sedi__ | G8: Noah - Purification of soul [Flame Haze's Insane] | J8: Slider aim | K8: 2794904 | L8: =IFERROR(__xludf.DUMMYFUNCTION("""COMPUTED_VALUE"""),"NM4") -> NM4 | N8: sakuraburst - Glacierfall (Park Remix) [haruto x ancel's ins*ne] | O8: 4.57912 | P8: 170 | Q8: 0.0016435185 | R8: 4 | S8: 9 | T8: 7.5 | U8: ScubDomino | V8: 2794904
B9: https://osu.ppy.sh/beatmapsets/1358622#osu/2827293 | C9: =IFERROR(__xludf.DUMMYFUNCTION("""COMPUTED_VALUE"""),2827293.0) -> 2827293 | D9: NM | E9: play hd3 | G9: Yorushika - Thoughtcrime [Akitoshi's Insane] | H9: skeleton nm1 | J9: Low ar/bpm finger control | K9: 2853477 | L9: =IFERROR(__xludf.DUMMYFUNCTION("""COMPUTED_VALUE"""),"NM5") -> NM5 | N9: sekai - Zange Mairi [Voice's Insane] | O9: 4.6484 | P9: 140 | Q9: 0.0020717593 | R9: 4.4 | S9: 8.3 | T9: 7 | U9: Yugu | V9: 2853477
B10: https://osu.ppy.sh/beatmapsets/956716#osu/2004679 | C10: =IFERROR(__xludf.DUMMYFUNCTION("""COMPUTED_VALUE"""),2004679.0) -> 2004679 | D10: NM | E10: lunexia | G10: Fractal Dreamers - Gardens Under A Spring Sky [Hyper] | H10: skeleton nm2 | J10: Consistency | K10: 1733441 | L10: =IFERROR(__xludf.DUMMYFUNCTION("""COMPUTED_VALUE"""),"HD1") -> HD1 | N10: Police Piccadilly feat. Hatsune Miku - Kire Carry On [negusver's Insane] | O10: 4.95838 | P10: 170 | Q10: 0.001724537 | R10: 4 | S10: 9 | T10: 8 | U10: Sinnoh | V10: 1733441
B11: https://osu.ppy.sh/beatmapsets/1508883#osu/3117101 | C11: =IFERROR(__xludf.DUMMYFUNCTION("""COMPUTED_VALUE"""),3117101.0) -> 3117101 | D11: NM | E11: play hd3 | G11: Yorushika - Dakara Boku wa Ongaku o Yameta [I'm not mistaken?] | H11: skeleton nm3 | J11: Reading/Streams | K11: 3460069 | L11: =IFERROR(__xludf.DUMMYFUNCTION("""COMPUTED_VALUE"""),"HD2") -> HD2 | N11: Siren - Polaris [8 is not a low ar guys] | O11: 4.42032 | P11: 174 | Q11: 0.0012731481 | R11: 4 | S11: 8 | T11: 7 | U11: -Cermia | V11: 3460069
B12: https://osu.ppy.sh/beatmapsets/564329#osu/1489274 | C12: =IFERROR(__xludf.DUMMYFUNCTION("""COMPUTED_VALUE"""),1489274.0) -> 1489274 | D12: NM | E12: play hd3 | G12: YUC'e - Sengoku HOP [apple's Insane] | H12: skeleton nm4 | J12: Consistency + Banger | K12: 1956568 | L12: =IFERROR(__xludf.DUMMYFUNCTION("""COMPUTED_VALUE"""),"HR1") -> HR1 | N12: PSYQUI feat. Such - Senchimentaruhatoboi [Insane] | O12: 4.85394 | P12: 160 | Q12: 0.0025 | R12: 4.94 | S12: 10 | T12: 10 | U12: eeezzzeee | V12: 1956568
B13: https://osu.ppy.sh/beatmapsets/1968201#osu/4082310 | C13: =IFERROR(__xludf.DUMMYFUNCTION("""COMPUTED_VALUE"""),4082310.0) -> 4082310 | D13: NM | E13: play hd3 | G13: chelmico - Easy Breezy [ezier bz] | H13: skeleton nm5 | J13: High CS/Wide angle jumps | K13: 295650 | L13: =IFERROR(__xludf.DUMMYFUNCTION("""COMPUTED_VALUE"""),"HR2") -> HR2 | N13: Perfume - Laser Beam [Mixagji] | O13: 4.62781 | P13: 135 | Q13: 0.0022453704 | R13: 6.5 | S13: 10 | T13: 9.8 | U13: Raging Bull | V13: 295650
B14: https://osu.ppy.sh/beatmapsets/50462#osu/155064 | C14: =IFERROR(__xludf.DUMMYFUNCTION("""COMPUTED_VALUE"""),155064.0) -> 155064 | D14: HD | E14: play hd3 | G14: Lon - Yuru Fuwa Jukai Girl [Insane] | H14: skeletion hd1 | J14: Burst heavy Consitency | K14: 3446883 | L14: =IFERROR(__xludf.DUMMYFUNCTION("""COMPUTED_VALUE"""),"DT1") -> DT1 | N14: Yumeno Yuki - First Time [KoldNoodl's Hard] | O14: 4.94646 | P14: 193.5 | Q14: 0.0016820988 | R14: 3.8 | S14: 9.6666667 | T14: 9.0833333 | U14: ImpurePug | V14: 3446883
B15: https://osu.ppy.sh/beatmapsets/1932625#osu/4024821 | C15: =IFERROR(__xludf.DUMMYFUNCTION("""COMPUTED_VALUE"""),4024821.0) -> 4024821 | D15: HD | E15: play hd3 | G15: Zemfira - kto? [riffy's insane] | H15: skeleton hd2 | J15: Alt/Bursts | K15: 1521209 | L15: =IFERROR(__xludf.DUMMYFUNCTION("""COMPUTED_VALUE"""),"DT2") -> DT2 | N15: YUC'e - Future Candy [Hard] | O15: 4.76186 | P15: 270 | Q15: 0.0013348765 | R15: 3.5 | S15: 9.6666667 | T15: 8.4166667 | U15: Nathan | V15: 1521209
B16: https://osu.ppy.sh/beatmapsets/1316097#osu/2729314 | C16: =IFERROR(__xludf.DUMMYFUNCTION("""COMPUTED_VALUE"""),2729314.0) -> 2729314 | D16: HR | E16: play hd3 | G16: Kaede To Kyo Aki Ame Kuzu - Q [Insane] | H16: skeleton hr1 | J16: Fingercontrol(?) | K16: 3616100 | L16: =IFERROR(__xludf.DUMMYFUNCTION("""COMPUTED_VALUE"""),"DT3") -> DT3 | N16: tarolabo - eth ken [hard] | O16: 4.72433 | P16: 189 | Q16: 0.00094135802 | R16: 3.6 | S16: 9.6666667 | T16: 8.75 | U16: DeviousPanda | V16: 3616100
B17: https://osu.ppy.sh/beatmapsets/25580#osu/87319 | C17: =IFERROR(__xludf.DUMMYFUNCTION("""COMPUTED_VALUE"""),87319.0) -> 87319 | D17: HR | E17: play hd3 | G17: Kakeru Hotarubi - Fanshi 3 Kami Goranshin [Insane] | H17: skeleton hr2 | J17: Speed CS3 | K17: 2151207 | L17: =IFERROR(__xludf.DUMMYFUNCTION("""COMPUTED_VALUE"""),"FM1") -> FM1 | N17: OISHII - ONIGIRI FREEWAY [LUKAS' INSANE] | O17: 4.63282 | P17: 210 | Q17: 0.0017592593 | R17: 3 | S17: 9 | T17: 8 | U17: Hazu- | V17: 2151207
B18: https://osu.ppy.sh/beatmapsets/914691#osu/1913099 | C18: =IFERROR(__xludf.DUMMYFUNCTION("""COMPUTED_VALUE"""),1913099.0) -> 1913099 | D18: DT | E18: play hd3 | G18: S3RL - MTC (Different Heaven Remix) [Hard] | H18: skeleton dt1 | J18: Grid Antimod | K18: 417898 | L18: =IFERROR(__xludf.DUMMYFUNCTION("""COMPUTED_VALUE"""),"FM2") -> FM2 | N18: Giga-P - Electric Angel [Sonnyc's Insane] | O18: 4.3997 | P18: 150 | Q18: 0.0015856481 | R18: 5 | S18: 8 | T18: 7 | U18: koreapenguin | V18: 417898
B19: https://osu.ppy.sh/beatmapsets/546820#osu/1521209 | C19: =IFERROR(__xludf.DUMMYFUNCTION("""COMPUTED_VALUE"""),1521209.0) -> 1521209 | D19: DT | E19: play hd3 | G19: YUC'e - Future Candy [Hard] | H19: skeleton dt2 | J19: Don't sighread :tf: | K19: 1857415 | L19: =IFERROR(__xludf.DUMMYFUNCTION("""COMPUTED_VALUE"""),"TB1") -> TB1 | N19: Au5 - Moonland [Collab Another] | O19: 5.08792 | P19: 170 | Q19: 0.0034027778 | R19: 4 | S19: 9 | T19: 8 | U19: DTM9 Nowa | V19: 1857415
B20: https://osu.ppy.sh/beatmapsets/1285447#osu/2967720 | C20: =IFERROR(__xludf.DUMMYFUNCTION("""COMPUTED_VALUE"""),2967720.0) -> 2967720 | D20: DT | E20: play hd3 | G20: hololive IDOL PROJECT - Koyoi wa Halloween Night! [sleepy's Hard] | H20: skeleton dt3
B21: https://osu.ppy.sh/beatmapsets/701330#osu/1498150 | C21: =IFERROR(__xludf.DUMMYFUNCTION("""COMPUTED_VALUE"""),1498150.0) -> 1498150 | D21: FM | E21: play hd3 | G21: I SEE MONSTAS - Holdin On (Skrillex and Nero Remix) [Insane] | H21: skeleton fm1
B22: https://osu.ppy.sh/beatmapsets/172900#osu/417898 | C22: =IFERROR(__xludf.DUMMYFUNCTION("""COMPUTED_VALUE"""),417898.0) -> 417898 | D22: FM | E22: play hd3 | G22: Giga-P - Electric Angel [Sonnyc's Insane] | H22: skeleton fm2
B23: https://osu.ppy.sh/beatmapsets/25802#osu/87369 | C23: =IFERROR(__xludf.DUMMYFUNCTION("""COMPUTED_VALUE"""),87369.0) -> 87369 | D23: HR | E23: yillow | G23: Hatsune Miku - Netoge Haijin Sprechchor [Insane] | H23: hr1 - streamy prob too hard
B24: https://osu.ppy.sh/beatmapsets/1157572#osu/2530278 | C24: =IFERROR(__xludf.DUMMYFUNCTION("""COMPUTED_VALUE"""),2530278.0) -> 2530278 | D24: HR | E24: yillow | G24: Hino Isuka - Moonheart (Mameyudoufu Remix) [Insane] | H24: hr1 - bursty "light tech"
B25: https://osu.ppy.sh/beatmapsets/409898#osu/892543 | C25: =IFERROR(__xludf.DUMMYFUNCTION("""COMPUTED_VALUE"""),892543.0) -> 892543 | D25: HR | E25: yillow | G25: Komiya Mao - (can you) understand me? [insane?] | H25: hr1 - just aim
B26: 3714964 | C26: =IFERROR(__xludf.DUMMYFUNCTION("""COMPUTED_VALUE"""),3714964.0) -> 3714964 | D26: HR | E26: play hd3 | G26: BotchiBoromaru - Otose Thunder [Shiny Braixen's Insane] | H26: hr1
B27: https://osu.ppy.sh/beatmapsets/1046876#osu/2200330 | C27: =IFERROR(__xludf.DUMMYFUNCTION("""COMPUTED_VALUE"""),2200330.0) -> 2200330 | D27: HD | E27: play hd3 | G27: nana(Sevencolors) - chameleon [Insane] | H27: hd2
B28: https://osu.ppy.sh/beatmapsets/824959#osu/1733441 | C28: =IFERROR(__xludf.DUMMYFUNCTION("""COMPUTED_VALUE"""),1733441.0) -> 1733441 | D28: HD | E28: play hd3 | G28: Police Piccadilly feat. Hatsune Miku - Kire Carry On [negusver's Insane] | H28: hd1
B29: https://osu.ppy.sh/beatmapsets/1759764#osu/3601684 | C29: =IFERROR(__xludf.DUMMYFUNCTION("""COMPUTED_VALUE"""),3601684.0) -> 3601684 | D29: NM | E29: play hd3 | G29: sekai - God-ish [Setu's Insane] | H29: nm3
B30: https://osu.ppy.sh/beatmapsets/123354#osu/315101 | C30: =IFERROR(__xludf.DUMMYFUNCTION("""COMPUTED_VALUE"""),315101.0) -> 315101 | D30: DT | E30: play hd3 | G30: DECO*27 - Ai Kotoba II [Insane] | H30: dt1
B31: https://osu.ppy.sh/beatmapsets/841634#osu/1761258 | C31: =IFERROR(__xludf.DUMMYFUNCTION("""COMPUTED_VALUE"""),1761258.0) -> 1761258 | D31: NM | E31: play hd3 | G31: HACHI feat. Hatsune Miku - Suna no Wakusei [Insane] | H31: nm5
B32: https://osu.ppy.sh/beatmapsets/1203052#osu/2701775 | C32: =IFERROR(__xludf.DUMMYFUNCTION("""COMPUTED_VALUE"""),2701775.0) -> 2701775 | D32: FM | G32: Chibanyan vs. Otogibara Era - GOMIKASU -Original Mix- [Insane] | H32: FM1
B33: https://osu.ppy.sh/beatmapsets/1693295#osu/3460069 | C33: =IFERROR(__xludf.DUMMYFUNCTION("""COMPUTED_VALUE"""),3460069.0) -> 3460069 | D33: HD | E33: lunexia | G33: Siren - Polaris [8 is not a low ar guys]
B34: https://osu.ppy.sh/beatmapsets/1488532#osu/3053637 | C34: =IFERROR(__xludf.DUMMYFUNCTION("""COMPUTED_VALUE"""),3053637.0) -> 3053637 | D34: DT | E34: play hd3 | G34: FROZEN QUALIA - Birthday [Hard]
B35: https://osu.ppy.sh/beatmapsets/1632817#osu/3332932 | C35: =IFERROR(__xludf.DUMMYFUNCTION("""COMPUTED_VALUE"""),3332932.0) -> 3332932 | D35: HR | E35: play hd3 | G35: Lil Nas X - THATS WHAT I WANT [GOKUGOHAN12468'S INSANE]
B36: https://osu.ppy.sh/beatmapsets/996628#osu/2151207 | C36: =IFERROR(__xludf.DUMMYFUNCTION("""COMPUTED_VALUE"""),2151207.0) -> 2151207 | D36: FM | E36: play hd3 | G36: OISHII - ONIGIRI FREEWAY [LUKAS' INSANE]
B37: https://osu.ppy.sh/beatmapsets/1494548#osu/3169863 | C37: =IFERROR(__xludf.DUMMYFUNCTION("""COMPUTED_VALUE"""),3169863.0) -> 3169863 | D37: NM | G37: DE DE MOUSE - Silly Love [0pp's Insane]
B38: https://osu.ppy.sh/beatmapsets/1401651#osu/2891411 | C38: =IFERROR(__xludf.DUMMYFUNCTION("""COMPUTED_VALUE"""),2891411.0) -> 2891411 | D38: HR | G38: kozato - Tsuki -Yue- [Kuse's Insane]
B39: https://osu.ppy.sh/beatmapsets/1329045#osu/2794904 | C39: =IFERROR(__xludf.DUMMYFUNCTION("""COMPUTED_VALUE"""),2794904.0) -> 2794904 | D39: NM | E39: play hd3 | G39: sakuraburst - Glacierfall (Park Remix) [haruto x ancel's ins*ne]
B40: https://osu.ppy.sh/beatmapsets/106568#osu/295650 | C40: =IFERROR(__xludf.DUMMYFUNCTION("""COMPUTED_VALUE"""),295650.0) -> 295650 | D40: HR | E40: therealdeathmatch | G40: Perfume - Laser Beam [Mixagji]
B41: https://osu.ppy.sh/beatmapsets/924701#osu/1956568 | C41: =IFERROR(__xludf.DUMMYFUNCTION("""COMPUTED_VALUE"""),1956568.0) -> 1956568 | D41: HR | E41: play hd3 | G41: PSYQUI feat. Such - Senchimentaruhatoboi [Insane]
B42: https://osu.ppy.sh/beatmapsets/1544600#osu/3239199 | C42: =IFERROR(__xludf.DUMMYFUNCTION("""COMPUTED_VALUE"""),3239199.0) -> 3239199 | D42: NM | E42: lunexia | G42: Tsukuyomi - Dareka no Shinzou ni Nareta nara [too's Insane]
B43: https://osu.ppy.sh/beatmapsets/1581327#osu/3446883 | C43: =IFERROR(__xludf.DUMMYFUNCTION("""COMPUTED_VALUE"""),3446883.0) -> 3446883 | D43: DT | E43: sedi__ | G43: Yumeno Yuki - First Time [KoldNoodl's Hard]
B44: https://osu.ppy.sh/beatmapsets/1765453#osu/3616100 | C44: =IFERROR(__xludf.DUMMYFUNCTION("""COMPUTED_VALUE"""),3616100.0) -> 3616100 | D44: DT | E44: sedi__ | G44: tarolabo - eth ken [hard]
B45: https://osu.ppy.sh/beatmapsets/1176431#osu/2853477 | C45: =IFERROR(__xludf.DUMMYFUNCTION("""COMPUTED_VALUE"""),2853477.0) -> 2853477 | D45: NM | E45: play hd3 | G45: sekai - Zange Mairi [Voice's Insane]
B46: https://osu.ppy.sh/beatmapsets/251437#osu/577517 | C46: =IFERROR(__xludf.DUMMYFUNCTION("""COMPUTED_VALUE"""),577517.0) -> 577517 | D46: TB | G46: Halozy - Genryuu Kaiko [Melody of Sanzu]
B47: https://osu.ppy.sh/beatmapsets/1901819#osu/3990086 | C47: =IFERROR(__xludf.DUMMYFUNCTION("""COMPUTED_VALUE"""),3990086.0) -> 3990086 | D47: NM | G47: Kai - Junk Lady [Deppy and Wanpachi's Insane]
B48: https://osu.ppy.sh/beatmapsets/790382#osu/1857415 | C48: =IFERROR(__xludf.DUMMYFUNCTION("""COMPUTED_VALUE"""),1857415.0) -> 1857415 | D48: TB | E48: yillow | G48: Au5 - Moonland [Collab Another]
B49: https://osu.ppy.sh/beatmapsets/1185294#osu/2536100 | C49: =IFERROR(__xludf.DUMMYFUNCTION("""COMPUTED_VALUE"""),2536100.0) -> 2536100 | D49: TB | E49: yillow | G49: Hatsuki Yura - Drivi'n greedy - Nhato Remix - [BF's Insane]

Sheet QF
A1: aaa
B2: Quarterfinals | C2: Best of | D2: =IFERROR(VLOOKUP(B2,Settings!E3:H12,3,0),"") -> 11 | E2: Bans | F2: =IFERROR(VLOOKUP(B2,Settings!E3:H12,4,0),"") -> 2
B3: Suggestions | J3: Pool Assembly
B4: Map Link | C4: ID | D4: Mod | E4: Suggestor | F4: Map | H4: Notes | J4: Note | K4: ID | L4: Mod | M4: Map | O4: SR | P4: BPM | Q4: Length | R4: CS | S4: AR | T4: OD | U4: Mapper | V4: ID
B5: https://osu.ppy.sh/beatmapsets/1615650#osu/3298592 | C5: =IFERROR(__xludf.DUMMYFUNCTION("ArrayFormula(IFERROR(VALUE(REGEXEXTRACT(B5:B104&"""",""\d+$""))))"),3298592.0) -> 3298592 | D5: HD | F5: {=MAP(C5:C104,LAMBDA(id,IFNA(IMAGE(MAPDATA(id,"cover_url")),"")))} | G5: {=IFNA(HYPERLINK(VLOOKUP(C5:C104,'_api'!B3:BC104,MATCH("url",'_api'!B2:W2,0),0),VLOOKUP(C5:C104,'_api'!B3:BC104,MATCH("string",'_api'!B2:W2,0),0)),"")} -> kors k - SigSig [Luscent's Insane] | H5: hd2 | J5: no modification one | K5: 1965654 | L5: =IFERROR(__xludf.DUMMYFUNCTION("TRANSPOSE(SPLIT(JOIN("","",MAP(TRANSPOSE(Settings!I2:P2),TRANSPOSE(INDEX(Settings!I3:P12,MATCH(B2,Settings!E3:E12,0))),LAMBDA(mod,n,JOIN("","",ARRAYFORMULA(IF(n=0,"""",mod&SEQUENCE(n))))))),"",""))"),"NM1") -> NM1 | M5: {=MAP(K5:K104,LAMBDA(id,IFNA(IMAGE(MAPDATA(id,"cover_url")),"")))} | N5: =IFNA(MAPDATA(K5:K104,"string_url"),"") -> Sangatsu no Phantasia - Pink Lemonade [Insane] | O5: {=IFNA(MAPDATA_MODDED(K5:K104,{"difficultyrating","bpm","hit_length"},L5:L104),"")} -> 5.08315 | P5: 191 | Q5: 0.0028703704 | R5: {=IFNA(MAPDATA_MODDED(K5:K104,"diff_"&{"size","approach","overall"},L5:L104),"")} -> 4 | S5: 9 | T5: 7 | U5: {=IFNA(MAPDATA(K5:K104,{"creator","beatmap_id"}),"")} -> Chirony | V5: 1965654
B6: https://osu.ppy.sh/beatmapsets/4404#osu/63604 | C6: =IFERROR(__xludf.DUMMYFUNCTION("""COMPUTED_VALUE"""),63604.0) -> 63604 | D6: HD | G6: Comp - Gensou no Satellite [Insane] | I6: c | J6: streams | K6: 1838159 | L6: =IFERROR(__xludf.DUMMYFUNCTION("""COMPUTED_VALUE"""),"NM2") -> NM2 | N6: Thaehan - Doki-Doki [rockstarrzz' Insane] | O6: 5.15169 | P6: 180 | Q6: 0.0011805556 | R6: 3.8 | S6: 9 | T6: 7.5 | U6: Mr HeliX | V6: 1838159
B7: https://osu.ppy.sh/beatmapsets/1270156#osu/2690081 | C7: =IFERROR(__xludf.DUMMYFUNCTION("""COMPUTED_VALUE"""),2690081.0) -> 2690081 | D7: FM | G7: Tenjin Kotone - Darling Dance [UjiMatcha's Insane] | H7: fm1 | J7: alt | K7: 2568756 | L7: =IFERROR(__xludf.DUMMYFUNCTION("""COMPUTED_VALUE"""),"NM3") -> NM3 | N7: Meguro Shoji feat. Lyn - Last Surprise -Scramble- [Expert] | O7: 4.81073 | P7: 123 | Q7: 0.0025115741 | R7: 3.6 | S7: 9.1 | T7: 8 | U7: moph | V7: 2568756
B8: https://osu.ppy.sh/beatmapsets/941246#osu/1965654 | C8: =IFERROR(__xludf.DUMMYFUNCTION("""COMPUTED_VALUE"""),1965654.0) -> 1965654 | D8: NM | E8: play hd3 | G8: Sangatsu no Phantasia - Pink Lemonade [Insane] | H8: nm1 | J8: tech | K8: 3341368 | L8: =IFERROR(__xludf.DUMMYFUNCTION("""COMPUTED_VALUE"""),"NM4") -> NM4 | N8: Nekomata Master+ - squall [0pp's Insane (Tournament Edit)] | O8: 4.59923 | P8: 190 | Q8: 0.0013888889 | R8: 4 | S8: 9.2 | T8: 7 | U8: Kyrian | V8: 3341368
B9: https://osu.ppy.sh/beatmapsets/1507979#osu/3118794 | C9: =IFERROR(__xludf.DUMMYFUNCTION("""COMPUTED_VALUE"""),3118794.0) -> 3118794 | D9: NM | E9: aoi hinami | G9: DIALOGUE+ - Jinsei Easy? [LV.20 Finshie's Insane] | H9: nm3 | J9: speed | K9: 4215637 | L9: =IFERROR(__xludf.DUMMYFUNCTION("""COMPUTED_VALUE"""),"NM5") -> NM5 | N9: the Art of Mankind - Unexisted [Insane] | O9: 5.01002 | P9: 217 | Q9: 0.0021412037 | R9: 4 | S9: 9 | T9: 8 | U9: quantumvortex | V9: 4215637
B10: https://osu.ppy.sh/beatmapsets/1586738#osu/3248255 | C10: =IFERROR(__xludf.DUMMYFUNCTION("""COMPUTED_VALUE"""),3248255.0) -> 3248255 | D10: HR | E10: yillow | G10: NICODE & M2U - Predawn [Mixagji's Insane] | H10: hr3 | J10: funny ar | K10: 3821597 | L10: =IFERROR(__xludf.DUMMYFUNCTION("""COMPUTED_VALUE"""),"NM6") -> NM6 | N10: Franz Ferdinand - This Fffire (TV Size) [enri's iNnnsane] | O10: 4.11281 | P10: 146.5 | Q10: 0.00096064815 | R10: 5 | S10: 6.9 | T10: 6.9 | U10: ninore | V10: 3821597
B11: https://osu.ppy.sh/beatmapsets/776928#osu/1635864 | C11: =IFERROR(__xludf.DUMMYFUNCTION("""COMPUTED_VALUE"""),1635864.0) -> 1635864 | D11: HD | E11: yillow | G11: NIVIRO - Memes (Speed Up Ver.) [moph's Insane] | H11: hd3 | J11: hidden modification one | K11: 2671048 | L11: =IFERROR(__xludf.DUMMYFUNCTION("""COMPUTED_VALUE"""),"HD1") -> HD1 | N11: Usada Pekora - Discommunication Alien [Ayyken's Another] | O11: 5.08091 | P11: 170 | Q11: 0.0023958333 | R11: 4.5 | S11: 9 | T11: 8.5 | U11: Yugu | V11: 2671048
B12: https://osu.ppy.sh/beatmapsets/660630#osu/1404975 | C12: =IFERROR(__xludf.DUMMYFUNCTION("""COMPUTED_VALUE"""),1404975.0) -> 1404975 | D12: HD | E12: yillow | G12: Ocelot - KAEDE [Kalindraz's EX] | H12: hd3 - probably too hard | J12: bursts/stream | K12: 105978 | L12: =IFERROR(__xludf.DUMMYFUNCTION("""COMPUTED_VALUE"""),"HD2") -> HD2 | N12: BRZion - Game Brain [Insane] | O12: 4.51204 | P12: 190 | Q12: 0.001712963 | R12: 4 | S12: 8 | T12: 6 | U12: Zapy | V12: 105978
B13: https://osu.ppy.sh/beatmapsets/737728#osu/1687599 | C13: =IFERROR(__xludf.DUMMYFUNCTION("""COMPUTED_VALUE"""),1687599.0) -> 1687599 | D13: NM | E13: play hd3 | G13: Camellia - Lunatic Rough Party!! [LCFC's HYPER] | H13: nm4 | J13: alt/tech | K13: 1491793 | L13: =IFERROR(__xludf.DUMMYFUNCTION("""COMPUTED_VALUE"""),"HD3") -> HD3 | N13: succducc - me & u [sing's insane] | O13: 4.95782 | P13: 160 | Q13: 0.0018865741 | R13: 4 | S13: 9 | T13: 8 | U13: Nathan | V13: 1491793
B14: https://osu.ppy.sh/b/2072245 | C14: =IFERROR(__xludf.DUMMYFUNCTION("""COMPUTED_VALUE"""),2072245.0) -> 2072245 | D14: NM | E14: lunexia | G14: Fractal Dreamers - Gardens Under A Spring Sky [Insane] | H14: nm2 | J14: simple consistency | K14: 3913591 | L14: =IFERROR(__xludf.DUMMYFUNCTION("""COMPUTED_VALUE"""),"HR1") -> HR1 | N14: kessoku band - Guitar to Kodoku to Aoi Hoshi [kuuti's Insane] | O14: 5.01388 | P14: 193 | Q14: 0.0024305556 | R14: 5.2 | S14: 10 | T14: 10 | U14: Shurelia | V14: 3913591
B15: https://osu.ppy.sh/beatmapsets/749096#osu/1596086 | C15: =IFERROR(__xludf.DUMMYFUNCTION("""COMPUTED_VALUE"""),1596086.0) -> 1596086 | D15: HD | E15: shironai14 | G15: Uinyasu, Occhoko Bunny - Aa Kenran no Yume ga Gotoku (Epsilon Remix) [Dailycare's Insane] | H15: HD1 | J15: yeah | K15: 37750 | L15: =IFERROR(__xludf.DUMMYFUNCTION("""COMPUTED_VALUE"""),"HR2") -> HR2 | N15: Cranky - Luvin' You [Alazy's Another] | O15: 4.74237 | P15: 160 | Q15: 0.0013541667 | R15: 6.5 | S15: 9.8 | T15: 9.8 | U15: avira0922 | V15: 37750
B16: https://osu.ppy.sh/beatmapsets/591635#osu/1251955 | C16: =IFERROR(__xludf.DUMMYFUNCTION("""COMPUTED_VALUE"""),1251955.0) -> 1251955 | D16: HD | E16: shironai14 | G16: M2U - Wicked Fate [LV.10] | H16: HD3 ar9 with hd2 gameplay | J16: alt flow | K16: 3248255 | L16: =IFERROR(__xludf.DUMMYFUNCTION("""COMPUTED_VALUE"""),"HR3") -> HR3 | N16: NICODE & M2U - Predawn [Mixagji's Insane] | O16: 4.87767 | P16: 140 | Q16: 0.0014236111 | R16: 5.2 | S16: 10 | T16: 10 | U16: Hishiro Chizuru | V16: 3248255
B17: https://osu.ppy.sh/beatmapsets/1186066#osu/2472143 | C17: =IFERROR(__xludf.DUMMYFUNCTION("""COMPUTED_VALUE"""),2472143.0) -> 2472143 | D17: FM | E17: shironai14 | G17: Self Deception - Weight Of The World [Insane] | H17: FM1 sliders aim | J17: double time modification one | K17: 674080 | L17: =IFERROR(__xludf.DUMMYFUNCTION("""COMPUTED_VALUE"""),"DT1") -> DT1 | N17: Reol - Asymmetry [pk's Hard] | O17: 5.0485 | P17: 276 | Q17: 0.0019135802 | R17: 4 | S17: 9.6666667 | T17: 8.4166667 | U17: Gaia | V17: 674080
B18: https://osu.ppy.sh/beatmapsets/1496234#osu/3221246 | C18: =IFERROR(__xludf.DUMMYFUNCTION("""COMPUTED_VALUE"""),3221246.0) -> 3221246 | D18: NM | E18: shironai14 | G18: tokiwa - wasurena feat. Sennzai [remembrance] | H18: NM4 banger song | J18: speed | K18: 3299370 | L18: =IFERROR(__xludf.DUMMYFUNCTION("""COMPUTED_VALUE"""),"DT2") -> DT2 | N18: -45 - System Sun [Hard] | O18: 4.96093 | P18: 228 | Q18: 0.0016975309 | R18: 4 | S18: 9.6666667 | T18: 9.0833333 | U18: Lasse | V18: 3299370
B19: https://osu.ppy.sh/beatmapsets/1855321#osu/3822120 | C19: =IFERROR(__xludf.DUMMYFUNCTION("""COMPUTED_VALUE"""),3822120.0) -> 3822120 | D19: HR | E19: shironai14 | G19: WAGAMAMA RAKIA - GR4VITY G4ME [LOG OFF B4NTER'S INS4NE] | H19: HR1 a bit speed with aim | J19: slider stuff | K19: 3822599 | L19: =IFERROR(__xludf.DUMMYFUNCTION("""COMPUTED_VALUE"""),"DT3") -> DT3 | N19: Nekomata Master+ - chaos eater -IIDX edition- [HARD] | O19: 4.91921 | P19: 315 | Q19: 0.00083333333 | R19: 3.5 | S19: 9.6666667 | T19: 8.4166667 | U19: pocket- | V19: 3822599
B20: https://osu.ppy.sh/beatmapsets/12469#osu/48215 | C20: =IFERROR(__xludf.DUMMYFUNCTION("""COMPUTED_VALUE"""),48215.0) -> 48215 | D20: HR | E20: shironai14 | G20: onoken - Quinine -A2D SIDE- [Lunatic] | H20: HR2 | J20: free modification one | K20: 3274886 | L20: =IFERROR(__xludf.DUMMYFUNCTION("""COMPUTED_VALUE"""),"FM1") -> FM1 | N20: Two Door Cinema Club - Cigarettes in the Theatre [Insane] | O20: 4.70593 | P20: 169 | Q20: 0.0021875 | R20: 4.2 | S20: 8.7 | T20: 8.2 | U20: entsetzen | V20: 3274886
B21: https://osu.ppy.sh/beatmapsets/1695872#osu/3616425 | C21: =IFERROR(__xludf.DUMMYFUNCTION("""COMPUTED_VALUE"""),3616425.0) -> 3616425 | D21: NM | E21: shironai14 | G21: BABYMETAL - Arkadia [Collab Expert] | H21: NM5 the map have 38 sec for skip in the beginning | J21: anti mod | K21: 3804111 | L21: =IFERROR(__xludf.DUMMYFUNCTION("""COMPUTED_VALUE"""),"FM2") -> FM2 | N21: Hiiragi Magnetite - Marshall Maximizer feat. KAFU [Hyper] | O21: 4.323 | P21: 190 | Q21: 0.0017824074 | R21: 5 | S21: 8 | T21: 7 | U21: Ixcors | V21: 3804111
B22: https://osu.ppy.sh/beatmapsets/1215814#osu/2532230 | C22: =IFERROR(__xludf.DUMMYFUNCTION("""COMPUTED_VALUE"""),2532230.0) -> 2532230 | D22: NM | E22: shironai14 | G22: BLANKFIELD - THE WORLD REVOLVING [Insane] | H22: more short nm5 | J22: hype tb | K22: 577517 | L22: =IFERROR(__xludf.DUMMYFUNCTION("""COMPUTED_VALUE"""),"TB1") -> TB1 | N22: Halozy - Genryuu Kaiko [Melody of Sanzu] | O22: 5.38366 | P22: 173 | Q22: 0.0034722222 | R22: 4 | S22: 9.2 | T22: 8 | U22: Mira-san | V22: 577517
B23: https://osu.ppy.sh/beatmapsets/1413965#osu/2986144 | C23: =IFERROR(__xludf.DUMMYFUNCTION("""COMPUTED_VALUE"""),2986144.0) -> 2986144 | D23: NM | E23: shironai14 | G23: Jibaku Shounen Band - No.7 [Stack's Insane] | H23: NM1 or HD1 second option
B24: https://osu.ppy.sh/beatmapsets/932901#osu/1975970 | C24: =IFERROR(__xludf.DUMMYFUNCTION("""COMPUTED_VALUE"""),1975970.0) -> 1975970 | D24: HD | E24: shironai14 | G24: Mili - Ga1ahad and Scientific Witchery [KKip's Insane] | H24: HD3 tapping
B25: https://osu.ppy.sh/beatmapsets/1847288#osu/3912466 | C25: =IFERROR(__xludf.DUMMYFUNCTION("""COMPUTED_VALUE"""),3912466.0) -> 3912466 | D25: NM | E25: shironai14 | G25: Mori Calliope - MERA MERA [frozz's Insane] | H25: vtuber nm3
B26: https://osu.ppy.sh/beatmapsets/756815#osu/1600995 | C26: =IFERROR(__xludf.DUMMYFUNCTION("""COMPUTED_VALUE"""),1600995.0) -> 1600995 | D26: NM | E26: shironai14 | G26: PUP - DVP [Lasse's Insane] | H26: NM3
B27: https://osu.ppy.sh/beatmaps/2800663 | C27: =IFERROR(__xludf.DUMMYFUNCTION("""COMPUTED_VALUE"""),2800663.0) -> 2800663 | D27: NM | E27: shironai14 | G27: Maison book girl - snow irony_ [deppy's insane_] | H27: NM6 NO
B28: https://osu.ppy.sh/beatmapsets/31480#osu/103476 | C28: =IFERROR(__xludf.DUMMYFUNCTION("""COMPUTED_VALUE"""),103476.0) -> 103476 | D28: HD | G28: Yuma Mizonokuchi - akasha-simulater [Insane] | H28: HD2
B29: https://osu.ppy.sh/beatmapsets/1880072#osu/3870932 | C29: =IFERROR(__xludf.DUMMYFUNCTION("""COMPUTED_VALUE"""),3870932.0) -> 3870932 | D29: NM | G29: Kikuo - Yousei no Kiri [Insane] | H29: nm6
D30: NM | H30: nm6
B31: https://osu.ppy.sh/beatmapsets/1888886#osu/3913591 | C31: =IFERROR(__xludf.DUMMYFUNCTION("""COMPUTED_VALUE"""),3913591.0) -> 3913591 | D31: HR | E31: play hd3 | G31: kessoku band - Guitar to Kodoku to Aoi Hoshi [kuuti's Insane]
B32: https://osu.ppy.sh/beatmapsets/292077#osu/674080 | C32: =IFERROR(__xludf.DUMMYFUNCTION("""COMPUTED_VALUE"""),674080.0) -> 674080 | D32: DT | E32: play hd3 | G32: Reol - Asymmetry [pk's Hard]
B33: https://osu.ppy.sh/beatmapsets/1207286#osu/2514122 | C33: =IFERROR(__xludf.DUMMYFUNCTION("""COMPUTED_VALUE"""),2514122.0) -> 2514122 | D33: FM | G33: Wagakki Band - Kagerou Days [Ducky-'s Insane]
B34: https://osu.ppy.sh/beatmapsets/1668789#osu/3407970 | C34: =IFERROR(__xludf.DUMMYFUNCTION("""COMPUTED_VALUE"""),3407970.0) -> 3407970 | D34: HR | G34: City Girl - L2M (feat. Kelsey Kuan) [Niva's Insane]
B35: https://osu.ppy.sh/beatmapsets/1415788#osu/2917786 | C35: =IFERROR(__xludf.DUMMYFUNCTION("""COMPUTED_VALUE"""),2917786.0) -> 2917786 | D35: HR | G35: Cro - Wie ich bin [Trust]
B36: https://osu.ppy.sh/beatmapsets/1181343#osu/2671048 | C36: =IFERROR(__xludf.DUMMYFUNCTION("""COMPUTED_VALUE"""),2671048.0) -> 2671048 | D36: HD | E36: play hd3 | G36: Usada Pekora - Discommunication Alien [Ayyken's Another]
B37: https://osu.ppy.sh/beatmapsets/20817#osu/74778 | C37: =IFERROR(__xludf.DUMMYFUNCTION("""COMPUTED_VALUE"""),74778.0) -> 74778 | D37: FM | G37: Megpoid GUMI - Mozaik Role [epa-]
B38: https://osu.ppy.sh/beatmapsets/1682134#osu/3530469 | C38: =IFERROR(__xludf.DUMMYFUNCTION("""COMPUTED_VALUE"""),3530469.0) -> 3530469 | D38: HD | G38: SHK - Halloween Party [Heilia's Insane]
B39: https://osu.ppy.sh/beatmapsets/699749#osu/1491793 | C39: =IFERROR(__xludf.DUMMYFUNCTION("""COMPUTED_VALUE"""),1491793.0) -> 1491793 | D39: HD | E39: play hd3 | G39: succducc - me & u [sing's insane]
B40: https://osu.ppy.sh/beatmapsets/1574603#osu/3291796 | C40: =IFERROR(__xludf.DUMMYFUNCTION("""COMPUTED_VALUE"""),3291796.0) -> 3291796 | D40: NM | G40: VeetaCrush - Mole [Kyutei's Insane]
B41: https://osu.ppy.sh/beatmapsets/1616029#osu/3299370 | C41: =IFERROR(__xludf.DUMMYFUNCTION("""COMPUTED_VALUE"""),3299370.0) -> 3299370 | D41: DT | E41: play hd3 | G41: -45 - System Sun [Hard]
B42: https://osu.ppy.sh/beatmapsets/1248923#osu/3822599 | C42: =IFERROR(__xludf.DUMMYFUNCTION("""COMPUTED_VALUE"""),3822599.0) -> 3822599 | D42: DT | E42: play hd3 | G42: Nekomata Master+ - chaos eater -IIDX edition- [HARD]
B43: https://osu.ppy.sh/beatmapsets/352570#osu/785982 | C43: =IFERROR(__xludf.DUMMYFUNCTION("""COMPUTED_VALUE"""),785982.0) -> 785982 | D43: FM | E43: yillow | G43: beatMARIO - Night of Knights [N a s y a's Insane]
B44: https://osu.ppy.sh/beatmapsets/156235#osu/382887 | C44: =IFERROR(__xludf.DUMMYFUNCTION("""COMPUTED_VALUE"""),382887.0) -> 382887 | D44: NM | E44: yillow | G44: Yooh - snow storm -euphoria- [EXHAUST]
B45: https://osu.ppy.sh/beatmapsets/2023886#osu/4215637 | C45: =IFERROR(__xludf.DUMMYFUNCTION("""COMPUTED_VALUE"""),4215637.0) -> 4215637 | D45: NM | E45: yillow | G45: the Art of Mankind - Unexisted [Insane]
B46: https://osu.ppy.sh/beatmapsets/1089084#osu/2277128 | C46: =IFERROR(__xludf.DUMMYFUNCTION("""COMPUTED_VALUE"""),2277128.0) -> 2277128 | D46: HD | E46: play hd3 | G46: Kola Kid - timer [Insane]
B47: https://osu.ppy.sh/beatmapsets/1851405#osu/3804111 | C47: =IFERROR(__xludf.DUMMYFUNCTION("""COMPUTED_VALUE"""),3804111.0) -> 3804111 | D47: FM | E47: play hd3 | G47: Hiiragi Magnetite - Marshall Maximizer feat. KAFU [Hyper]
B48: https://osu.ppy.sh/beatmapsets/992847#osu/2076261 | C48: =IFERROR(__xludf.DUMMYFUNCTION("""COMPUTED_VALUE"""),2076261.0) -> 2076261 | D48: TB | G48: RIOT - Overkill [Noble]
B49: https://osu.ppy.sh/beatmapsets/519054#osu/1838159 | C49: =IFERROR(__xludf.DUMMYFUNCTION("""COMPUTED_VALUE"""),1838159.0) -> 1838159 | D49: NM | E49: lunexia | G49: Thaehan - Doki-Doki [rockstarrzz' Insane]
D50: NM
B51: https://osu.ppy.sh/beatmapsets/251437#osu/577517 | C51: =IFERROR(__xludf.DUMMYFUNCTION("""COMPUTED_VALUE"""),577517.0) -> 577517 | D51: TB | G51: Halozy - Genryuu Kaiko [Melody of Sanzu]
B52: https://osu.ppy.sh/beatmapsets/1178471#osu/2568756 | C52: =IFERROR(__xludf.DUMMYFUNCTION("""COMPUTED_VALUE"""),2568756.0) -> 2568756 | D52: NM | G52: Meguro Shoji feat. Lyn - Last Surprise -Scramble- [Expert]
B53: https://osu.ppy.sh/beatmapsets/1441316#osu/3341368 | C53: =IFERROR(__xludf.DUMMYFUNCTION("""COMPUTED_VALUE"""),3341368.0) -> 3341368 | D53: NM | G53: Nekomata Master+ - squall [0pp's Insane (Tournament Edit)]
B54: https://osu.ppy.sh/beatmapsets/1598238#osu/3274886 | C54: =IFERROR(__xludf.DUMMYFUNCTION("""COMPUTED_VALUE"""),3274886.0) -> 3274886 | D54: FM | G54: Two Door Cinema Club - Cigarettes in the Theatre [Insane]
B55: https://osu.ppy.sh/beatmapsets/20817#osu/74779 | C55: =IFERROR(__xludf.DUMMYFUNCTION("""COMPUTED_VALUE"""),74779.0) -> 74779 | D55: HR | G55: Megpoid GUMI - Mozaik Role [PoLKs]
B56: https://osu.ppy.sh/beatmapsets/8923#osu/37750 | C56: =IFERROR(__xludf.DUMMYFUNCTION("""COMPUTED_VALUE"""),37750.0) -> 37750 | D56: HR | G56: Cranky - Luvin' You [Alazy's Another]
B57: https://osu.ppy.sh/beatmapsets/31224#osu/105978 | C57: =IFERROR(__xludf.DUMMYFUNCTION("""COMPUTED_VALUE"""),105978.0) -> 105978 | D57: HD | G57: BRZion - Game Brain [Insane]
B58: https://osu.ppy.sh/beatmapsets/1857926#osu/3821597 | C58: =IFERROR(__xludf.DUMMYFUNCTION("""COMPUTED_VALUE"""),3821597.0) -> 3821597 | D58: NM | G58: Franz Ferdinand - This Fffire (TV Size) [enri's iNnnsane]

Sheet SF
B2: Semifinals | C2: Best of | D2: =IFERROR(VLOOKUP(B2,Settings!E3:H12,3,0),"") -> 11 | E2: Bans | F2: =IFERROR(VLOOKUP(B2,Settings!E3:H12,4,0),"") -> 2
B3: Suggestions | J3: Pool Assembly
B4: Map Link | C4: ID | D4: Mod | E4: Suggestor | F4: Map | H4: Notes | J4: Note | K4: ID | L4: Mod | M4: Map | O4: SR | P4: BPM | Q4: Length | R4: CS | S4: AR | T4: OD | U4: Mapper | V4: ID
B5: https://osu.ppy.sh/beatmapsets/663255#osu/1405094 | C5: =IFERROR(__xludf.DUMMYFUNCTION("ArrayFormula(IFERROR(VALUE(REGEXEXTRACT(B5:B104&"""",""\d+$""))))"),1405094.0) -> 1405094 | D5: HR | E5: yillow | F5: {=MAP(C5:C104,LAMBDA(id,IFNA(IMAGE(MAPDATA(id,"cover_url")),"")))} | G5: {=IFNA(HYPERLINK(VLOOKUP(C5:C104,'_api'!B3:BC104,MATCH("url",'_api'!B2:W2,0),0),VLOOKUP(C5:C104,'_api'!B3:BC104,MATCH("string",'_api'!B2:W2,0),0)),"")} -> Camellia - Routing [Another] | H5: hr3 | J5: nanahira | K5: 1717844 | L5: =IFERROR(__xludf.DUMMYFUNCTION("TRANSPOSE(SPLIT(JOIN("","",MAP(TRANSPOSE(Settings!I2:P2),TRANSPOSE(INDEX(Settings!I3:P12,MATCH(B2,Settings!E3:E12,0))),LAMBDA(mod,n,JOIN("","",ARRAYFORMULA(IF(n=0,"""",mod&SEQUENCE(n))))))),"",""))"),"NM1") -> NM1 | M5: {=MAP(K5:K104,LAMBDA(id,IFNA(IMAGE(MAPDATA(id,"cover_url")),"")))} | N5: =IFNA(MAPDATA(K5:K104,"string_url"),"") -> t+pazolite - Party in the HOLLOWood feat. Nanahira [INSane] | O5: {=IFNA(MAPDATA_MODDED(K5:K104,{"difficultyrating","bpm","hit_length"},L5:L104),"")} -> 5.37201 | P5: 178 | Q5: 0.0026041667 | R5: {=IFNA(MAPDATA_MODDED(K5:K104,"diff_"&{"size","approach","overall"},L5:L104),"")} -> 4 | S5: 9 | T5: 8 | U5: {=IFNA(MAPDATA(K5:K104,{"creator","beatmap_id"}),"")} -> eiri- | V5: 1717844
B6: https://osu.ppy.sh/beatmapsets/1763440#osu/3841174 | C6: =IFERROR(__xludf.DUMMYFUNCTION("""COMPUTED_VALUE"""),3841174.0) -> 3841174 | D6: HR | E6: play hd3 | G6: Pmarusama. - S'il vous President [Teages's Insane] | I6: c | J6: long streams | K6: 3656173 | L6: =IFERROR(__xludf.DUMMYFUNCTION("""COMPUTED_VALUE"""),"NM2") -> NM2 | N6: GIVEON - Favourite Mistake [Halogenix Edit] [Insane] | O6: 5.19532 | P6: 172 | Q6: 0.0015740741 | R6: 4 | S6: 9.1 | T6: 8 | U6: quantumvortex | V6: 3656173
B7: https://osu.ppy.sh/beatmapsets/315299#osu/703042 | C7: =IFERROR(__xludf.DUMMYFUNCTION("""COMPUTED_VALUE"""),703042.0) -> 703042 | D7: HR | E7: yillow | G7: Rita - Dream Walker [Quilt's Insane] | H7: hr1 - consistency + streams | J7: aim alt | K7: 2715749 | L7: =IFERROR(__xludf.DUMMYFUNCTION("""COMPUTED_VALUE"""),"NM3") -> NM3 | N7: ALI - Wild Side [Squilly's Insane] | O7: 5.03898 | P7: 134 | Q7: 0.0016550926 | R7: 3 | S7: 9.2 | T7: 8 | U7: fieryrage | V7: 2715749
B8: 2514122 | C8: =IFERROR(__xludf.DUMMYFUNCTION("""COMPUTED_VALUE"""),2514122.0) -> 2514122 | D8: FM | E8: play hd3 | G8: Wagakki Band - Kagerou Days [Ducky-'s Insane] | J8: long sliders | K8: 3291796 | L8: =IFERROR(__xludf.DUMMYFUNCTION("""COMPUTED_VALUE"""),"NM4") -> NM4 | N8: VeetaCrush - Mole [Kyutei's Insane] | O8: 4.70195 | P8: 172 | Q8: 0.0015625 | R8: 3.8 | S8: 9 | T8: 8.6 | U8: JeZag | V8: 3291796
B9: https://osu.ppy.sh/beatmapsets/1659194#osu/3399446 | C9: =IFERROR(__xludf.DUMMYFUNCTION("""COMPUTED_VALUE"""),3399446.0) -> 3399446 | D9: HD | E9: yillow | G9: Yooh - Heracles [Another] | H9: hd3 | J9: speed | K9: 3187491 | L9: =IFERROR(__xludf.DUMMYFUNCTION("""COMPUTED_VALUE"""),"NM5") -> NM5 | N9: Camellia - Killerbeast [Spiritual] | O9: 5.1866 | P9: 220 | Q9: 0.0024537037 | R9: 3.8 | S9: 9.2 | T9: 8 | U9: Subokuu | V9: 3187491
B10: https://osu.ppy.sh/beatmapsets/1140943#osu/2383229 | C10: =IFERROR(__xludf.DUMMYFUNCTION("""COMPUTED_VALUE"""),2383229.0) -> 2383229 | D10: HD | E10: yillow | G10: aran - Sunny After Rain [feat. Kanata.N] [Rainbow] | H10: hd3 | J10: ar7 stop and go | K10: 3990086 | L10: =IFERROR(__xludf.DUMMYFUNCTION("""COMPUTED_VALUE"""),"NM6") -> NM6 | N10: Kai - Junk Lady [Deppy and Wanpachi's Insane] | O10: 4.56568 | P10: 174 | Q10: 0.0013657407 | R10: 3.8 | S10: 7 | T10: 7 | U10: Deppyforce | V10: 3990086
B11: https://osu.ppy.sh/beatmapsets/927758#osu/1972425 | C11: =IFERROR(__xludf.DUMMYFUNCTION("""COMPUTED_VALUE"""),1972425.0) -> 1972425 | D11: HD | E11: yillow | G11: Aso Natsuko - Perfect-area complete! [Asuka_-'s Insane] | H11: hd1 | J11: anti aim | K11: 1972425 | L11: =IFERROR(__xludf.DUMMYFUNCTION("""COMPUTED_VALUE"""),"HD1") -> HD1 | N11: Aso Natsuko - Perfect-area complete! [Asuka_-'s Insane] | O11: 5.21311 | P11: 183 | Q11: 0.0024537037 | R11: 3.7 | S11: 9.3 | T11: 8 | U11: gary00737 | V11: 1972425
B12: https://osu.ppy.sh/beatmapsets/1574603#osu/3291796 | C12: =IFERROR(__xludf.DUMMYFUNCTION("""COMPUTED_VALUE"""),3291796.0) -> 3291796 | D12: NM | G12: VeetaCrush - Mole [Kyutei's Insane] | H12: nm4 | J12: ar8 | K12: 2277128 | L12: =IFERROR(__xludf.DUMMYFUNCTION("""COMPUTED_VALUE"""),"HD2") -> HD2 | N12: Kola Kid - timer [Insane] | O12: 4.71265 | P12: 180 | Q12: 0.0013657407 | R12: 4 | S12: 8 | T12: 7 | U12: Mirash | V12: 2277128
B13: https://osu.ppy.sh/beatmapsets/1785134#osu/3656173 | C13: =IFERROR(__xludf.DUMMYFUNCTION("""COMPUTED_VALUE"""),3656173.0) -> 3656173 | D13: NM | G13: GIVEON - Favourite Mistake [Halogenix Edit] [Insane] | J13: light tech | K13: 2044890 | L13: =IFERROR(__xludf.DUMMYFUNCTION("""COMPUTED_VALUE"""),"HD3") -> HD3 | N13: YUC'e - POISON -KO3 Remix- [Insane] | O13: 5.03191 | P13: 170 | Q13: 0.0022222222 | R13: 3.8 | S13: 9.1 | T13: 8 | U13: JrSzZ | V13: 2044890
B14: https://osu.ppy.sh/beatmapsets/1436167#osu/2992124 | C14: =IFERROR(__xludf.DUMMYFUNCTION("""COMPUTED_VALUE"""),2992124.0) -> 2992124 | D14: NM | G14: BPM15Q - Go Shoot! [Melo's Insane] | J14: slider consistency | K14: 3454421 | L14: =IFERROR(__xludf.DUMMYFUNCTION("""COMPUTED_VALUE"""),"HR1") -> HR1 | N14: Harumaki Gohan feat. Hatsune Miku - Hotaru wa Inakatta [Kuse's Insane] | O14: 5.19533 | P14: 206 | Q14: 0.0023148148 | R14: 5.2 | S14: 10 | T14: 10 | U14: Irin | V14: 3454421
B15: https://osu.ppy.sh/beatmapsets/1871920#osu/3986899 | C15: =IFERROR(__xludf.DUMMYFUNCTION("""COMPUTED_VALUE"""),3986899.0) -> 3986899 | D15: NM | G15: ZAQ - Dance In The Game [Light's Insane] | J15: 1/3rd cs6.5 | K15: 2917786 | L15: =IFERROR(__xludf.DUMMYFUNCTION("""COMPUTED_VALUE"""),"HR2") -> HR2 | N15: Cro - Wie ich bin [Trust] | O15: 4.85907 | P15: 130 | Q15: 0.0019791667 | R15: 6.5 | S15: 10 | T15: 10 | U15: Cacturne | V15: 2917786
B16: https://osu.ppy.sh/beatmapsets/1030737#osu/2200110 | C16: =IFERROR(__xludf.DUMMYFUNCTION("""COMPUTED_VALUE"""),2200110.0) -> 2200110 | D16: NM | G16: Irreversible Mechanism - Cold Winds [Insane] | J16: alt | K16: 1405094 | L16: =IFERROR(__xludf.DUMMYFUNCTION("""COMPUTED_VALUE"""),"HR3") -> HR3 | N16: Camellia - Routing [Another] | O16: 5.0835 | P16: 144 | Q16: 0.0012731481 | R16: 4.55 | S16: 10 | T16: 10 | U16: Mir | V16: 1405094
B17: https://osu.ppy.sh/beatmapsets/1901819#osu/3990086 | C17: =IFERROR(__xludf.DUMMYFUNCTION("""COMPUTED_VALUE"""),3990086.0) -> 3990086 | D17: NM | G17: Kai - Junk Lady [Deppy and Wanpachi's Insane] | J17: consistency | K17: 1592512 | L17: =IFERROR(__xludf.DUMMYFUNCTION("""COMPUTED_VALUE"""),"DT1") -> DT1 | N17: 96neko - Primitive emotion [Hard] | O17: 5.31524 | P17: 285 | Q17: 0.0016126543 | R17: 4 | S17: 9.6666667 | T17: 8.75 | U17: Lasse | V17: 1592512
B18: https://osu.ppy.sh/beatmapsets/1283387#osu/2666261 | C18: =IFERROR(__xludf.DUMMYFUNCTION("""COMPUTED_VALUE"""),2666261.0) -> 2666261 | D18: HD | G18: Akatsuki Records - KARMANATIONS [Insane] | J18: bursts | K18: 2388648 | L18: =IFERROR(__xludf.DUMMYFUNCTION("""COMPUTED_VALUE"""),"DT2") -> DT2 | N18: umu. - Dareka no Shinzou ni Nareta Nara [Hard] | O18: 5.127 | P18: 217.5 | Q18: 0.0016975309 | R18: 3.8 | S18: 9.6666667 | T18: 9.0833333 | U18: xbopost | V18: 2388648
B19: https://osu.ppy.sh/beatmapsets/25802#osu/87369 | C19: =IFERROR(__xludf.DUMMYFUNCTION("""COMPUTED_VALUE"""),87369.0) -> 87369 | D19: HD | G19: Hatsune Miku - Netoge Haijin Sprechchor [Insane] | J19: finger control | K19: 3819183 | L19: =IFERROR(__xludf.DUMMYFUNCTION("""COMPUTED_VALUE"""),"DT3") -> DT3 | N19: AAAA + Umeboshi Chazuke - Cait Sith [Setu's Hard] | O19: 5.16896 | P19: 255 | Q19: 0.0013503086 | R19: 3.5 | S19: 9.6666667 | T19: 8.4166667 | U19: bob | V19: 3819183
B20: https://osu.ppy.sh/beatmapsets/295225#osu/667685 | C20: =IFERROR(__xludf.DUMMYFUNCTION("""COMPUTED_VALUE"""),667685.0) -> 667685 | D20: HR | G20: Reol - Plus Danshi ver Reol [Lunatic] | J20: perfect stacks | K20: 2514122 | L20: =IFERROR(__xludf.DUMMYFUNCTION("""COMPUTED_VALUE"""),"FM1") -> FM1 | N20: Wagakki Band - Kagerou Days [Ducky-'s Insane] | O20: 4.95233 | P20: 200 | Q20: 0.0025810185 | R20: 3 | S20: 9 | T20: 8 | U20: IOException | V20: 2514122
B21: https://osu.ppy.sh/beatmapsets/853045#osu/1782851 | C21: =IFERROR(__xludf.DUMMYFUNCTION("""COMPUTED_VALUE"""),1782851.0) -> 1782851 | D21: HR | G21: Kajiura Yuki - Pugna cum maga [Insane] | J21: finger control | K21: 28366 | L21: =IFERROR(__xludf.DUMMYFUNCTION("""COMPUTED_VALUE"""),"FM2") -> FM2 | N21: Brandy - Cross Time !! [DJPop Mix] | O21: 4.71486 | P21: 160 | Q21: 0.0016203704 | R21: 5 | S21: 8 | T21: 8 | U21: buraimaster1234 | V21: 28366
B22: https://osu.ppy.sh/beatmapsets/755512#osu/1592512 | C22: =IFERROR(__xludf.DUMMYFUNCTION("""COMPUTED_VALUE"""),1592512.0) -> 1592512 | D22: DT | G22: 96neko - Primitive emotion [Hard] | J22: banger | K22: 1248147 | L22: =IFERROR(__xludf.DUMMYFUNCTION("""COMPUTED_VALUE"""),"TB1") -> TB1 | N22: Camellia - EXiT this Earths Atomosphere [Astral] | O22: 5.47932 | P22: 170 | Q22: 0.0035648148 | R22: 4 | S22: 9.4 | T22: 8 | U22: DWShin | V22: 1248147
B23: https://osu.ppy.sh/beatmapsets/1848926#osu/3819183 | C23: =IFERROR(__xludf.DUMMYFUNCTION("""COMPUTED_VALUE"""),3819183.0) -> 3819183 | D23: DT | G23: AAAA + Umeboshi Chazuke - Cait Sith [Setu's Hard]
B24: https://osu.ppy.sh/beatmapsets/1272023#osu/2643263 | C24: =IFERROR(__xludf.DUMMYFUNCTION("""COMPUTED_VALUE"""),2643263.0) -> 2643263 | D24: FM | G24: Shawn Wasabi - LEMONS feat. kennedi [lemonade]
B25: https://osu.ppy.sh/beatmapsets/663220#osu/1403845 | C25: =IFERROR(__xludf.DUMMYFUNCTION("""COMPUTED_VALUE"""),1403845.0) -> 1403845 | G25: HyperJuice - City Lights feat. EVO+, Jinmenusagi (Zekk Remix) [C00L & Yamicchi's Another]
B26: https://osu.ppy.sh/beatmapsets/1391326#osu/2872861 | C26: =IFERROR(__xludf.DUMMYFUNCTION("""COMPUTED_VALUE"""),2872861.0) -> 2872861 | D26: HD | G26: Rude-a - Paradise [Lobelia's Insane]
B27: https://osu.ppy.sh/beatmapsets/1415788#osu/2917786 | C27: =IFERROR(__xludf.DUMMYFUNCTION("""COMPUTED_VALUE"""),2917786.0) -> 2917786 | D27: HR | G27: Cro - Wie ich bin [Trust]
B28: https://osu.ppy.sh/beatmapsets/1109683#osu/2715749 | C28: =IFERROR(__xludf.DUMMYFUNCTION("""COMPUTED_VALUE"""),2715749.0) -> 2715749 | D28: NM | G28: ALI - Wild Side [Squilly's Insane]
B29: https://osu.ppy.sh/beatmapsets/967021#osu/2044890 | C29: =IFERROR(__xludf.DUMMYFUNCTION("""COMPUTED_VALUE"""),2044890.0) -> 2044890 | D29: HD | G29: YUC'e - POISON -KO3 Remix- [Insane]
B30: https://osu.ppy.sh/beatmapsets/1676960#osu/3454421 | C30: =IFERROR(__xludf.DUMMYFUNCTION("""COMPUTED_VALUE"""),3454421.0) -> 3454421 | D30: HR | G30: Harumaki Gohan feat. Hatsune Miku - Hotaru wa Inakatta [Kuse's Insane]
B31: https://osu.ppy.sh/beatmapsets/47124#osu/152180 | C31: =IFERROR(__xludf.DUMMYFUNCTION("""COMPUTED_VALUE"""),152180.0) -> 152180 | D31: HD | G31: ALiCE'S EMOTiON - LUNA [Lunatic]
B32: https://osu.ppy.sh/beatmapsets/1173192#osu/2446833 | C32: =IFERROR(__xludf.DUMMYFUNCTION("""COMPUTED_VALUE"""),2446833.0) -> 2446833 | D32: HR | G32: Ricky Montgomery - This December [Stalker]
B33: https://osu.ppy.sh/beatmapsets/1399793#osu/2942900 | C33: =IFERROR(__xludf.DUMMYFUNCTION("""COMPUTED_VALUE"""),2942900.0) -> 2942900 | D33: DT | G33: Hoshimachi Suisei with Hololive Fantasy - Saga Jihen [Mocaotic's Hard]
B34: https://osu.ppy.sh/beatmapsets/1760668#osu/4133990 | C34: =IFERROR(__xludf.DUMMYFUNCTION("""COMPUTED_VALUE"""),4133990.0) -> 4133990 | D34: DT | G34: lapix - Day by Day feat. Nicole Curry [Hard]
B35: https://osu.ppy.sh/beatmapsets/1313297#osu/2758832 | C35: =IFERROR(__xludf.DUMMYFUNCTION("""COMPUTED_VALUE"""),2758832.0) -> 2758832 | D35: DT | G35: the peggies - Neverland [Hard]
B36: https://osu.ppy.sh/beatmapsets/828940#osu/1738876 | C36: =IFERROR(__xludf.DUMMYFUNCTION("""COMPUTED_VALUE"""),1738876.0) -> 1738876 | D36: HD | G36: ZUN - A Sacred Lot [Oni] | H36: HD2
B37: https://osu.ppy.sh/beatmapsets/5918#osu/28366 | C37: =IFERROR(__xludf.DUMMYFUNCTION("""COMPUTED_VALUE"""),28366.0) -> 28366 | D37: FM | G37: Brandy - Cross Time !! [DJPop Mix]
B38: https://osu.ppy.sh/beatmapsets/1641533#osu/3350322 | C38: =IFERROR(__xludf.DUMMYFUNCTION("""COMPUTED_VALUE"""),3350322.0) -> 3350322 | D38: HD | G38: Down - Luscent [Lunatic]
B39: https://osu.ppy.sh/beatmapsets/1621130#osu/3309941 | C39: =IFERROR(__xludf.DUMMYFUNCTION("""COMPUTED_VALUE"""),3309941.0) -> 3309941 | D39: HD | G39: Dio feat. Sef - Aye [Lesjuh's Aye!!] | H39: if hd1 is repooled
B40: https://osu.ppy.sh/beatmapsets/1098181#osu/2388648 | C40: =IFERROR(__xludf.DUMMYFUNCTION("""COMPUTED_VALUE"""),2388648.0) -> 2388648 | D40: DT | G40: umu. - Dareka no Shinzou ni Nareta Nara [Hard]
B41: https://osu.ppy.sh/beatmapsets/299454#osu/722224 | C41: =IFERROR(__xludf.DUMMYFUNCTION("""COMPUTED_VALUE"""),722224.0) -> 722224 | D41: TB | G41: Sawai Miku - Colorful. (Asterisk DnB Remix) [Megumi]
B42: https://osu.ppy.sh/beatmapsets/1349093#osu/3187491 | C42: =IFERROR(__xludf.DUMMYFUNCTION("""COMPUTED_VALUE"""),3187491.0) -> 3187491 | D42: NM | G42: Camellia - Killerbeast [Spiritual]
B43: https://osu.ppy.sh/beatmapsets/31224#osu/105978 | C43: =IFERROR(__xludf.DUMMYFUNCTION("""COMPUTED_VALUE"""),105978.0) -> 105978 | D43: HD | G43: BRZion - Game Brain [Insane]
B44: https://osu.ppy.sh/beatmapsets/25392#osu/86079 | C44: =IFERROR(__xludf.DUMMYFUNCTION("""COMPUTED_VALUE"""),86079.0) -> 86079 | G44: Pastry - Goblin Girl [Lunatic]
B45: https://osu.ppy.sh/beatmapsets/1089084#osu/2277128 | C45: =IFERROR(__xludf.DUMMYFUNCTION("""COMPUTED_VALUE"""),2277128.0) -> 2277128 | D45: HD | G45: Kola Kid - timer [Insane]
B46: https://osu.ppy.sh/beatmapsets/819349#osu/1717844 | C46: =IFERROR(__xludf.DUMMYFUNCTION("""COMPUTED_VALUE"""),1717844.0) -> 1717844 | D46: NM | E46: yillow | G46: t+pazolite - Party in the HOLLOWood feat. Nanahira [INSane]
B47: https://osu.ppy.sh/beatmapsets/589697#osu/1248147 | C47: =IFERROR(__xludf.DUMMYFUNCTION("""COMPUTED_VALUE"""),1248147.0) -> 1248147 | D47: TB | E47: yillow | G47: Camellia - EXiT this Earths Atomosphere [Astral]

Sheet F
B2: Finals | C2: Best of | D2: =IFERROR(VLOOKUP(B2,Settings!E3:H12,3,0),"") -> 13 | E2: Bans | F2: =IFERROR(VLOOKUP(B2,Settings!E3:H12,4,0),"") -> 2
B3: Suggestions | J3: Pool Assembly
B4: Map Link | C4: ID | D4: Mod | E4: Suggestor | F4: Map | H4: Notes | J4: Note | K4: ID | L4: Mod | M4: Map | O4: SR | P4: BPM | Q4: Length | R4: CS | S4: AR | T4: OD | U4: Mapper | V4: ID
B5: https://osu.ppy.sh/beatmapsets/286414#osu/646609 | C5: =IFERROR(__xludf.DUMMYFUNCTION("ArrayFormula(IFERROR(VALUE(REGEXEXTRACT(B5:B104&"""",""\d+$""))))"),646609.0) -> 646609 | D5: TB | E5: yillow | F5: {=MAP(C5:C104,LAMBDA(id,IFNA(IMAGE(MAPDATA(id,"cover_url")),"")))} | G5: {=IFNA(HYPERLINK(VLOOKUP(C5:C104,'_api'!B3:BC104,MATCH("url",'_api'!B2:W2,0),0),VLOOKUP(C5:C104,'_api'!B3:BC104,MATCH("string",'_api'!B2:W2,0),0)),"")} -> Camellia - dreamless wanderer [Ethereal] | H5: tech with some consistency | J5: Consistency | K5: 2198934 | L5: =IFERROR(__xludf.DUMMYFUNCTION("TRANSPOSE(SPLIT(JOIN("","",MAP(TRANSPOSE(Settings!I2:P2),TRANSPOSE(INDEX(Settings!I3:P12,MATCH(B2,Settings!E3:E12,0))),LAMBDA(mod,n,JOIN("","",ARRAYFORMULA(IF(n=0,"""",mod&SEQUENCE(n))))))),"",""))"),"NM1") -> NM1 | M5: {=MAP(K5:K104,LAMBDA(id,IFNA(IMAGE(MAPDATA(id,"cover_url")),"")))} | N5: =IFNA(MAPDATA(K5:K104,"string_url"),"") -> Camellia - Racemization [extreme] | O5: {=IFNA(MAPDATA_MODDED(K5:K104,{"difficultyrating","bpm","hit_length"},L5:L104),"")} -> 5.52323 | P5: 202 | Q5: 0.0022916667 | R5: {=IFNA(MAPDATA_MODDED(K5:K104,"diff_"&{"size","approach","overall"},L5:L104),"")} -> 4 | S5: 9.3 | T5: 8.3 | U5: {=IFNA(MAPDATA(K5:K104,{"creator","beatmap_id"}),"")} -> Ciyus Miapah | V5: 2198934
B6: https://osu.ppy.sh/beatmapsets/1328138#osu/2751338 | C6: =IFERROR(__xludf.DUMMYFUNCTION("""COMPUTED_VALUE"""),2751338.0) -> 2751338 | D6: HD | E6: play hd3 | G6: Kudou Chitose - CHO-DARI- [EX] | H6: hd3 | I6: c | J6: Flow aim streams | K6: 3010348 | L6: =IFERROR(__xludf.DUMMYFUNCTION("""COMPUTED_VALUE"""),"NM2") -> NM2 | N6: vierre cloud - moment [astronic's another] | O6: 5.55254 | P6: 171.3 | Q6: 0.0011458333 | R6: 4 | S6: 9 | T6: 8.2 | U6: Mimari | V6: 3010348
B7: https://osu.ppy.sh/beatmapsets/1557107#osu/3182641 | C7: =IFERROR(__xludf.DUMMYFUNCTION("""COMPUTED_VALUE"""),3182641.0) -> 3182641 | D7: HD | E7: play hd3 | G7: bbno$ & Rich Brian - edamame [flakesjan's extra] | H7: hd1 | J7: Aim control alt | K7: 3774971 | L7: =IFERROR(__xludf.DUMMYFUNCTION("""COMPUTED_VALUE"""),"NM3") -> NM3 | N7: Ryokuoushoku Shakai - Zutto Zutto Zutto [Kloyd's Expert] | O7: 5.25357 | P7: 128 | Q7: 0.0025925926 | R7: 4 | S7: 9.4 | T7: 9 | U7: mnyui | V7: 3774971
B8: https://osu.ppy.sh/beatmapsets/853045#osu/1782851 | C8: =IFERROR(__xludf.DUMMYFUNCTION("""COMPUTED_VALUE"""),1782851.0) -> 1782851 | D8: HR | E8: play hd3 | G8: Kajiura Yuki - Pugna cum maga [Insane] | J8: Long slider tech | K8: 3802110 | L8: =IFERROR(__xludf.DUMMYFUNCTION("""COMPUTED_VALUE"""),"NM4") -> NM4 | N8: USAO - Gruequix [Expert] | O8: 5.28144 | P8: 128 | Q8: 0.0018981481 | R8: 3.7 | S8: 9 | T8: 8 | U8: Cubby | V8: 3802110
B9: https://osu.ppy.sh/beatmapsets/908811#osu/1896582 | C9: =IFERROR(__xludf.DUMMYFUNCTION("""COMPUTED_VALUE"""),1896582.0) -> 1896582 | D9: HD | G9: M2U - Mare Maris [Another] | H9: Hd3 tech | J9: Speed | K9: 309900 | L9: =IFERROR(__xludf.DUMMYFUNCTION("""COMPUTED_VALUE"""),"NM5") -> NM5 | N9: Prim - Koisuru*Uchuu Sensou!! [Another 220BPM] | O9: 5.51825 | P9: 220 | Q9: 0.0012268519 | R9: 4 | S9: 9 | T9: 7 | U9: LemonTT | V9: 309900
B10: https://osu.ppy.sh/beatmapsets/1519388#osu/3256307 | C10: =IFERROR(__xludf.DUMMYFUNCTION("""COMPUTED_VALUE"""),3256307.0) -> 3256307 | D10: TB | E10: yillow | G10: Kikuo - Hole Dwelling [Bottomless] | H10: aim rhythm | J10: Low ar aim | K10: 3870932 | L10: =IFERROR(__xludf.DUMMYFUNCTION("""COMPUTED_VALUE"""),"NM6") -> NM6 | N10: Kikuo - Yousei no Kiri [Insane] | O10: 4.62529 | P10: 160 | Q10: 0.0014583333 | R10: 5 | S10: 7 | T10: 7 | U10: Vararaup | V10: 3870932
B11: https://osu.ppy.sh/beatmapsets/1683876#osu/3444608 | C11: =IFERROR(__xludf.DUMMYFUNCTION("""COMPUTED_VALUE"""),3444608.0) -> 3444608 | D11: NM | G11: Down - Ekoro [Another] | H11: nm6 | J11: Awkward linear | K11: 571620 | L11: =IFERROR(__xludf.DUMMYFUNCTION("""COMPUTED_VALUE"""),"HD1") -> HD1 | N11: DJ S3RL - T-T-Techno (feat. Jesskah) [fanzhen's X-Tra] | O11: 5.50651 | P11: 175 | Q11: 0.001875 | R11: 4.2 | S11: 9.1 | T11: 8 | U11: nold_1702 | V11: 571620
B12: https://osu.ppy.sh/beatmapsets/49459#osu/192181 | C12: =IFERROR(__xludf.DUMMYFUNCTION("""COMPUTED_VALUE"""),192181.0) -> 192181 | D12: FM | G12: Memme - Extreme Fantasy [Insane] | H12: fm2 | J12: Reading aim | K12: 3563737 | L12: =IFERROR(__xludf.DUMMYFUNCTION("""COMPUTED_VALUE"""),"HD2") -> HD2 | N12: capsule - A.I. automatic infection [Insane] | O12: 5.05513 | P12: 170 | Q12: 0.0020486111 | R12: 4 | S12: 8 | T12: 8 | U12: _xyliac | V12: 3563737
B13: https://osu.ppy.sh/beatmapsets/702272#osu/1485947 | C13: =IFERROR(__xludf.DUMMYFUNCTION("""COMPUTED_VALUE"""),1485947.0) -> 1485947 | D13: TB | E13: play hd3 | G13: Pendulum - Hold Your Colour [Iridescence] | J13: Tapping tech | K13: 2751338 | L13: =IFERROR(__xludf.DUMMYFUNCTION("""COMPUTED_VALUE"""),"HD3") -> HD3 | N13: Kudou Chitose - CHO-DARI- [EX] | O13: 5.25951 | P13: 80 | Q13: 0.0015277778 | R13: 4.2 | S13: 9.2 | T13: 8.7 | U13: SMOKELIND | V13: 2751338
B14: https://osu.ppy.sh/beatmapsets/1069288#osu/2239337 | C14: =IFERROR(__xludf.DUMMYFUNCTION("""COMPUTED_VALUE"""),2239337.0) -> 2239337 | D14: HD | E14: yillow | G14: BUTAOTOME - Towa no Maigo [Insane] | H14: hd2 | J14: Consistency | K14: 2288966 | L14: =IFERROR(__xludf.DUMMYFUNCTION("""COMPUTED_VALUE"""),"HR1") -> HR1 | N14: BAND-MAID - I can't live without you. [Insane] | O14: 5.42869 | P14: 180 | Q14: 0.0025925926 | R14: 5.2 | S14: 10 | T14: 10 | U14: Lasse | V14: 2288966
B15: https://osu.ppy.sh/beatmapsets/1052199#osu/2198934 | C15: =IFERROR(__xludf.DUMMYFUNCTION("""COMPUTED_VALUE"""),2198934.0) -> 2198934 | D15: NM | E15: yillow | G15: Camellia - Racemization [extreme] | H15: nm1 | J15: Precision aim | K15: 2691754 | L15: =IFERROR(__xludf.DUMMYFUNCTION("""COMPUTED_VALUE"""),"HR2") -> HR2 | N15: Sta & Feryquitous - 2 Minutes Euphoria [Pata-Mon's Insane] | O15: 5.20036 | P15: 170 | Q15: 0.0018518519 | R15: 6.5 | S15: 10 | T15: 9.8 | U15: Ryuusei Aika | V15: 2691754
B16: https://osu.ppy.sh/beatmapsets/533428#osu/1387177 | C16: =IFERROR(__xludf.DUMMYFUNCTION("""COMPUTED_VALUE"""),1387177.0) -> 1387177 | D16: NM | E16: yillow | G16: android52 - super anime groove 3d world [Insane] | H16: nm6 | J16: Tech tapping | K16: 2856139 | L16: =IFERROR(__xludf.DUMMYFUNCTION("""COMPUTED_VALUE"""),"HR3") -> HR3 | N16: Eagle - S!ck [Down's Insane] | O16: 5.36535 | P16: 177 | Q16: 0.0012731481 | R16: 5.2 | S16: 10 | T16: 10 | U16: Heilia | V16: 2856139
B17: https://osu.ppy.sh/beatmapsets/1339826#osu/2775823 | C17: =IFERROR(__xludf.DUMMYFUNCTION("""COMPUTED_VALUE"""),2775823.0) -> 2775823 | D17: HD | E17: play hd3 | G17: rissyuu feat. Choko - Paa ~Papapapaa ver~ [ExPaat] | J17: ar 8.3 so scary | K17: 765880 | L17: =IFERROR(__xludf.DUMMYFUNCTION("""COMPUTED_VALUE"""),"DT1") -> DT1 | N17: Komine Lisa - Resuscitated Hope [Insane] | O17: 5.44841 | P17: 195 | Q17: 0.0021527778 | R17: 4 | S17: 9.8666667 | T17: 9.0833333 | U17: Okorin | V17: 765880
B18: https://osu.ppy.sh/beatmapsets/1377112#osu/3206318 | C18: =IFERROR(__xludf.DUMMYFUNCTION("""COMPUTED_VALUE"""),3206318.0) -> 3206318 | D18: HD | E18: yillow | G18: aran - L.F.O [Orange's Extra] | H18: HG3 | J18: Bursts | K18: 345642 | L18: =IFERROR(__xludf.DUMMYFUNCTION("""COMPUTED_VALUE"""),"DT2") -> DT2 | N18: Memme - NEW Astronomas [Priti's Hyper] | O18: 5.50915 | P18: 240 | Q18: 0.00082561728 | R18: 4 | S18: 9.6666667 | T18: 8.4166667 | U18: Charles445 | V18: 345642
B19: https://osu.ppy.sh/beatmapsets/701625#osu/1484886 | C19: =IFERROR(__xludf.DUMMYFUNCTION("""COMPUTED_VALUE"""),1484886.0) -> 1484886 | D19: TB | E19: yillow | G19: Camellia - flying in the flow of deep-sea [trench] | J19: Finger control | K19: 2671858 | L19: =IFERROR(__xludf.DUMMYFUNCTION("""COMPUTED_VALUE"""),"DT3") -> DT3 | N19: Camellia - Compute It With Some Devilish Alcoholic Steampunk Engines [F4UZ4N's Hard] | O19: 5.36977 | P19: 247.5 | Q19: 0.0017438272 | R19: 3.7 | S19: 9.6666667 | T19: 9.0833333 | U19: OneShotFox | V19: 2671858
B20: https://osu.ppy.sh/beatmapsets/1838113#osu/3774971 | C20: =IFERROR(__xludf.DUMMYFUNCTION("""COMPUTED_VALUE"""),3774971.0) -> 3774971 | D20: NM | G20: Ryokuoushoku Shakai - Zutto Zutto Zutto [Kloyd's Expert] | J20: ar 7.7 so scary | K20: 4150885 | L20: =IFERROR(__xludf.DUMMYFUNCTION("""COMPUTED_VALUE"""),"DT4") -> DT4 | N20: KOTOKO - Princess Bride! (Cut Ver.) [Hard] | O20: 4.76974 | P20: 232.5 | Q20: 0.00099537037 | R20: 5 | S20: 8.3333333 | T20: 7.75 | U20: E4pi4mak | V20: 4150885
B21: https://osu.ppy.sh/beatmapsets/1371662#osu/2835868 | C21: =IFERROR(__xludf.DUMMYFUNCTION("""COMPUTED_VALUE"""),2835868.0) -> 2835868 | D21: HR | E21: play hd3 | G21: Mics!! - PAINT IT!! [Insane] | J21: Balanced consistency | K21: 4197268 | L21: =IFERROR(__xludf.DUMMYFUNCTION("""COMPUTED_VALUE"""),"FM1") -> FM1 | N21: Kenshi Yonezu - KICK BACK [STOMPMARK'S INSANE] | O21: 5.02118 | P21: 204 | Q21: 0.0021064815 | R21: 3 | S21: 9 | T21: 8 | U21: Mizujin | V21: 4197268
B22: https://osu.ppy.sh/beatmapsets/1965625#osu/4075902 | C22: =IFERROR(__xludf.DUMMYFUNCTION("""COMPUTED_VALUE"""),4075902.0) -> 4075902 | D22: HD | E22: yillow | G22: Azari - Black Out [----] | J22: Stream Fingercontrol | K22: 192181 | L22: =IFERROR(__xludf.DUMMYFUNCTION("""COMPUTED_VALUE"""),"FM2") -> FM2 | N22: Memme - Extreme Fantasy [Insane] | O22: 4.71418 | P22: 152 | Q22: 0.0016087963 | R22: 5 | S22: 8 | T22: 7 | U22: AngelHoney | V22: 192181
B23: https://osu.ppy.sh/beatmapsets/1880072#osu/3870932 | C23: =IFERROR(__xludf.DUMMYFUNCTION("""COMPUTED_VALUE"""),3870932.0) -> 3870932 | D23: NM | E23: play hd3 | G23: Kikuo - Yousei no Kiri [Insane] | J23: Tech | K23: 3499229 | L23: =IFERROR(__xludf.DUMMYFUNCTION("""COMPUTED_VALUE"""),"FM3") -> FM3 | N23: Mysteka - Hesperos [Mayu's Insane] | O23: 5.12068 | P23: 173 | Q23: 0.0018055556 | R23: 3.8 | S23: 9.2 | T23: 8 | U23: Acylica | V23: 3499229
B24: https://osu.ppy.sh/beatmapsets/98038#osu/261729 | C24: =IFERROR(__xludf.DUMMYFUNCTION("""COMPUTED_VALUE"""),261729.0) -> 261729 | D24: NM | E24: yillow | G24: ave;new feat. Sakura Saori - Piste SMILE Non-stop!! [Insane] | J24: Tapping consistency | K24: 1485947 | L24: =IFERROR(__xludf.DUMMYFUNCTION("""COMPUTED_VALUE"""),"TB1") -> TB1 | N24: Pendulum - Hold Your Colour [Iridescence] | O24: 5.71401 | P24: 174 | Q24: 0.0033796296 | R24: 4 | S24: 9.2 | T24: 9 | U24: ProfessionalBox | V24: 1485947
B25: https://osu.ppy.sh/beatmapsets/611507#osu/1290855 | C25: =IFERROR(__xludf.DUMMYFUNCTION("""COMPUTED_VALUE"""),1290855.0) -> 1290855 | D25: NM | G25: Balduin & Wolfgang Lohr (feat. Alanna) - Dizzy (Radio Edit) [Repertoire] | H25: potential nm3
B26: https://osu.ppy.sh/beatmapsets/1170697#osu/2442178 | C26: =IFERROR(__xludf.DUMMYFUNCTION("""COMPUTED_VALUE"""),2442178.0) -> 2442178 | D26: NM | E26: play hd3 | G26: KNOWER - Overtime [Ecstasy]
B27: https://osu.ppy.sh/beatmapsets/891366#osu/1863289 | C27: =IFERROR(__xludf.DUMMYFUNCTION("""COMPUTED_VALUE"""),1863289.0) -> 1863289 | D27: NM | E27: play hd3 | G27: HyuN - Illusion of Inflict [Expert]
B28: https://osu.ppy.sh/beatmapsets/291495#osu/757386 | C28: =IFERROR(__xludf.DUMMYFUNCTION("""COMPUTED_VALUE"""),757386.0) -> 757386 | D28: NM | E28: play hd3 | G28: orangentle - HAELEQUIN [toybot's Insane] | H28: nm2
B29: https://osu.ppy.sh/beatmapsets/1366507#osu/3010348 | C29: =IFERROR(__xludf.DUMMYFUNCTION("""COMPUTED_VALUE"""),3010348.0) -> 3010348 | D29: NM | E29: yillow | G29: vierre cloud - moment [astronic's another]
B30: https://osu.ppy.sh/beatmapsets/1409478#osu/2906707 | C30: =IFERROR(__xludf.DUMMYFUNCTION("""COMPUTED_VALUE"""),2906707.0) -> 2906707 | D30: NM | E30: play hd3 | G30: Camellia feat. Nanahira - POLKAMANIA [ANOTHER]
B31: https://osu.ppy.sh/beatmapsets/1305940#osu/2842836 | C31: =IFERROR(__xludf.DUMMYFUNCTION("""COMPUTED_VALUE"""),2842836.0) -> 2842836 | D31: NM | E31: play hd3 | G31: C-Show - Make Some Noise for Mr.C [Crissa's Another]
B32: https://osu.ppy.sh/beatmapsets/1580891#osu/3851000 | C32: =IFERROR(__xludf.DUMMYFUNCTION("""COMPUTED_VALUE"""),3851000.0) -> 3851000 | D32: HR | E32: play hd3 | G32: PSYQUI - Hysteric Night Girl -Awakening- (feat. Such) [Insane]
B33: https://osu.ppy.sh/beatmapsets/984013#osu/2058908 | C33: =IFERROR(__xludf.DUMMYFUNCTION("""COMPUTED_VALUE"""),2058908.0) -> 2058908 | D33: HR | E33: yillow | G33: Dictate - Militant [Oscar Sierra Uniform] | H33: slider aim hr3
B34: https://osu.ppy.sh/beatmapsets/366884#osu/804959 | C34: =IFERROR(__xludf.DUMMYFUNCTION("""COMPUTED_VALUE"""),804959.0) -> 804959 | D34: DT | E34: play hd3 | G34: yuikonnu - caramel heaven [Fortune's Hyper]
B35: https://osu.ppy.sh/beatmapsets/1286316#osu/2856139 | C35: =IFERROR(__xludf.DUMMYFUNCTION("""COMPUTED_VALUE"""),2856139.0) -> 2856139 | D35: HR | E35: yillow | G35: Eagle - S!ck [Down's Insane] | H35: finger control tech hr3
B37: https://osu.ppy.sh/beatmapsets/1610294#osu/3499229 | C37: =IFERROR(__xludf.DUMMYFUNCTION("""COMPUTED_VALUE"""),3499229.0) -> 3499229 | D37: FM | E37: play hd3 | G37: Mysteka - Hesperos [Mayu's Insane]
B38: https://osu.ppy.sh/beatmapsets/1954230#osu/4197268 | C38: =IFERROR(__xludf.DUMMYFUNCTION("""COMPUTED_VALUE"""),4197268.0) -> 4197268 | D38: FM | E38: play hd3 | G38: Kenshi Yonezu - KICK BACK [STOMPMARK'S INSANE]
B39: 86079 | C39: =IFERROR(__xludf.DUMMYFUNCTION("""COMPUTED_VALUE"""),86079.0) -> 86079 | D39: FM | E39: yillow | G39: Pastry - Goblin Girl [Lunatic]
B40: https://osu.ppy.sh/beatmapsets/1360537#osu/2849167 | C40: =IFERROR(__xludf.DUMMYFUNCTION("""COMPUTED_VALUE"""),2849167.0) -> 2849167 | D40: DT | E40: play hd3 | G40: hololive IDOL PROJECT - Suspect [Hinsvar's Hard]
B41: https://osu.ppy.sh/beatmapsets/1997114#osu/4150885 | C41: =IFERROR(__xludf.DUMMYFUNCTION("""COMPUTED_VALUE"""),4150885.0) -> 4150885 | D41: DT | E41: play hd3 | G41: KOTOKO - Princess Bride! (Cut Ver.) [Hard]
B42: https://osu.ppy.sh/beatmapsets/1522116#osu/3798371 | C42: =IFERROR(__xludf.DUMMYFUNCTION("""COMPUTED_VALUE"""),3798371.0) -> 3798371 | D42: DT | E42: play hd3 | G42: Metrik - We Got It (feat. Rothwell) [619's Hard]
B43: https://osu.ppy.sh/beatmapsets/769346#osu/2839573 | C43: =IFERROR(__xludf.DUMMYFUNCTION("""COMPUTED_VALUE"""),2839573.0) -> 2839573 | D43: NM | E43: yillow | G43: Whispered - Exile of the Floating World [-Kemsyt's Insane] | H43: "speed"
B44: https://osu.ppy.sh/beatmapsets/1809661#osu/3711739 | C44: =IFERROR(__xludf.DUMMYFUNCTION("""COMPUTED_VALUE"""),3711739.0) -> 3711739 | D44: NM | E44: yillow | G44: deathcount - A Beautiful Degeneracy (Remix by Stazma The Junglechrist) [Expert] | H44: speed.
B45: https://osu.ppy.sh/beatmapsets/1066757#osu/2835894 | C45: =IFERROR(__xludf.DUMMYFUNCTION("""COMPUTED_VALUE"""),2835894.0) -> 2835894 | D45: NM | G45: ZUTOMAYO - Haze Haseru Haterumade [AyluscenathanMyMommy's Collab Extra] | H45: nm3?
B46: https://osu.ppy.sh/beatmapsets/1665981#osu/3404589 | C46: =IFERROR(__xludf.DUMMYFUNCTION("""COMPUTED_VALUE"""),3404589.0) -> 3404589 | D46: NM | E46: yillow | G46: Mata & ZDECHLY OSA - PATOKISS [Ekspercki Bluenationa] | H46: nm4
B47: https://osu.ppy.sh/beatmapsets/87188#osu/345642 | C47: =IFERROR(__xludf.DUMMYFUNCTION("""COMPUTED_VALUE"""),345642.0) -> 345642 | D47: DT | E47: yillow | G47: Memme - NEW Astronomas [Priti's Hyper] | H47: dt2
B48: https://osu.ppy.sh/beatmapsets/1301388#osu/2970566 | C48: =IFERROR(__xludf.DUMMYFUNCTION("""COMPUTED_VALUE"""),2970566.0) -> 2970566 | D48: DT | E48: yillow | G48: Feryquitous - Hemizorv [Flask's Hard] | H48: dt3
B49: https://osu.ppy.sh/b/1035068 | C49: =IFERROR(__xludf.DUMMYFUNCTION("""COMPUTED_VALUE"""),1035068.0) -> 1035068 | D49: DT | E49: yillow | G49: Hana - Gekka Jasmine (2014ver.) [Gyro's Light Insane] | H49: dt2
B50: https://osu.ppy.sh/beatmapsets/376552#osu/824390 | C50: =IFERROR(__xludf.DUMMYFUNCTION("""COMPUTED_VALUE"""),824390.0) -> 824390 | D50: DT | E50: yillow | G50: Hana - Sakura no Uta [Light Insane] | H50: dt1
B51: https://osu.ppy.sh/beatmapsets/761026#osu/2111279 | C51: =IFERROR(__xludf.DUMMYFUNCTION("""COMPUTED_VALUE"""),2111279.0) -> 2111279 | D51: NM | E51: play hd3 | G51: AngelMaker - A Dark Omen [Tukan's Light Extra]
B52: https://osu.ppy.sh/beatmapsets/1158494#osu/2417645 | C52: =IFERROR(__xludf.DUMMYFUNCTION("""COMPUTED_VALUE"""),2417645.0) -> 2417645 | D52: HD | E52: play hd3 | G52: TUYU - Rock na Kimi to wa Owakare da [Farewell Extra]
B53: https://osu.ppy.sh/beatmapsets/347023#osu/765880 | C53: =IFERROR(__xludf.DUMMYFUNCTION("""COMPUTED_VALUE"""),765880.0) -> 765880 | D53: DT | E53: play hd3 | G53: Komine Lisa - Resuscitated Hope [Insane]
B54: https://osu.ppy.sh/beatmapsets/1650533#osu/3396297 | C54: =IFERROR(__xludf.DUMMYFUNCTION("""COMPUTED_VALUE"""),3396297.0) -> 3396297 | D54: FM | E54: yillow | G54: A.SAKA - Nanatsu Hiiragisuikou [Pata-Mon's Hyper]
B55: https://osu.ppy.sh/beatmapsets/1280207#osu/2691754 | C55: =IFERROR(__xludf.DUMMYFUNCTION("""COMPUTED_VALUE"""),2691754.0) -> 2691754 | D55: HR | E55: yillow | G55: Sta & Feryquitous - 2 Minutes Euphoria [Pata-Mon's Insane]
B56: https://osu.ppy.sh/beatmapsets/1850818#osu/3802110 | C56: =IFERROR(__xludf.DUMMYFUNCTION("""COMPUTED_VALUE"""),3802110.0) -> 3802110 | D56: NM | E56: play hd3 | G56: USAO - Gruequix [Expert]
B57: https://osu.ppy.sh/beatmapsets/1268030#osu/2671858 | C57: =IFERROR(__xludf.DUMMYFUNCTION("""COMPUTED_VALUE"""),2671858.0) -> 2671858 | D57: DT | E57: play hd3 | G57: Camellia - Compute It With Some Devilish Alcoholic Steampunk Engines [F4UZ4N's Hard]
B58: https://osu.ppy.sh/beatmapsets/1093430#osu/2288966 | C58: =IFERROR(__xludf.DUMMYFUNCTION("""COMPUTED_VALUE"""),2288966.0) -> 2288966 | D58: HR | E58: play hd3 | G58: BAND-MAID - I can't live without you. [Insane]
B59: https://osu.ppy.sh/beatmapsets/1248914#osu/3752605 | C59: =IFERROR(__xludf.DUMMYFUNCTION("""COMPUTED_VALUE"""),3752605.0) -> 3752605 | D59: HD | E59: play hd3 | G59: inabakumori - Tsukuri Kake no Shinshou [LeCandy's Extra]
B60: https://osu.ppy.sh/beatmapsets/1670825#osu/3953905 | C60: =IFERROR(__xludf.DUMMYFUNCTION("""COMPUTED_VALUE"""),3953905.0) -> 3953905 | D60: HD | E60: yillow | G60: bulow - Revolver (Sped Up Ver.) [NoFail's Extra]
B61: https://osu.ppy.sh/beatmapsets/120987#osu/309899 | C61: =IFERROR(__xludf.DUMMYFUNCTION("""COMPUTED_VALUE"""),309899.0) -> 309899 | D61: NM | E61: yillow | G61: Prim - Koisuru*Uchuu Sensou!! [Another 220BPM AR10]
B62: https://osu.ppy.sh/beatmapsets/120987#osu/309900 | C62: =IFERROR(__xludf.DUMMYFUNCTION("""COMPUTED_VALUE"""),309900.0) -> 309900 | D62: NM | E62: yillow | G62: Prim - Koisuru*Uchuu Sensou!! [Another 220BPM]
B63: https://osu.ppy.sh/beatmapsets/1670118#osu/3563737 | C63: =IFERROR(__xludf.DUMMYFUNCTION("""COMPUTED_VALUE"""),3563737.0) -> 3563737 | D63: HD | E63: play hd3 | G63: capsule - A.I. automatic infection [Insane]
B64: https://osu.ppy.sh/beatmapsets/83560#osu/571620 | C64: =IFERROR(__xludf.DUMMYFUNCTION("""COMPUTED_VALUE"""),571620.0) -> 571620 | D64: HD | E64: yillow | G64: DJ S3RL - T-T-Techno (feat. Jesskah) [fanzhen's X-Tra]
B86: 975342 | C86: =IFERROR(__xludf.DUMMYFUNCTION("""COMPUTED_VALUE"""),975342.0) -> 975342 | G86: Fahrstuhl Musik - Elevator Music [LowComboFC's Going Downwards]

Sheet GF
B2: Finals | C2: Best of | D2: =IFERROR(VLOOKUP(B2,Settings!E3:H12,3,0),"") -> 13 | E2: Bans | F2: =IFERROR(VLOOKUP(B2,Settings!E3:H12,4,0),"") -> 2
B3: Suggestions | J3: Pool Assembly
B4: Map Link | C4: ID | D4: Mod | E4: Suggestor | F4: Map | H4: Notes | J4: Note | K4: ID | L4: Mod | M4: Map | O4: SR | P4: BPM | Q4: Length | R4: CS | S4: AR | T4: OD | U4: Mapper | V4: ID
C5: =IFERROR(__xludf.DUMMYFUNCTION("ArrayFormula(IFERROR(VALUE(REGEXEXTRACT(B5:B104&"""",""\d+$""))))"),"") | F5: {=MAP(C5:C104,LAMBDA(id,IFNA(IMAGE(MAPDATA(id,"cover_url")),"")))} | G5: {=IFNA(HYPERLINK(VLOOKUP(C5:C104,'_api'!B3:BC104,MATCH("url",'_api'!B2:W2,0),0),VLOOKUP(C5:C104,'_api'!B3:BC104,MATCH("string",'_api'!B2:W2,0),0)),"")} | K5: 2792506 | L5: =IFERROR(__xludf.DUMMYFUNCTION("TRANSPOSE(SPLIT(JOIN("","",MAP(TRANSPOSE(Settings!I2:P2),TRANSPOSE(INDEX(Settings!I3:P12,MATCH(B2,Settings!E3:E12,0))),LAMBDA(mod,n,JOIN("","",ARRAYFORMULA(IF(n=0,"""",mod&SEQUENCE(n))))))),"",""))"),"NM1") -> NM1 | M5: {=MAP(K5:K104,LAMBDA(id,IFNA(IMAGE(MAPDATA(id,"cover_url")),"")))} | N5: =IFNA(MAPDATA(K5:K104,"string_url"),"") -> Airots - Tougen Roman (Epsilon Remix) [Dailycare's Extra] | O5: {=IFNA(MAPDATA_MODDED(K5:K104,{"difficultyrating","bpm","hit_length"},L5:L104),"")} -> 5.67773 | P5: 175 | Q5: 0.0029050926 | R5: {=IFNA(MAPDATA_MODDED(K5:K104,"diff_"&{"size","approach","overall"},L5:L104),"")} -> 4.2 | S5: 9.3 | T5: 8 | U5: {=IFNA(MAPDATA(K5:K104,{"creator","beatmap_id"}),"")} -> GIDZ | V5: 2792506
B6: https://osu.ppy.sh/beatmapsets/1793226#osu/3795759 | C6: =IFERROR(__xludf.DUMMYFUNCTION("""COMPUTED_VALUE"""),3795759.0) -> 3795759 | D6: HD | E6: pekonya | G6: mezClA (Evatan & Mecotan) - Azul Remix [Callie's Another] | H6: HD wildcard | I6: c | J6: omg is that -+ AGAIN | K6: 3714369 | L6: =IFERROR(__xludf.DUMMYFUNCTION("""COMPUTED_VALUE"""),"NM2") -> NM2 | N6: daisan - -+ [Light Another] | O6: 5.75189 | P6: 185 | Q6: 0.001412037 | R6: 4 | S6: 9.3 | T6: 8 | U6: [Crz]Makii | V6: 3714369
B7: https://osu.ppy.sh/beatmapsets/891581#osu/1863870 | C7: =IFERROR(__xludf.DUMMYFUNCTION("""COMPUTED_VALUE"""),1863870.0) -> 1863870 | D7: HD | E7: pekonya | G7: M2U - Velocity [Yugu's Jerk (Extra)] | H7: HD3 | K7: 3461206 | L7: =IFERROR(__xludf.DUMMYFUNCTION("""COMPUTED_VALUE"""),"NM3") -> NM3 | N7: Hatsuki Yura - Witchcraft [mogumogu] | O7: 5.42973 | P7: 135 | Q7: 0.0027662037 | R7: 4.2 | S7: 9.3 | T7: 8 | U7: Umbra | V7: 3461206
B8: https://osu.ppy.sh/beatmapsets/688128#osu/1456307 | C8: =IFERROR(__xludf.DUMMYFUNCTION("""COMPUTED_VALUE"""),1456307.0) -> 1456307 | D8: FM | E8: yillow | G8: Memme - Blessing Snow [Left's Another] | J8: slider | K8: 1737928 | L8: =IFERROR(__xludf.DUMMYFUNCTION("""COMPUTED_VALUE"""),"NM4") -> NM4 | N8: Zekk - Feelsleft0ut [Acyl x toybot's Another] | O8: 5.21701 | P8: 170 | Q8: 0.0010648148 | R8: 4.2 | S8: 9 | T8: 9 | U8: J1_ | V8: 1737928
B9: https://osu.ppy.sh/beatmapsets/1985409#osu/4134134 | C9: =IFERROR(__xludf.DUMMYFUNCTION("""COMPUTED_VALUE"""),4134134.0) -> 4134134 | D9: HD | E9: play hd3 | G9: Kairiki bear feat. Hatsune Miku - Starry Start [Starstruck (CS4 Edit)] | H9: hd2 | K9: 3711739 | L9: =IFERROR(__xludf.DUMMYFUNCTION("""COMPUTED_VALUE"""),"NM5") -> NM5 | N9: deathcount - A Beautiful Degeneracy (Remix by Stazma The Junglechrist) [Expert] | O9: 5.57368 | P9: 230 | Q9: 0.0013773148 | R9: 4 | S9: 9 | T9: 8 | U9: quantumvortex | V9: 3711739
B10: https://osu.ppy.sh/beatmapsets/8284#osu/34211 | C10: =IFERROR(__xludf.DUMMYFUNCTION("""COMPUTED_VALUE"""),34211.0) -> 34211 | D10: NM | E10: play hd3 | G10: Hatsune Miku - Hatsune Miku no Shoushitsu [Uninstall] | H10: :> | K10: 3711612 | L10: =IFERROR(__xludf.DUMMYFUNCTION("""COMPUTED_VALUE"""),"NM6") -> NM6 | N10: Kotoha - Cat Loving [bongo's Insane] | O10: 4.81674 | P10: 163 | Q10: 0.0013194444 | R10: 4 | S10: 7 | T10: 8 | U10: Kotoha | V10: 3711612
B11: https://osu.ppy.sh/beatmapsets/734135#osu/1567978 | C11: =IFERROR(__xludf.DUMMYFUNCTION("""COMPUTED_VALUE"""),1567978.0) -> 1567978 | D11: DT | E11: play hd3 | G11: Chito (CV: Minase Inori), Yuuri (CV: Kubo Yurika) - More One Night (Assertive Hardcore Bootleg) [Mathew's Hard] | K11: 2348578 | L11: =IFERROR(__xludf.DUMMYFUNCTION("""COMPUTED_VALUE"""),"HD1") -> HD1 | N11: Chikuwa - Jinsei Matatabi [Expert] | O11: 5.68607 | P11: 186 | Q11: 0.0022569444 | R11: 4 | S11: 9.2 | T11: 8.9 | U11: Kuse | V11: 2348578
B12: https://osu.ppy.sh/beatmapsets/490662#osu/1045757 | C12: =IFERROR(__xludf.DUMMYFUNCTION("""COMPUTED_VALUE"""),1045757.0) -> 1045757 | D12: TB | E12: play hd3 | G12: Shoji Meguro - Kimi no Kioku (Aethral Remix) [Remembrance] | J12: might be too hard | K12: 4134134 | L12: =IFERROR(__xludf.DUMMYFUNCTION("""COMPUTED_VALUE"""),"HD2") -> HD2 | N12: Kairiki bear feat. Hatsune Miku - Starry Start [Starstruck (CS4 Edit)] | O12: 5.22745 | P12: 181 | Q12: 0.0017476852 | R12: 4 | S12: 8 | T12: 8 | U12: Ixcors | V12: 4134134
B13: https://osu.ppy.sh/beatmapsets/1670825#osu/3412490 | C13: =IFERROR(__xludf.DUMMYFUNCTION("""COMPUTED_VALUE"""),3412490.0) -> 3412490 | D13: HD | E13: yillow | G13: bulow - Revolver (Sped Up Ver.) [Extra] | H13: hd1 | K13: 2565268 | L13: =IFERROR(__xludf.DUMMYFUNCTION("""COMPUTED_VALUE"""),"HD3") -> HD3 | N13: Camellia - Wolves Standing Towards Enemies [Insane] | O13: 5.299 | P13: 191 | Q13: 0.0017824074 | R13: 4.5 | S13: 9.2 | T13: 8 | U13: Regou | V13: 2565268
B14: https://osu.ppy.sh/beatmapsets/962568#osu/2015481 | C14: =IFERROR(__xludf.DUMMYFUNCTION("""COMPUTED_VALUE"""),2015481.0) -> 2015481 | D14: HR | E14: yillow | G14: BUTAOTOME - Futari Dake no Kotoba [kiry's Insane] | H14: hr2 | K14: 1258993 | L14: =IFERROR(__xludf.DUMMYFUNCTION("""COMPUTED_VALUE"""),"HR1") -> HR1 | N14: Dreamcatcher - Chase Me [Extra] | O14: 5.49537 | P14: 200 | Q14: 0.0020486111 | R14: 5.2 | S14: 10 | T14: 10 | U14: Natsu | V14: 1258993
B15: https://osu.ppy.sh/beatmapsets/586144#osu/1258993 | C15: =IFERROR(__xludf.DUMMYFUNCTION("""COMPUTED_VALUE"""),1258993.0) -> 1258993 | D15: HR | E15: yillow | G15: Dreamcatcher - Chase Me [Extra] | H15: RAW AIM | K15: 1592403 | L15: =IFERROR(__xludf.DUMMYFUNCTION("""COMPUTED_VALUE"""),"HR2") -> HR2 | N15: factal - Wake Up While Sleeping [Insane] | O15: 5.31905 | P15: 160 | Q15: 0.0017592593 | R15: 6.5 | S15: 10 | T15: 10 | U15: Nokris | V15: 1592403
B16: https://osu.ppy.sh/beatmapsets/1170697#osu/2442178 | C16: =IFERROR(__xludf.DUMMYFUNCTION("""COMPUTED_VALUE"""),2442178.0) -> 2442178 | D16: NM | E16: play hd3 | G16: KNOWER - Overtime [Ecstasy] | H16: nm3 | K16: 3333734 | L16: =IFERROR(__xludf.DUMMYFUNCTION("""COMPUTED_VALUE"""),"HR3") -> HR3 | N16: USAO - Chariot (Extended Mix) [lebronJAM] | O16: 5.41149 | P16: 128 | Q16: 0.0021875 | R16: 5.2 | S16: 10 | T16: 10 | U16: Realazy | V16: 3333734
B17: https://osu.ppy.sh/beatmapsets/611507#osu/1290855 | C17: =IFERROR(__xludf.DUMMYFUNCTION("""COMPUTED_VALUE"""),1290855.0) -> 1290855 | D17: FM | E17: yillow | G17: Balduin & Wolfgang Lohr (feat. Alanna) - Dizzy (Radio Edit) [Repertoire] | H17: fm3 | K17: 2519731 | L17: =IFERROR(__xludf.DUMMYFUNCTION("""COMPUTED_VALUE"""),"DT1") -> DT1 | N17: Inui Toko - Kimagure Romantic [Light Insane] | O17: 5.72936 | P17: 255 | Q17: 0.0017592593 | R17: 4 | S17: 10 | T17: 9.0833333 | U17: newton- | V17: 2519731
K18: 1035068 | L18: =IFERROR(__xludf.DUMMYFUNCTION("""COMPUTED_VALUE"""),"DT2") -> DT2 | N18: Hana - Gekka Jasmine (2014ver.) [Gyro's Light Insane] | O18: 5.68312 | P18: 255 | Q18: 0.0015354938 | R18: 3.8 | S18: 9.8666667 | T18: 9.0833333 | U18: PinkHeart | V18: 1035068
B19: https://osu.ppy.sh/beatmapsets/1633242#osu/3333734 | C19: =IFERROR(__xludf.DUMMYFUNCTION("""COMPUTED_VALUE"""),3333734.0) -> 3333734 | D19: HR | E19: yillow | G19: USAO - Chariot (Extended Mix) [lebronJAM] | H19: hr3 | K19: 1707909 | L19: =IFERROR(__xludf.DUMMYFUNCTION("""COMPUTED_VALUE"""),"DT3") -> DT3 | N19: USAO - FREEDOM (Extended Mix) [Hard] | O19: 5.48578 | P19: 255 | Q19: 0.0016358025 | R19: 4 | S19: 9.6666667 | T19: 8.4166667 | U19: C00L | V19: 1707909
B20: https://osu.ppy.sh/beatmapsets/1339826#osu/2775823 | C20: =IFERROR(__xludf.DUMMYFUNCTION("""COMPUTED_VALUE"""),2775823.0) -> 2775823 | D20: HD | E20: play hd3 | G20: rissyuu feat. Choko - Paa ~Papapapaa ver~ [ExPaat] | K20: 25341 | L20: =IFERROR(__xludf.DUMMYFUNCTION("""COMPUTED_VALUE"""),"DT4") -> DT4 | N20: Crazy Loop - Love Is A Simple Thing [EEeee's Love Ain't So Simple] | O20: 5.00306 | P20: 228 | Q20: 0.0013040123 | R20: 5 | S20: 8.3333333 | T20: 7.75 | U20: eee | V20: 25341
B21: https://osu.ppy.sh/beatmapsets/1152554#osu/2405667 | C21: =IFERROR(__xludf.DUMMYFUNCTION("""COMPUTED_VALUE"""),2405667.0) -> 2405667 | D21: HD | E21: Fuwub | G21: raito - Blood Drain -Again- [Expert] | H21: troll pool | K21: 3883278 | L21: =IFERROR(__xludf.DUMMYFUNCTION("""COMPUTED_VALUE"""),"FM1") -> FM1 | N21: Natori Sana - Mondainai Tripper! [Insane] | O21: 5.29251 | P21: 180 | Q21: 0.002025463 | R21: 3 | S21: 9 | T21: 7.5 | U21: milr_ | V21: 3883278
B22: https://osu.ppy.sh/beatmapsets/1809661#osu/3711739 | C22: =IFERROR(__xludf.DUMMYFUNCTION("""COMPUTED_VALUE"""),3711739.0) -> 3711739 | D22: NM | E22: yillow | G22: deathcount - A Beautiful Degeneracy (Remix by Stazma The Junglechrist) [Expert] | K22: 58701 | L22: =IFERROR(__xludf.DUMMYFUNCTION("""COMPUTED_VALUE"""),"FM2") -> FM2 | N22: IOSYS - Midnight Lightning Bolt [Lunatic] | O22: 5.0039 | P22: 155 | Q22: 0.0018634259 | R22: 5 | S22: 8 | T22: 8 | U22: pieguy1372 | V22: 58701
B23: https://osu.ppy.sh/beatmapsets/1020335#osu/2134906 | C23: =IFERROR(__xludf.DUMMYFUNCTION("""COMPUTED_VALUE"""),2134906.0) -> 2134906 | D23: NM | E23: yillow | G23: highcolor_sunz - RE-OVERDOSE [Expert] | H23: nm3 | K23: 3853742 | L23: =IFERROR(__xludf.DUMMYFUNCTION("""COMPUTED_VALUE"""),"FM3") -> FM3 | N23: lapix - Flamenco House [JeZalt's Another] | O23: 5.05375 | P23: 130 | Q23: 0.0016203704 | R23: 3.5 | S23: 8.8 | T23: 8 | U23: Luminiscental | V23: 3853742
B24: https://osu.ppy.sh/beatmapsets/1629444#osu/3326410 | C24: =IFERROR(__xludf.DUMMYFUNCTION("""COMPUTED_VALUE"""),3326410.0) -> 3326410 | D24: DT | E24: play hd3 | G24: Absofacto - Dissolve [Dissolve] | K24: 862338 | L24: =IFERROR(__xludf.DUMMYFUNCTION("""COMPUTED_VALUE"""),"TB1") -> TB1 | N24: Camellia - d:for the DELTA [Delirium] | O24: 6.01809 | P24: 174 | Q24: 0.0033680556 | R24: 4 | S24: 9.4 | T24: 8.5 | U24: ProfessionalBox | V24: 862338
B25: https://osu.ppy.sh/beatmapsets/1123944#osu/2348578 | C25: =IFERROR(__xludf.DUMMYFUNCTION("""COMPUTED_VALUE"""),2348578.0) -> 2348578 | D25: HD | E25: play hd3 | G25: Chikuwa - Jinsei Matatabi [Expert]
B26: https://osu.ppy.sh/beatmapsets/411990#osu/929118 | C26: =IFERROR(__xludf.DUMMYFUNCTION("""COMPUTED_VALUE"""),929118.0) -> 929118 | D26: NM | E26: yillow | G26: The Ghost of 3.13 - Daydream [Extreme] | H26: nm5
B27: https://osu.ppy.sh/beatmapsets/1299595#osu/2718270 | C27: =IFERROR(__xludf.DUMMYFUNCTION("""COMPUTED_VALUE"""),2718270.0) -> 2718270 | E27: play hd3 | G27: Reol - Q? [Mir's Extra]
B28: https://osu.ppy.sh/beatmapsets/311328#osu/1744385 | C28: =IFERROR(__xludf.DUMMYFUNCTION("""COMPUTED_VALUE"""),1744385.0) -> 1744385 | D28: NM | E28: play hd3 | G28: Foreground Eclipse - Storytellers [Akitoshi's Extra]
B29: https://osu.ppy.sh/beatmapsets/1318545#osu/3186407 | C29: =IFERROR(__xludf.DUMMYFUNCTION("""COMPUTED_VALUE"""),3186407.0) -> 3186407 | D29: HD | E29: play hd3 | G29: lapix - Day by day (PSYQUI Remix) [MarcoBrolo's Insane] | H29: this map??? as hd3???
B30: https://osu.ppy.sh/beatmapsets/85802#osu/243487 | C30: =IFERROR(__xludf.DUMMYFUNCTION("""COMPUTED_VALUE"""),243487.0) -> 243487 | D30: NM | E30: play hd3 | G30: RYO - Shuffle Heaven [Another]
B31: https://osu.ppy.sh/beatmapsets/1764690#osu/3614024 | C31: =IFERROR(__xludf.DUMMYFUNCTION("""COMPUTED_VALUE"""),3614024.0) -> 3614024 | D31: NM | E31: play hd3 | G31: tv room - Know It All [insane_TVTVTTTVVT]
B32: https://osu.ppy.sh/beatmapsets/1536850#osu/3257641 | C32: =IFERROR(__xludf.DUMMYFUNCTION("""COMPUTED_VALUE"""),3257641.0) -> 3257641 | D32: HR | E32: play hd3 | G32: leroy - the dariacore to YTP pipeline [noin's insane]
B33: https://osu.ppy.sh/beatmapsets/1557716#osu/3182052 | C33: =IFERROR(__xludf.DUMMYFUNCTION("""COMPUTED_VALUE"""),3182052.0) -> 3182052 | D33: FM | E33: play hd3 | G33: Pegboard Nerds - Heartbit (feat. Tia Simone) [pulse.exe]
B34: https://osu.ppy.sh/beatmapsets/1493511#osu/3071429 | C34: =IFERROR(__xludf.DUMMYFUNCTION("""COMPUTED_VALUE"""),3071429.0) -> 3071429 | D34: DT | E34: play hd3 | G34: Police Piccadilly feat. KAFU - Furachi na Kassai [mrforse's Light Insane]
B35: https://osu.ppy.sh/beatmapsets/763406#osu/1653270 | C35: =IFERROR(__xludf.DUMMYFUNCTION("""COMPUTED_VALUE"""),1653270.0) -> 1653270 | D35: DT | G35: Hondo Kaede, Oonishi Saori, Waki Azumi, Kino Hina, Matsuda Risae, Suzuki Eri - Save you Save me [Gaia's Insane] | H35: dt1
B36: https://osu.ppy.sh/beatmapsets/33651#osu/117424 | C36: =IFERROR(__xludf.DUMMYFUNCTION("""COMPUTED_VALUE"""),117424.0) -> 117424 | D36: FM | E36: play hd3 | G36: Hatsune Miku - Rubik's Cube [6x6x6]
B37: https://osu.ppy.sh/beatmapsets/1312343#osu/2855311 | C37: =IFERROR(__xludf.DUMMYFUNCTION("""COMPUTED_VALUE"""),2855311.0) -> 2855311 | D37: DT | E37: play hd3 | G37: Kijibato - w/WWW feat. Hoshimiya Toto [Hard]
B38: https://osu.ppy.sh/beatmapsets/1885986#osu/3883278 | C38: =IFERROR(__xludf.DUMMYFUNCTION("""COMPUTED_VALUE"""),3883278.0) -> 3883278 | D38: FM | E38: play hd3 | G38: Natori Sana - Mondainai Tripper! [Insane]
B39: https://osu.ppy.sh/beatmapsets/749323#osu/1592403 | C39: =IFERROR(__xludf.DUMMYFUNCTION("""COMPUTED_VALUE"""),1592403.0) -> 1592403 | D39: HR | E39: yillow | G39: factal - Wake Up While Sleeping [Insane]
B40: https://osu.ppy.sh/beatmapsets/5285#osu/26436 | C40: =IFERROR(__xludf.DUMMYFUNCTION("""COMPUTED_VALUE"""),26436.0) -> 26436 | D40: HR | E40: yillow | G40: IOSYS - Cirno's Perfect Math Class [DJPop's Streams]
B41: https://osu.ppy.sh/beatmapsets/1007796#osu/2111658 | C41: =IFERROR(__xludf.DUMMYFUNCTION("""COMPUTED_VALUE"""),2111658.0) -> 2111658 | D41: HR | E41: yillow | G41: Gentle Stick - Bach Imitation [Insane]
B42: https://osu.ppy.sh/beatmapsets/171676#osu/424554 | C42: =IFERROR(__xludf.DUMMYFUNCTION("""COMPUTED_VALUE"""),424554.0) -> 424554 | D42: HR | E42: yillow | G42: SHK - Identity Part 5 [Kami's Another]
B43: https://osu.ppy.sh/beatmapsets/1225001#osu/2559136 | C43: =IFERROR(__xludf.DUMMYFUNCTION("""COMPUTED_VALUE"""),2559136.0) -> 2559136 | D43: HR | E43: yillow | G43: ARForest - Infection [Eulogy] | H43: TECH HR2
B44: https://osu.ppy.sh/beatmapsets/1321446#osu/2792506 | C44: =IFERROR(__xludf.DUMMYFUNCTION("""COMPUTED_VALUE"""),2792506.0) -> 2792506 | D44: NM | E44: yillow | G44: Airots - Tougen Roman (Epsilon Remix) [Dailycare's Extra] | H44: light tech (?) nm1
B45: https://osu.ppy.sh/beatmapsets/1790018#osu/3686559 | C45: =IFERROR(__xludf.DUMMYFUNCTION("""COMPUTED_VALUE"""),3686559.0) -> 3686559 | D45: NM | E45: play hd3 | G45: Maison book girl - bath room [deppy's insane] | H45: this is a serious nm6
B46: https://osu.ppy.sh/beatmapsets/824205#osu/1938365 | C46: =IFERROR(__xludf.DUMMYFUNCTION("""COMPUTED_VALUE"""),1938365.0) -> 1938365 | D46: NM | E46: play hd3 | G46: positive MAD-crew - Mynarco [IOException's Extra]
B47: https://osu.ppy.sh/beatmapsets/787583#osu/1699306 | C47: =IFERROR(__xludf.DUMMYFUNCTION("""COMPUTED_VALUE"""),1699306.0) -> 1699306 | D47: NM | E47: play hd3 | G47: Kobaryo - Sulyvahn [feat. USAO] [Insane]
B48: https://osu.ppy.sh/beatmapsets/359191#osu/789815 | C48: =IFERROR(__xludf.DUMMYFUNCTION("""COMPUTED_VALUE"""),789815.0) -> 789815 | D48: NM | E48: play hd3 | G48: xi - ANiMA [LV.11] | H48: another nm2
B49: https://osu.ppy.sh/beatmapsets/732280#osu/1631406 | C49: =IFERROR(__xludf.DUMMYFUNCTION("""COMPUTED_VALUE"""),1631406.0) -> 1631406 | D49: NM | E49: play hd3 | G49: aran - VOLT (USAO Remix) [Plaudible's Extra]
B50: https://osu.ppy.sh/beatmapsets/1239626#osu/2961839 | C50: =IFERROR(__xludf.DUMMYFUNCTION("""COMPUTED_VALUE"""),2961839.0) -> 2961839 | D50: DT | E50: play hd3 | G50: cinnamons x evening cinema - summertime [nathan's insane]
B51: https://osu.ppy.sh/beatmapsets/821587#osu/1737928 | C51: =IFERROR(__xludf.DUMMYFUNCTION("""COMPUTED_VALUE"""),1737928.0) -> 1737928 | D51: NM | E51: yillow | G51: Zekk - Feelsleft0ut [Acyl x toybot's Another]
B52: https://osu.ppy.sh/beatmapsets/1239841#osu/2577703 | C52: =IFERROR(__xludf.DUMMYFUNCTION("""COMPUTED_VALUE"""),2577703.0) -> 2577703 | D52: NM | E52: yillow | G52: False Noise - Space Angel [808 MIMOLETTE]
B53: https://osu.ppy.sh/beatmapsets/4907#osu/25341 | C53: =IFERROR(__xludf.DUMMYFUNCTION("""COMPUTED_VALUE"""),25341.0) -> 25341 | D53: DT | E53: yillow | G53: Crazy Loop - Love Is A Simple Thing [EEeee's Love Ain't So Simple]
B54: https://osu.ppy.sh/beatmapsets/1228132#osu/2565268 | C54: =IFERROR(__xludf.DUMMYFUNCTION("""COMPUTED_VALUE"""),2565268.0) -> 2565268 | D54: HD | E54: yillow | G54: Camellia - Wolves Standing Towards Enemies [Insane]
B55: https://osu.ppy.sh/beatmapsets/1842709#osu/3802071 | C55: =IFERROR(__xludf.DUMMYFUNCTION("""COMPUTED_VALUE"""),3802071.0) -> 3802071 | D55: NM | E55: yillow | G55: john - Utage [Dabbe's Hidden Insane]
B56: https://osu.ppy.sh/beatmapsets/1804775#osu/3700933 | C56: =IFERROR(__xludf.DUMMYFUNCTION("""COMPUTED_VALUE"""),3700933.0) -> 3700933 | D56: FM | E56: yillow | G56: PRXSXNT FXTURE - SMOKED OUT [X]
B57: https://osu.ppy.sh/b/3853742 | C57: =IFERROR(__xludf.DUMMYFUNCTION("""COMPUTED_VALUE"""),3853742.0) -> 3853742 | D57: FM | E57: yillow | G57: lapix - Flamenco House [JeZalt's Another]
B58: https://osu.ppy.sh/b/3039329 | C58: =IFERROR(__xludf.DUMMYFUNCTION("""COMPUTED_VALUE"""),3039329.0) -> 3039329 | D58: NM | E58: yillow | G58: 0rb1t - I Lost [SOSC Summer 2021 GFs]
B59: https://osu.ppy.sh/beatmapsets/1634320#osu/3714369 | C59: =IFERROR(__xludf.DUMMYFUNCTION("""COMPUTED_VALUE"""),3714369.0) -> 3714369 | D59: NM | E59: yillow | G59: daisan - -+ [Light Another]
B60: https://osu.ppy.sh/b/2690998 | C60: =IFERROR(__xludf.DUMMYFUNCTION("""COMPUTED_VALUE"""),2690998.0) -> 2690998 | D60: NM | E60: yillow | G60: FROZEN QUALIA - Aisubeki Hibi e [Tsumia's Extra]
B61: https://osu.ppy.sh/beatmapsets/1547170#osu/3461206 | C61: =IFERROR(__xludf.DUMMYFUNCTION("""COMPUTED_VALUE"""),3461206.0) -> 3461206 | D61: NM | E61: yillow | G61: Hatsuki Yura - Witchcraft [mogumogu]
B62: https://osu.ppy.sh/beatmapsets/1090567#osu/2279885 | C62: =IFERROR(__xludf.DUMMYFUNCTION("""COMPUTED_VALUE"""),2279885.0) -> 2279885 | D62: NM | E62: yillow | G62: ORESAMA - Hotohashiru [Extra]
B63: https://osu.ppy.sh/beatmapsets/128931#osu/847315 | C63: =IFERROR(__xludf.DUMMYFUNCTION("""COMPUTED_VALUE"""),847315.0) -> 847315 | D63: DT | E63: play hd3 | G63: Feint - Tower Of Heaven (You Are Slaves) [Hyper]
B64: https://osu.ppy.sh/beatmapsets/28257#osu/99407 | C64: =IFERROR(__xludf.DUMMYFUNCTION("""COMPUTED_VALUE"""),99407.0) -> 99407 | D64: FM | E64: play hd3 | G64: Shihoko Hirata - Pursuing My True Self [KIRBY Mix]
B65: https://osu.ppy.sh/beatmapsets/16371#osu/58701 | C65: =IFERROR(__xludf.DUMMYFUNCTION("""COMPUTED_VALUE"""),58701.0) -> 58701 | D65: FM | E65: yillow | G65: IOSYS - Midnight Lightning Bolt [Lunatic]
B66: https://osu.ppy.sh/beatmapsets/749304#osu/1707909 | C66: =IFERROR(__xludf.DUMMYFUNCTION("""COMPUTED_VALUE"""),1707909.0) -> 1707909 | D66: DT | E66: play hd3 | G66: USAO - FREEDOM (Extended Mix) [Hard]
B67: https://osu.ppy.sh/beatmapsets/1817644#osu/3772514 | C67: =IFERROR(__xludf.DUMMYFUNCTION("""COMPUTED_VALUE"""),3772514.0) -> 3772514 | D67: DT | E67: yillow | G67: KARUT - Glitch Street [Zekk's Hard]
B68: https://osu.ppy.sh/beatmapsets/396370#osu/862338 | C68: =IFERROR(__xludf.DUMMYFUNCTION("""COMPUTED_VALUE"""),862338.0) -> 862338 | D68: TB | E68: play hd3 | G68: Camellia - d:for the DELTA [Delirium]
B69: https://osu.ppy.sh/beatmapsets/1809604#osu/3711612 | C69: =IFERROR(__xludf.DUMMYFUNCTION("""COMPUTED_VALUE"""),3711612.0) -> 3711612 | D69: NM | E69: play hd3 | G69: Kotoha - Cat Loving [bongo's Insane]
B70: https://osu.ppy.sh/beatmapsets/1130251#osu/2519731 | C70: =IFERROR(__xludf.DUMMYFUNCTION("""COMPUTED_VALUE"""),2519731.0) -> 2519731 | D70: DT | E70: play hd3 | G70: Inui Toko - Kimagure Romantic [Light Insane]
B71: https://osu.ppy.sh/beatmapsets/408745#osu/1035068 | C71: =IFERROR(__xludf.DUMMYFUNCTION("""COMPUTED_VALUE"""),1035068.0) -> 1035068 | D71: DT | G71: Hana - Gekka Jasmine (2014ver.) [Gyro's Light Insane]

Sheet Import Range Template - Quals o
A2: c | D2: GRANDFINALS | F2: Ave. SR <> AVE. LENGTH | L2: - mAPPOOL PACK -
D4: Banner | E4: Mod | F4: Artist - Song [Difficulty] | G4: SR | H4: BPM | I4: Length | J4: CS | K4: AR | L4: OD | M4: Mapper | N4: ID
E5: c
A27: c | D27: FINALS | F27: Ave. SR <> AVE. LENGTH | L27: - mAPPOOL PACK -
D29: Banner | E29: Mod | F29: Artist - Song [Difficulty] | G29: SR | H29: BPM | I29: Length | J29: CS | K29: AR | L29: OD | M29: Mapper | N29: ID
E30: c
A53: c | D53: SEMIFINALS | F53: Ave. SR <> AVE. LENGTH | L53: - mAPPOOL PACK -
D55: Banner | E55: Mod | F55: Artist - Song [Difficulty] | G55: SR | H55: BPM | I55: Length | J55: CS | K55: AR | L55: OD | M55: Mapper | N55: ID
E56: c
A79: c | D79: QUARTERFINALS | F79: Ave. SR <> AVE. LENGTH | L79: - mAPPOOL PACK -
D81: Banner | E81: Mod | F81: Artist - Song [Difficulty] | G81: SR | H81: BPM | I81: Length | J81: CS | K81: AR | L81: OD | M81: Mapper | N81: ID
E82: c
A105: c | D105: RO16 | F105: Ave. SR <> AVE. LENGTH | L105: - mAPPOOL PACK -
D107: Banner | E107: Mod | F107: Artist - Song [Difficulty] | G107: SR | H107: BPM | I107: Length | J107: CS | K107: AR | L107: OD | M107: Mapper | N107: ID
E108: c
A131: c | D131: RO32 | F131: Ave. SR <> AVE. LENGTH | L131: - mAPPOOL PACK -
D133: Banner | E133: Mod | F133: Artist - Song [Difficulty] | G133: SR | H133: BPM | I133: Length | J133: CS | K133: AR | L133: OD | M133: Mapper | N133: ID
E134: c
F156: c
A157: c | D157: Qualifiers | F157: Ave. SR <> AVE. LENGTH | L157: - mAPPOOL PACK -
D159: Banner | E159: Mod | F159: Artist - Song [Difficulty] | G159: SR | H159: BPM | I159: Length | J159: CS | K159: AR | L159: OD | M159: Mapper | N159: ID
E160: c

Sheet --- auto stuffs  archived ---

Sheet Instructions
B2: Video Tutorial | E2: =IMAGE("https://i.imgur.com/V5nuXji.png")
B4: A menu called "Mappooling Manager" will appear at the top of the screen after the sheet has finished loading
B5: 1 | C5: Set all of your required values in the "Settings" sheet. Comments are left for every relevant field, please take a look at them!
B6: 2 | C6: Run the "Authorize Scripts" menu item
B7: 3 | C7: Run the "API Key > Add API Key" menu item
B8: 4 | C8: Run the "Mappools > Generate mappool sheets" menu item
B9: 5 | C9: Enter map links in the "Suggestions" side of a stage mappool sheet
B10: 6 | C10: Enter map IDs in the "Pool Assembly" side to set the maps for the finished mappool
B12: 7 | C12: Add a mappool design (refer to video tutorial)
C13: Example Designs Sheet
B15: 8 | C15: Publicize your sheet

Sheet FinalPublic Sheet
B2: Releasing your mappool to the public
B4: 1 | C4: Check the video tutorial on how to import and customize a mappool design
B5: 2 | C5: Right click your final design sheet at the bottom > Copy to, and copy to your public sheet
B6: 3 | C6: On the public sheet, press Ctrl+A, then the Delete key to clear all cell text
B7: 4 | C7: Go to the cell A1 (top left) and use =IMPORTRANGE("<mappool sheet link>", "Mappool!A1:O150") and adjust the ranges accordingly depending on what the final sheet is called
B9: 5 | C9: Any changes to the pool assembly will be reflected to the public sheet instantly. I recommend you adjust the IMPORTRANGE range parameter whenever you want to release a new pool.
B11: 6 | C11: If you use the IMPORTRANGE method, then your mappooling sheet URL will be exposed in the function. Make sure to use E-Mail protection at all times!

Sheet Export
B2: Simple export format for the ref sheet template or for other usecases
B4: Ref sheet format | F4: Custom data columns (unhide columns for more)
B5: Stage | C5: Mod | D5: ID | E5: Map | F5: string_url | G5: artist | H5: bpm
B6: =IFERROR(__xludf.DUMMYFUNCTION("TRANSPOSE(SPLIT(JOIN("","",ArrayFormula(REPT(Settings!E3:E12&"","",Settings!Q3:Q12))),"",""))"),"Qualifiers") -> Qualifiers | C6: =IFERROR(__xludf.DUMMYFUNCTION("IFERROR(MAP({""L"",""K""},LAMBDA(col,TRANSPOSE(SPLIT(JOIN("","",MAP(FILTER(Settings!F3:F12,Settings!D3:D12),FILTER(Settings!Q3:Q12,Settings!D3:D12),LAMBDA(stage,count,JOIN("","",ARRAY_CONSTRAIN(INDIRECT(stage&""!""&col&""5:""&col),count,1))))),"","")))))"),"NM1") -> NM1 | D6: =IFERROR(__xludf.DUMMYFUNCTION("""COMPUTED_VALUE"""),3924030.0) -> 3924030 | E6: {=IFERROR(MAPDATA(D6:D624,"string_url"),"")} -> nonoc - Relive [Insane] | F6: {=IFERROR(MAPDATA(D6:D624,F5:U5),"")} -> nonoc - Relive [Insane] | G6: nonoc | H6: 196
B7: =IFERROR(__xludf.DUMMYFUNCTION("""COMPUTED_VALUE"""),"Qualifiers") -> Qualifiers | C7: =IFERROR(__xludf.DUMMYFUNCTION("""COMPUTED_VALUE"""),"NM2") -> NM2 | D7: =IFERROR(__xludf.DUMMYFUNCTION("""COMPUTED_VALUE"""),908887.0) -> 908887 | E7: void - Crisscrosser [Insane] | F7: void - Crisscrosser [Insane] | G7: void | H7: 170
B8: =IFERROR(__xludf.DUMMYFUNCTION("""COMPUTED_VALUE"""),"Qualifiers") -> Qualifiers | C8: =IFERROR(__xludf.DUMMYFUNCTION("""COMPUTED_VALUE"""),"NM3") -> NM3 | D8: =IFERROR(__xludf.DUMMYFUNCTION("""COMPUTED_VALUE"""),3035501.0) -> 3035501 | E8: Sangatsu no Phantasia - Koufuku na Wagamama [Insane] | F8: Sangatsu no Phantasia - Koufuku na Wagamama [Insane] | G8: Sangatsu no Phantasia | H8: 135
B9: =IFERROR(__xludf.DUMMYFUNCTION("""COMPUTED_VALUE"""),"Qualifiers") -> Qualifiers | C9: =IFERROR(__xludf.DUMMYFUNCTION("""COMPUTED_VALUE"""),"NM4") -> NM4 | D9: =IFERROR(__xludf.DUMMYFUNCTION("""COMPUTED_VALUE"""),3737825.0) -> 3737825 | E9: PSYQUI - Education [sorciere's Insane] | F9: PSYQUI - Education [sorciere's Insane] | G9: PSYQUI | H9: 180
B10: =IFERROR(__xludf.DUMMYFUNCTION("""COMPUTED_VALUE"""),"Qualifiers") -> Qualifiers | C10: =IFERROR(__xludf.DUMMYFUNCTION("""COMPUTED_VALUE"""),"HD1") -> HD1 | D10: =IFERROR(__xludf.DUMMYFUNCTION("""COMPUTED_VALUE"""),2094462.0) -> 2094462 | E10: Ax feat. Natsukawa Yoko - Sakimori Renka [Insane] | F10: Ax feat. Natsukawa Yoko - Sakimori Renka [Insane] | G10: Ax feat. Natsukawa Yoko | H10: 170
B11: =IFERROR(__xludf.DUMMYFUNCTION("""COMPUTED_VALUE"""),"Qualifiers") -> Qualifiers | C11: =IFERROR(__xludf.DUMMYFUNCTION("""COMPUTED_VALUE"""),"HD2") -> HD2 | D11: =IFERROR(__xludf.DUMMYFUNCTION("""COMPUTED_VALUE"""),2619929.0) -> 2619929 | E11: Amane - BOOZEHOUND [Down's Insane] | F11: Amane - BOOZEHOUND [Down's Insane] | G11: Amane | H11: 165
B12: =IFERROR(__xludf.DUMMYFUNCTION("""COMPUTED_VALUE"""),"Qualifiers") -> Qualifiers | C12: =IFERROR(__xludf.DUMMYFUNCTION("""COMPUTED_VALUE"""),"HR1") -> HR1 | D12: =IFERROR(__xludf.DUMMYFUNCTION("""COMPUTED_VALUE"""),2027623.0) -> 2027623 | E12: THE ORAL CIGARETTES - Wagamama de Gomakasanaide [Panda & Melwoine's Insane] | F12: THE ORAL CIGARETTES - Wagamama de Gomakasanaide [Panda & Melwoine's Insane] | G12: THE ORAL CIGARETTES | H12: 142
B13: =IFERROR(__xludf.DUMMYFUNCTION("""COMPUTED_VALUE"""),"Qualifiers") -> Qualifiers | C13: =IFERROR(__xludf.DUMMYFUNCTION("""COMPUTED_VALUE"""),"HR2") -> HR2 | D13: =IFERROR(__xludf.DUMMYFUNCTION("""COMPUTED_VALUE"""),1523138.0) -> 1523138 | E13: Kajiura Yuki - Sis puella magica! [Tea Party] | F13: Kajiura Yuki - Sis puella magica! [Tea Party] | G13: Kajiura Yuki | H13: 155.42
B14: =IFERROR(__xludf.DUMMYFUNCTION("""COMPUTED_VALUE"""),"Qualifiers") -> Qualifiers | C14: =IFERROR(__xludf.DUMMYFUNCTION("""COMPUTED_VALUE"""),"DT1") -> DT1 | D14: =IFERROR(__xludf.DUMMYFUNCTION("""COMPUTED_VALUE"""),4105349.0) -> 4105349 | E14: ICHIKO - YOU'RE THE ONE [ANDREA & ASUKO'S HARD] | F14: ICHIKO - YOU'RE THE ONE [ANDREA & ASUKO'S HARD] | G14: ICHIKO | H14: 157
B15: =IFERROR(__xludf.DUMMYFUNCTION("""COMPUTED_VALUE"""),"Qualifiers") -> Qualifiers | C15: =IFERROR(__xludf.DUMMYFUNCTION("""COMPUTED_VALUE"""),"DT2") -> DT2 | D15: =IFERROR(__xludf.DUMMYFUNCTION("""COMPUTED_VALUE"""),3533589.0) -> 3533589 | E15: DIANA - Beethoven Virus [Aranel's Hard] | F15: DIANA - Beethoven Virus [Aranel's Hard] | G15: DIANA | H15: 156
B16: =IFERROR(__xludf.DUMMYFUNCTION("""COMPUTED_VALUE"""),"Round of 32") -> Round of 32 | C16: =IFERROR(__xludf.DUMMYFUNCTION("""COMPUTED_VALUE"""),"NM1") -> NM1 | D16: =IFERROR(__xludf.DUMMYFUNCTION("""COMPUTED_VALUE"""),2277989.0) -> 2277989 | E16: Hazuki - Uso to Shinjitsu [Insane] | F16: Hazuki - Uso to Shinjitsu [Insane] | G16: Hazuki | H16: 190
B17: =IFERROR(__xludf.DUMMYFUNCTION("""COMPUTED_VALUE"""),"Round of 32") -> Round of 32 | C17: =IFERROR(__xludf.DUMMYFUNCTION("""COMPUTED_VALUE"""),"NM2") -> NM2 | D17: =IFERROR(__xludf.DUMMYFUNCTION("""COMPUTED_VALUE"""),3297107.0) -> 3297107 | E17: Jun Kuroda - Terpsichore [Dancer's Delight] | F17: Jun Kuroda - Terpsichore [Dancer's Delight] | G17: Jun Kuroda | H17: 181
B18: =IFERROR(__xludf.DUMMYFUNCTION("""COMPUTED_VALUE"""),"Round of 32") -> Round of 32 | C18: =IFERROR(__xludf.DUMMYFUNCTION("""COMPUTED_VALUE"""),"NM3") -> NM3 | D18: =IFERROR(__xludf.DUMMYFUNCTION("""COMPUTED_VALUE"""),2440455.0) -> 2440455 | E18: PUP - Anaphylaxis [Insane] | F18: PUP - Anaphylaxis [Insane] | G18: PUP | H18: 252
B19: =IFERROR(__xludf.DUMMYFUNCTION("""COMPUTED_VALUE"""),"Round of 32") -> Round of 32 | C19: =IFERROR(__xludf.DUMMYFUNCTION("""COMPUTED_VALUE"""),"NM4") -> NM4 | D19: =IFERROR(__xludf.DUMMYFUNCTION("""COMPUTED_VALUE"""),3248876.0) -> 3248876 | E19: ISOMERZ (DJ Raisei + seatrus) - Symmetric [BOUYAAA's Insane] | F19: ISOMERZ (DJ Raisei + seatrus) - Symmetric [BOUYAAA's Insane] | G19: ISOMERZ (DJ Raisei + seatrus) | H19: 200
B20: =IFERROR(__xludf.DUMMYFUNCTION("""COMPUTED_VALUE"""),"Round of 32") -> Round of 32 | C20: =IFERROR(__xludf.DUMMYFUNCTION("""COMPUTED_VALUE"""),"NM5") -> NM5 | D20: =IFERROR(__xludf.DUMMYFUNCTION("""COMPUTED_VALUE"""),1989991.0) -> 1989991 | E20: Pastel*Palettes - Happy Synthesizer [Insane] | F20: Pastel*Palettes - Happy Synthesizer [Insane] | G20: Pastel*Palettes | H20: 127
B21: =IFERROR(__xludf.DUMMYFUNCTION("""COMPUTED_VALUE"""),"Round of 32") -> Round of 32 | C21: =IFERROR(__xludf.DUMMYFUNCTION("""COMPUTED_VALUE"""),"HD1") -> HD1 | D21: =IFERROR(__xludf.DUMMYFUNCTION("""COMPUTED_VALUE"""),3280686.0) -> 3280686 | E21: Tsumiki - phony [Hatsune Miku's Insane] | F21: Tsumiki - phony [Hatsune Miku's Insane] | G21: Tsumiki | H21: 170
B22: =IFERROR(__xludf.DUMMYFUNCTION("""COMPUTED_VALUE"""),"Round of 32") -> Round of 32 | C22: =IFERROR(__xludf.DUMMYFUNCTION("""COMPUTED_VALUE"""),"HD2") -> HD2 | D22: =IFERROR(__xludf.DUMMYFUNCTION("""COMPUTED_VALUE"""),134141.0) -> 134141 | E22: P*Light - Poppin' Shower [Hyper] | F22: P*Light - Poppin' Shower [Hyper] | G22: P*Light | H22: 175
B23: =IFERROR(__xludf.DUMMYFUNCTION("""COMPUTED_VALUE"""),"Round of 32") -> Round of 32 | C23: =IFERROR(__xludf.DUMMYFUNCTION("""COMPUTED_VALUE"""),"HR1") -> HR1 | D23: =IFERROR(__xludf.DUMMYFUNCTION("""COMPUTED_VALUE"""),2659337.0) -> 2659337 | E23: Omoi - Teo [waji's Insane] | F23: Omoi - Teo [waji's Insane] | G23: Omoi | H23: 185
B24: =IFERROR(__xludf.DUMMYFUNCTION("""COMPUTED_VALUE"""),"Round of 32") -> Round of 32 | C24: =IFERROR(__xludf.DUMMYFUNCTION("""COMPUTED_VALUE"""),"HR2") -> HR2 | D24: =IFERROR(__xludf.DUMMYFUNCTION("""COMPUTED_VALUE"""),2110801.0) -> 2110801 | E24: Silentroom - NULCTRL [Pattern 03a "exHRD" LMT] | F24: Silentroom - NULCTRL [Pattern 03a "exHRD" LMT] | G24: Silentroom | H24: 100
B25: =IFERROR(__xludf.DUMMYFUNCTION("""COMPUTED_VALUE"""),"Round of 32") -> Round of 32 | C25: =IFERROR(__xludf.DUMMYFUNCTION("""COMPUTED_VALUE"""),"DT1") -> DT1 | D25: =IFERROR(__xludf.DUMMYFUNCTION("""COMPUTED_VALUE"""),2044893.0) -> 2044893 | E25: mafumafu - Moudoku ga Osou [Hard] | F25: mafumafu - Moudoku ga Osou [Hard] | G25: mafumafu | H25: 156
B26: =IFERROR(__xludf.DUMMYFUNCTION("""COMPUTED_VALUE"""),"Round of 32") -> Round of 32 | C26: =IFERROR(__xludf.DUMMYFUNCTION("""COMPUTED_VALUE"""),"DT2") -> DT2 | D26: =IFERROR(__xludf.DUMMYFUNCTION("""COMPUTED_VALUE"""),2366848.0) -> 2366848 | E26: ARForest - Aoba [Hard] | F26: ARForest - Aoba [Hard] | G26: ARForest | H26: 150
B27: =IFERROR(__xludf.DUMMYFUNCTION("""COMPUTED_VALUE"""),"Round of 32") -> Round of 32 | C27: =IFERROR(__xludf.DUMMYFUNCTION("""COMPUTED_VALUE"""),"DT3") -> DT3 | D27: =IFERROR(__xludf.DUMMYFUNCTION("""COMPUTED_VALUE"""),3396305.0) -> 3396305 | E27: xi - Mirage Garden [PaRaDogi's Hard] | F27: xi - Mirage Garden [PaRaDogi's Hard] | G27: xi | H27: 156
B28: =IFERROR(__xludf.DUMMYFUNCTION("""COMPUTED_VALUE"""),"Round of 32") -> Round of 32 | C28: =IFERROR(__xludf.DUMMYFUNCTION("""COMPUTED_VALUE"""),"FM1") -> FM1 | D28: =IFERROR(__xludf.DUMMYFUNCTION("""COMPUTED_VALUE"""),846261.0) -> 846261 | E28: Shawn Wasabi - Marble Soda [Narcissu's Insane] | F28: Shawn Wasabi - Marble Soda [Narcissu's Insane] | G28: Shawn Wasabi | H28: 168
B29: =IFERROR(__xludf.DUMMYFUNCTION("""COMPUTED_VALUE"""),"Round of 32") -> Round of 32 | C29: =IFERROR(__xludf.DUMMYFUNCTION("""COMPUTED_VALUE"""),"FM2") -> FM2 | D29: =IFERROR(__xludf.DUMMYFUNCTION("""COMPUTED_VALUE"""),3743202.0) -> 3743202 | E29: -45 - Total Eclipse of The Sun [Hard] | F29: -45 - Total Eclipse of The Sun [Hard] | G29: -45 | H29: 120
B30: =IFERROR(__xludf.DUMMYFUNCTION("""COMPUTED_VALUE"""),"Round of 32") -> Round of 32 | C30: =IFERROR(__xludf.DUMMYFUNCTION("""COMPUTED_VALUE"""),"TB1") -> TB1 | D30: =IFERROR(__xludf.DUMMYFUNCTION("""COMPUTED_VALUE"""),3446761.0) -> 3446761 | E30: Ata - Euphoria [Aiq's Insane] | F30: Ata - Euphoria [Aiq's Insane] | G30: Ata | H30: 190
B31: =IFERROR(__xludf.DUMMYFUNCTION("""COMPUTED_VALUE"""),"Round of 16") -> Round of 16 | C31: =IFERROR(__xludf.DUMMYFUNCTION("""COMPUTED_VALUE"""),"NM1") -> NM1 | D31: =IFERROR(__xludf.DUMMYFUNCTION("""COMPUTED_VALUE"""),2827293.0) -> 2827293 | E31: Yorushika - Thoughtcrime [Akitoshi's Insane] | F31: Yorushika - Thoughtcrime [Akitoshi's Insane] | G31: Yorushika | H31: 200
B32: =IFERROR(__xludf.DUMMYFUNCTION("""COMPUTED_VALUE"""),"Round of 16") -> Round of 16 | C32: =IFERROR(__xludf.DUMMYFUNCTION("""COMPUTED_VALUE"""),"NM2") -> NM2 | D32: =IFERROR(__xludf.DUMMYFUNCTION("""COMPUTED_VALUE"""),2004679.0) -> 2004679 | E32: Fractal Dreamers - Gardens Under A Spring Sky [Hyper] | F32: Fractal Dreamers - Gardens Under A Spring Sky [Hyper] | G32: Fractal Dreamers | H32: 195
B33: =IFERROR(__xludf.DUMMYFUNCTION("""COMPUTED_VALUE"""),"Round of 16") -> Round of 16 | C33: =IFERROR(__xludf.DUMMYFUNCTION("""COMPUTED_VALUE"""),"NM3") -> NM3 | D33: =IFERROR(__xludf.DUMMYFUNCTION("""COMPUTED_VALUE"""),3239199.0) -> 3239199 | E33: Tsukuyomi - Dareka no Shinzou ni Nareta nara [too's Insane] | F33: Tsukuyomi - Dareka no Shinzou ni Nareta nara [too's Insane] | G33: Tsukuyomi | H33: 143
B34: =IFERROR(__xludf.DUMMYFUNCTION("""COMPUTED_VALUE"""),"Round of 16") -> Round of 16 | C34: =IFERROR(__xludf.DUMMYFUNCTION("""COMPUTED_VALUE"""),"NM4") -> NM4 | D34: =IFERROR(__xludf.DUMMYFUNCTION("""COMPUTED_VALUE"""),2794904.0) -> 2794904 | E34: sakuraburst - Glacierfall (Park Remix) [haruto x ancel's ins*ne] | F34: sakuraburst - Glacierfall (Park Remix) [haruto x ancel's ins*ne] | G34: sakuraburst | H34: 170
B35: =IFERROR(__xludf.DUMMYFUNCTION("""COMPUTED_VALUE"""),"Round of 16") -> Round of 16 | C35: =IFERROR(__xludf.DUMMYFUNCTION("""COMPUTED_VALUE"""),"NM5") -> NM5 | D35: =IFERROR(__xludf.DUMMYFUNCTION("""COMPUTED_VALUE"""),2853477.0) -> 2853477 | E35: sekai - Zange Mairi [Voice's Insane] | F35: sekai - Zange Mairi [Voice's Insane] | G35: sekai | H35: 140
B36: =IFERROR(__xludf.DUMMYFUNCTION("""COMPUTED_VALUE"""),"Round of 16") -> Round of 16 | C36: =IFERROR(__xludf.DUMMYFUNCTION("""COMPUTED_VALUE"""),"HD1") -> HD1 | D36: =IFERROR(__xludf.DUMMYFUNCTION("""COMPUTED_VALUE"""),1733441.0) -> 1733441 | E36: Police Piccadilly feat. Hatsune Miku - Kire Carry On [negusver's Insane] | F36: Police Piccadilly feat. Hatsune Miku - Kire Carry On [negusver's Insane] | G36: Police Piccadilly feat. Hatsune Miku | H36: 170
B37: =IFERROR(__xludf.DUMMYFUNCTION("""COMPUTED_VALUE"""),"Round of 16") -> Round of 16 | C37: =IFERROR(__xludf.DUMMYFUNCTION("""COMPUTED_VALUE"""),"HD2") -> HD2 | D37: =IFERROR(__xludf.DUMMYFUNCTION("""COMPUTED_VALUE"""),3460069.0) -> 3460069 | E37: Siren - Polaris [8 is not a low ar guys] | F37: Siren - Polaris [8 is not a low ar guys] | G37: Siren | H37: 174
B38: =IFERROR(__xludf.DUMMYFUNCTION("""COMPUTED_VALUE"""),"Round of 16") -> Round of 16 | C38: =IFERROR(__xludf.DUMMYFUNCTION("""COMPUTED_VALUE"""),"HR1") -> HR1 | D38: =IFERROR(__xludf.DUMMYFUNCTION("""COMPUTED_VALUE"""),1956568.0) -> 1956568 | E38: PSYQUI feat. Such - Senchimentaruhatoboi [Insane] | F38: PSYQUI feat. Such - Senchimentaruhatoboi [Insane] | G38: PSYQUI feat. Such | H38: 160
B39: =IFERROR(__xludf.DUMMYFUNCTION("""COMPUTED_VALUE"""),"Round of 16") -> Round of 16 | C39: =IFERROR(__xludf.DUMMYFUNCTION("""COMPUTED_VALUE"""),"HR2") -> HR2 | D39: =IFERROR(__xludf.DUMMYFUNCTION("""COMPUTED_VALUE"""),295650.0) -> 295650 | E39: Perfume - Laser Beam [Mixagji] | F39: Perfume - Laser Beam [Mixagji] | G39: Perfume | H39: 135
B40: =IFERROR(__xludf.DUMMYFUNCTION("""COMPUTED_VALUE"""),"Round of 16") -> Round of 16 | C40: =IFERROR(__xludf.DUMMYFUNCTION("""COMPUTED_VALUE"""),"DT1") -> DT1 | D40: =IFERROR(__xludf.DUMMYFUNCTION("""COMPUTED_VALUE"""),3446883.0) -> 3446883 | E40: Yumeno Yuki - First Time [KoldNoodl's Hard] | F40: Yumeno Yuki - First Time [KoldNoodl's Hard] | G40: Yumeno Yuki | H40: 129
B41: =IFERROR(__xludf.DUMMYFUNCTION("""COMPUTED_VALUE"""),"Round of 16") -> Round of 16 | C41: =IFERROR(__xludf.DUMMYFUNCTION("""COMPUTED_VALUE"""),"DT2") -> DT2 | D41: =IFERROR(__xludf.DUMMYFUNCTION("""COMPUTED_VALUE"""),1521209.0) -> 1521209 | E41: YUC'e - Future Candy [Hard] | F41: YUC'e - Future Candy [Hard] | G41: YUC'e | H41: 180
B42: =IFERROR(__xludf.DUMMYFUNCTION("""COMPUTED_VALUE"""),"Round of 16") -> Round of 16 | C42: =IFERROR(__xludf.DUMMYFUNCTION("""COMPUTED_VALUE"""),"DT3") -> DT3 | D42: =IFERROR(__xludf.DUMMYFUNCTION("""COMPUTED_VALUE"""),3616100.0) -> 3616100 | E42: tarolabo - eth ken [hard] | F42: tarolabo - eth ken [hard] | G42: tarolabo | H42: 126
B43: =IFERROR(__xludf.DUMMYFUNCTION("""COMPUTED_VALUE"""),"Round of 16") -> Round of 16 | C43: =IFERROR(__xludf.DUMMYFUNCTION("""COMPUTED_VALUE"""),"FM1") -> FM1 | D43: =IFERROR(__xludf.DUMMYFUNCTION("""COMPUTED_VALUE"""),2151207.0) -> 2151207 | E43: OISHII - ONIGIRI FREEWAY [LUKAS' INSANE] | F43: OISHII - ONIGIRI FREEWAY [LUKAS' INSANE] | G43: OISHII | H43: 210
B44: =IFERROR(__xludf.DUMMYFUNCTION("""COMPUTED_VALUE"""),"Round of 16") -> Round of 16 | C44: =IFERROR(__xludf.DUMMYFUNCTION("""COMPUTED_VALUE"""),"FM2") -> FM2 | D44: =IFERROR(__xludf.DUMMYFUNCTION("""COMPUTED_VALUE"""),417898.0) -> 417898 | E44: Giga-P - Electric Angel [Sonnyc's Insane] | F44: Giga-P - Electric Angel [Sonnyc's Insane] | G44: Giga-P | H44: 150
B45: =IFERROR(__xludf.DUMMYFUNCTION("""COMPUTED_VALUE"""),"Round of 16") -> Round of 16 | C45: =IFERROR(__xludf.DUMMYFUNCTION("""COMPUTED_VALUE"""),"TB1") -> TB1 | D45: =IFERROR(__xludf.DUMMYFUNCTION("""COMPUTED_VALUE"""),1857415.0) -> 1857415 | E45: Au5 - Moonland [Collab Another] | F45: Au5 - Moonland [Collab Another] | G45: Au5 | H45: 170
B46: =IFERROR(__xludf.DUMMYFUNCTION("""COMPUTED_VALUE"""),"Quarterfinals") -> Quarterfinals | C46: =IFERROR(__xludf.DUMMYFUNCTION("""COMPUTED_VALUE"""),"NM1") -> NM1 | D46: =IFERROR(__xludf.DUMMYFUNCTION("""COMPUTED_VALUE"""),1965654.0) -> 1965654 | E46: Sangatsu no Phantasia - Pink Lemonade [Insane] | F46: Sangatsu no Phantasia - Pink Lemonade [Insane] | G46: Sangatsu no Phantasia | H46: 191
B47: =IFERROR(__xludf.DUMMYFUNCTION("""COMPUTED_VALUE"""),"Quarterfinals") -> Quarterfinals | C47: =IFERROR(__xludf.DUMMYFUNCTION("""COMPUTED_VALUE"""),"NM2") -> NM2 | D47: =IFERROR(__xludf.DUMMYFUNCTION("""COMPUTED_VALUE"""),1838159.0) -> 1838159 | E47: Thaehan - Doki-Doki [rockstarrzz' Insane] | F47: Thaehan - Doki-Doki [rockstarrzz' Insane] | G47: Thaehan | H47: 180
B48: =IFERROR(__xludf.DUMMYFUNCTION("""COMPUTED_VALUE"""),"Quarterfinals") -> Quarterfinals | C48: =IFERROR(__xludf.DUMMYFUNCTION("""COMPUTED_VALUE"""),"NM3") -> NM3 | D48: =IFERROR(__xludf.DUMMYFUNCTION("""COMPUTED_VALUE"""),2568756.0) -> 2568756 | E48: Meguro Shoji feat. Lyn - Last Surprise -Scramble- [Expert] | F48: Meguro Shoji feat. Lyn - Last Surprise -Scramble- [Expert] | G48: Meguro Shoji feat. Lyn | H48: 123
B49: =IFERROR(__xludf.DUMMYFUNCTION("""COMPUTED_VALUE"""),"Quarterfinals") -> Quarterfinals | C49: =IFERROR(__xludf.DUMMYFUNCTION("""COMPUTED_VALUE"""),"NM4") -> NM4 | D49: =IFERROR(__xludf.DUMMYFUNCTION("""COMPUTED_VALUE"""),3341368.0) -> 3341368 | E49: Nekomata Master+ - squall [0pp's Insane (Tournament Edit)] | F49: Nekomata Master+ - squall [0pp's Insane (Tournament Edit)] | G49: Nekomata Master+ | H49: 190
B50: =IFERROR(__xludf.DUMMYFUNCTION("""COMPUTED_VALUE"""),"Quarterfinals") -> Quarterfinals | C50: =IFERROR(__xludf.DUMMYFUNCTION("""COMPUTED_VALUE"""),"NM5") -> NM5 | D50: =IFERROR(__xludf.DUMMYFUNCTION("""COMPUTED_VALUE"""),4215637.0) -> 4215637 | E50: the Art of Mankind - Unexisted [Insane] | F50: the Art of Mankind - Unexisted [Insane] | G50: the Art of Mankind | H50: 217
B51: =IFERROR(__xludf.DUMMYFUNCTION("""COMPUTED_VALUE"""),"Quarterfinals") -> Quarterfinals | C51: =IFERROR(__xludf.DUMMYFUNCTION("""COMPUTED_VALUE"""),"NM6") -> NM6 | D51: =IFERROR(__xludf.DUMMYFUNCTION("""COMPUTED_VALUE"""),3821597.0) -> 3821597 | E51: Franz Ferdinand - This Fffire (TV Size) [enri's iNnnsane] | F51: Franz Ferdinand - This Fffire (TV Size) [enri's iNnnsane] | G51: Franz Ferdinand | H51: 146.5
B52: =IFERROR(__xludf.DUMMYFUNCTION("""COMPUTED_VALUE"""),"Quarterfinals") -> Quarterfinals | C52: =IFERROR(__xludf.DUMMYFUNCTION("""COMPUTED_VALUE"""),"HD1") -> HD1 | D52: =IFERROR(__xludf.DUMMYFUNCTION("""COMPUTED_VALUE"""),2671048.0) -> 2671048 | E52: Usada Pekora - Discommunication Alien [Ayyken's Another] | F52: Usada Pekora - Discommunication Alien [Ayyken's Another] | G52: Usada Pekora | H52: 170
B53: =IFERROR(__xludf.DUMMYFUNCTION("""COMPUTED_VALUE"""),"Quarterfinals") -> Quarterfinals | C53: =IFERROR(__xludf.DUMMYFUNCTION("""COMPUTED_VALUE"""),"HD2") -> HD2 | D53: =IFERROR(__xludf.DUMMYFUNCTION("""COMPUTED_VALUE"""),105978.0) -> 105978 | E53: BRZion - Game Brain [Insane] | F53: BRZion - Game Brain [Insane] | G53: BRZion | H53: 190
B54: =IFERROR(__xludf.DUMMYFUNCTION("""COMPUTED_VALUE"""),"Quarterfinals") -> Quarterfinals | C54: =IFERROR(__xludf.DUMMYFUNCTION("""COMPUTED_VALUE"""),"HD3") -> HD3 | D54: =IFERROR(__xludf.DUMMYFUNCTION("""COMPUTED_VALUE"""),1491793.0) -> 1491793 | E54: succducc - me & u [sing's insane] | F54: succducc - me & u [sing's insane] | G54: succducc | H54: 160
B55: =IFERROR(__xludf.DUMMYFUNCTION("""COMPUTED_VALUE"""),"Quarterfinals") -> Quarterfinals | C55: =IFERROR(__xludf.DUMMYFUNCTION("""COMPUTED_VALUE"""),"HR1") -> HR1 | D55: =IFERROR(__xludf.DUMMYFUNCTION("""COMPUTED_VALUE"""),3913591.0) -> 3913591 | E55: kessoku band - Guitar to Kodoku to Aoi Hoshi [kuuti's Insane] | F55: kessoku band - Guitar to Kodoku to Aoi Hoshi [kuuti's Insane] | G55: kessoku band | H55: 193
B56: =IFERROR(__xludf.DUMMYFUNCTION("""COMPUTED_VALUE"""),"Quarterfinals") -> Quarterfinals | C56: =IFERROR(__xludf.DUMMYFUNCTION("""COMPUTED_VALUE"""),"HR2") -> HR2 | D56: =IFERROR(__xludf.DUMMYFUNCTION("""COMPUTED_VALUE"""),37750.0) -> 37750 | E56: Cranky - Luvin' You [Alazy's Another] | F56: Cranky - Luvin' You [Alazy's Another] | G56: Cranky | H56: 160
B57: =IFERROR(__xludf.DUMMYFUNCTION("""COMPUTED_VALUE"""),"Quarterfinals") -> Quarterfinals | C57: =IFERROR(__xludf.DUMMYFUNCTION("""COMPUTED_VALUE"""),"HR3") -> HR3 | D57: =IFERROR(__xludf.DUMMYFUNCTION("""COMPUTED_VALUE"""),3248255.0) -> 3248255 | E57: NICODE & M2U - Predawn [Mixagji's Insane] | F57: NICODE & M2U - Predawn [Mixagji's Insane] | G57: NICODE & M2U | H57: 140
B58: =IFERROR(__xludf.DUMMYFUNCTION("""COMPUTED_VALUE"""),"Quarterfinals") -> Quarterfinals | C58: =IFERROR(__xludf.DUMMYFUNCTION("""COMPUTED_VALUE"""),"DT1") -> DT1 | D58: =IFERROR(__xludf.DUMMYFUNCTION("""COMPUTED_VALUE"""),674080.0) -> 674080 | E58: Reol - Asymmetry [pk's Hard] | F58: Reol - Asymmetry [pk's Hard] | G58: Reol | H58: 184
B59: =IFERROR(__xludf.DUMMYFUNCTION("""COMPUTED_VALUE"""),"Quarterfinals") -> Quarterfinals | C59: =IFERROR(__xludf.DUMMYFUNCTION("""COMPUTED_VALUE"""),"DT2") -> DT2 | D59: =IFERROR(__xludf.DUMMYFUNCTION("""COMPUTED_VALUE"""),3299370.0) -> 3299370 | E59: -45 - System Sun [Hard] | F59: -45 - System Sun [Hard] | G59: -45 | H59: 152
B60: =IFERROR(__xludf.DUMMYFUNCTION("""COMPUTED_VALUE"""),"Quarterfinals") -> Quarterfinals | C60: =IFERROR(__xludf.DUMMYFUNCTION("""COMPUTED_VALUE"""),"DT3") -> DT3 | D60: =IFERROR(__xludf.DUMMYFUNCTION("""COMPUTED_VALUE"""),3822599.0) -> 3822599 | E60: Nekomata Master+ - chaos eater -IIDX edition- [HARD] | F60: Nekomata Master+ - chaos eater -IIDX edition- [HARD] | G60: Nekomata Master+ | H60: 210
B61: =IFERROR(__xludf.DUMMYFUNCTION("""COMPUTED_VALUE"""),"Quarterfinals") -> Quarterfinals | C61: =IFERROR(__xludf.DUMMYFUNCTION("""COMPUTED_VALUE"""),"FM1") -> FM1 | D61: =IFERROR(__xludf.DUMMYFUNCTION("""COMPUTED_VALUE"""),3274886.0) -> 3274886 | E61: Two Door Cinema Club - Cigarettes in the Theatre [Insane] | F61: Two Door Cinema Club - Cigarettes in the Theatre [Insane] | G61: Two Door Cinema Club | H61: 169
B62: =IFERROR(__xludf.DUMMYFUNCTION("""COMPUTED_VALUE"""),"Quarterfinals") -> Quarterfinals | C62: =IFERROR(__xludf.DUMMYFUNCTION("""COMPUTED_VALUE"""),"FM2") -> FM2 | D62: =IFERROR(__xludf.DUMMYFUNCTION("""COMPUTED_VALUE"""),3804111.0) -> 3804111 | E62: Hiiragi Magnetite - Marshall Maximizer feat. KAFU [Hyper] | F62: Hiiragi Magnetite - Marshall Maximizer feat. KAFU [Hyper] | G62: Hiiragi Magnetite | H62: 190
B63: =IFERROR(__xludf.DUMMYFUNCTION("""COMPUTED_VALUE"""),"Quarterfinals") -> Quarterfinals | C63: =IFERROR(__xludf.DUMMYFUNCTION("""COMPUTED_VALUE"""),"TB1") -> TB1 | D63: =IFERROR(__xludf.DUMMYFUNCTION("""COMPUTED_VALUE"""),577517.0) -> 577517 | E63: Halozy - Genryuu Kaiko [Melody of Sanzu] | F63: Halozy - Genryuu Kaiko [Melody of Sanzu] | G63: Halozy | H63: 173
B64: =IFERROR(__xludf.DUMMYFUNCTION("""COMPUTED_VALUE"""),"Semifinals") -> Semifinals | C64: =IFERROR(__xludf.DUMMYFUNCTION("""COMPUTED_VALUE"""),"NM1") -> NM1 | D64: =IFERROR(__xludf.DUMMYFUNCTION("""COMPUTED_VALUE"""),1717844.0) -> 1717844 | E64: t+pazolite - Party in the HOLLOWood feat. Nanahira [INSane] | F64: t+pazolite - Party in the HOLLOWood feat. Nanahira [INSane] | G64: t+pazolite | H64: 178
B65: =IFERROR(__xludf.DUMMYFUNCTION("""COMPUTED_VALUE"""),"Semifinals") -> Semifinals | C65: =IFERROR(__xludf.DUMMYFUNCTION("""COMPUTED_VALUE"""),"NM2") -> NM2 | D65: =IFERROR(__xludf.DUMMYFUNCTION("""COMPUTED_VALUE"""),3656173.0) -> 3656173 | E65: GIVEON - Favourite Mistake [Halogenix Edit] [Insane] | F65: GIVEON - Favourite Mistake [Halogenix Edit] [Insane] | G65: GIVEON | H65: 172
B66: =IFERROR(__xludf.DUMMYFUNCTION("""COMPUTED_VALUE"""),"Semifinals") -> Semifinals | C66: =IFERROR(__xludf.DUMMYFUNCTION("""COMPUTED_VALUE"""),"NM3") -> NM3 | D66: =IFERROR(__xludf.DUMMYFUNCTION("""COMPUTED_VALUE"""),2715749.0) -> 2715749 | E66: ALI - Wild Side [Squilly's Insane] | F66: ALI - Wild Side [Squilly's Insane] | G66: ALI | H66: 134
B67: =IFERROR(__xludf.DUMMYFUNCTION("""COMPUTED_VALUE"""),"Semifinals") -> Semifinals | C67: =IFERROR(__xludf.DUMMYFUNCTION("""COMPUTED_VALUE"""),"NM4") -> NM4 | D67: =IFERROR(__xludf.DUMMYFUNCTION("""COMPUTED_VALUE"""),3291796.0) -> 3291796 | E67: VeetaCrush - Mole [Kyutei's Insane] | F67: VeetaCrush - Mole [Kyutei's Insane] | G67: VeetaCrush | H67: 172
B68: =IFERROR(__xludf.DUMMYFUNCTION("""COMPUTED_VALUE"""),"Semifinals") -> Semifinals | C68: =IFERROR(__xludf.DUMMYFUNCTION("""COMPUTED_VALUE"""),"NM5") -> NM5 | D68: =IFERROR(__xludf.DUMMYFUNCTION("""COMPUTED_VALUE"""),3187491.0) -> 3187491 | E68: Camellia - Killerbeast [Spiritual] | F68: Camellia - Killerbeast [Spiritual] | G68: Camellia | H68: 220
B69: =IFERROR(__xludf.DUMMYFUNCTION("""COMPUTED_VALUE"""),"Semifinals") -> Semifinals | C69: =IFERROR(__xludf.DUMMYFUNCTION("""COMPUTED_VALUE"""),"NM6") -> NM6 | D69: =IFERROR(__xludf.DUMMYFUNCTION("""COMPUTED_VALUE"""),3990086.0) -> 3990086 | E69: Kai - Junk Lady [Deppy and Wanpachi's Insane] | F69: Kai - Junk Lady [Deppy and Wanpachi's Insane] | G69: Kai | H69: 174
B70: =IFERROR(__xludf.DUMMYFUNCTION("""COMPUTED_VALUE"""),"Semifinals") -> Semifinals | C70: =IFERROR(__xludf.DUMMYFUNCTION("""COMPUTED_VALUE"""),"HD1") -> HD1 | D70: =IFERROR(__xludf.DUMMYFUNCTION("""COMPUTED_VALUE"""),1972425.0) -> 1972425 | E70: Aso Natsuko - Perfect-area complete! [Asuka_-'s Insane] | F70: Aso Natsuko - Perfect-area complete! [Asuka_-'s Insane] | G70: Aso Natsuko | H70: 183
B71: =IFERROR(__xludf.DUMMYFUNCTION("""COMPUTED_VALUE"""),"Semifinals") -> Semifinals | C71: =IFERROR(__xludf.DUMMYFUNCTION("""COMPUTED_VALUE"""),"HD2") -> HD2 | D71: =IFERROR(__xludf.DUMMYFUNCTION("""COMPUTED_VALUE"""),2277128.0) -> 2277128 | E71: Kola Kid - timer [Insane] | F71: Kola Kid - timer [Insane] | G71: Kola Kid | H71: 180
B72: =IFERROR(__xludf.DUMMYFUNCTION("""COMPUTED_VALUE"""),"Semifinals") -> Semifinals | C72: =IFERROR(__xludf.DUMMYFUNCTION("""COMPUTED_VALUE"""),"HD3") -> HD3 | D72: =IFERROR(__xludf.DUMMYFUNCTION("""COMPUTED_VALUE"""),2044890.0) -> 2044890 | E72: YUC'e - POISON -KO3 Remix- [Insane] | F72: YUC'e - POISON -KO3 Remix- [Insane] | G72: YUC'e | H72: 170
B73: =IFERROR(__xludf.DUMMYFUNCTION("""COMPUTED_VALUE"""),"Semifinals") -> Semifinals | C73: =IFERROR(__xludf.DUMMYFUNCTION("""COMPUTED_VALUE"""),"HR1") -> HR1 | D73: =IFERROR(__xludf.DUMMYFUNCTION("""COMPUTED_VALUE"""),3454421.0) -> 3454421 | E73: Harumaki Gohan feat. Hatsune Miku - Hotaru wa Inakatta [Kuse's Insane] | F73: Harumaki Gohan feat. Hatsune Miku - Hotaru wa Inakatta [Kuse's Insane] | G73: Harumaki Gohan feat. Hatsune Miku | H73: 206
B74: =IFERROR(__xludf.DUMMYFUNCTION("""COMPUTED_VALUE"""),"Semifinals") -> Semifinals | C74: =IFERROR(__xludf.DUMMYFUNCTION("""COMPUTED_VALUE"""),"HR2") -> HR2 | D74: =IFERROR(__xludf.DUMMYFUNCTION("""COMPUTED_VALUE"""),2917786.0) -> 2917786 | E74: Cro - Wie ich bin [Trust] | F74: Cro - Wie ich bin [Trust] | G74: Cro | H74: 130
B75: =IFERROR(__xludf.DUMMYFUNCTION("""COMPUTED_VALUE"""),"Semifinals") -> Semifinals | C75: =IFERROR(__xludf.DUMMYFUNCTION("""COMPUTED_VALUE"""),"HR3") -> HR3 | D75: =IFERROR(__xludf.DUMMYFUNCTION("""COMPUTED_VALUE"""),1405094.0) -> 1405094 | E75: Camellia - Routing [Another] | F75: Camellia - Routing [Another] | G75: Camellia | H75: 144
B76: =IFERROR(__xludf.DUMMYFUNCTION("""COMPUTED_VALUE"""),"Semifinals") -> Semifinals | C76: =IFERROR(__xludf.DUMMYFUNCTION("""COMPUTED_VALUE"""),"DT1") -> DT1 | D76: =IFERROR(__xludf.DUMMYFUNCTION("""COMPUTED_VALUE"""),1592512.0) -> 1592512 | E76: 96neko - Primitive emotion [Hard] | F76: 96neko - Primitive emotion [Hard] | G76: 96neko | H76: 190
B77: =IFERROR(__xludf.DUMMYFUNCTION("""COMPUTED_VALUE"""),"Semifinals") -> Semifinals | C77: =IFERROR(__xludf.DUMMYFUNCTION("""COMPUTED_VALUE"""),"DT2") -> DT2 | D77: =IFERROR(__xludf.DUMMYFUNCTION("""COMPUTED_VALUE"""),2388648.0) -> 2388648 | E77: umu. - Dareka no Shinzou ni Nareta Nara [Hard] | F77: umu. - Dareka no Shinzou ni Nareta Nara [Hard] | G77: umu. | H77: 145
B78: =IFERROR(__xludf.DUMMYFUNCTION("""COMPUTED_VALUE"""),"Semifinals") -> Semifinals | C78: =IFERROR(__xludf.DUMMYFUNCTION("""COMPUTED_VALUE"""),"DT3") -> DT3 | D78: =IFERROR(__xludf.DUMMYFUNCTION("""COMPUTED_VALUE"""),3819183.0) -> 3819183 | E78: AAAA + Umeboshi Chazuke - Cait Sith [Setu's Hard] | F78: AAAA + Umeboshi Chazuke - Cait Sith [Setu's Hard] | G78: AAAA + Umeboshi Chazuke | H78: 170
B79: =IFERROR(__xludf.DUMMYFUNCTION("""COMPUTED_VALUE"""),"Semifinals") -> Semifinals | C79: =IFERROR(__xludf.DUMMYFUNCTION("""COMPUTED_VALUE"""),"FM1") -> FM1 | D79: =IFERROR(__xludf.DUMMYFUNCTION("""COMPUTED_VALUE"""),2514122.0) -> 2514122 | E79: Wagakki Band - Kagerou Days [Ducky-'s Insane] | F79: Wagakki Band - Kagerou Days [Ducky-'s Insane] | G79: Wagakki Band | H79: 200
B80: =IFERROR(__xludf.DUMMYFUNCTION("""COMPUTED_VALUE"""),"Semifinals") -> Semifinals | C80: =IFERROR(__xludf.DUMMYFUNCTION("""COMPUTED_VALUE"""),"FM2") -> FM2 | D80: =IFERROR(__xludf.DUMMYFUNCTION("""COMPUTED_VALUE"""),28366.0) -> 28366 | E80: Brandy - Cross Time !! [DJPop Mix] | F80: Brandy - Cross Time !! [DJPop Mix] | G80: Brandy | H80: 160
B81: =IFERROR(__xludf.DUMMYFUNCTION("""COMPUTED_VALUE"""),"Semifinals") -> Semifinals | C81: =IFERROR(__xludf.DUMMYFUNCTION("""COMPUTED_VALUE"""),"TB1") -> TB1 | D81: =IFERROR(__xludf.DUMMYFUNCTION("""COMPUTED_VALUE"""),1248147.0) -> 1248147 | E81: Camellia - EXiT this Earths Atomosphere [Astral] | F81: Camellia - EXiT this Earths Atomosphere [Astral] | G81: Camellia | H81: 170
B82: =IFERROR(__xludf.DUMMYFUNCTION("""COMPUTED_VALUE"""),"Finals") -> Finals | C82: =IFERROR(__xludf.DUMMYFUNCTION("""COMPUTED_VALUE"""),"NM1") -> NM1 | D82: =IFERROR(__xludf.DUMMYFUNCTION("""COMPUTED_VALUE"""),2198934.0) -> 2198934 | E82: Camellia - Racemization [extreme] | F82: Camellia - Racemization [extreme] | G82: Camellia | H82: 202
B83: =IFERROR(__xludf.DUMMYFUNCTION("""COMPUTED_VALUE"""),"Finals") -> Finals | C83: =IFERROR(__xludf.DUMMYFUNCTION("""COMPUTED_VALUE"""),"NM2") -> NM2 | D83: =IFERROR(__xludf.DUMMYFUNCTION("""COMPUTED_VALUE"""),3010348.0) -> 3010348 | E83: vierre cloud - moment [astronic's another] | F83: vierre cloud - moment [astronic's another] | G83: vierre cloud | H83: 171.3
B84: =IFERROR(__xludf.DUMMYFUNCTION("""COMPUTED_VALUE"""),"Finals") -> Finals | C84: =IFERROR(__xludf.DUMMYFUNCTION("""COMPUTED_VALUE"""),"NM3") -> NM3 | D84: =IFERROR(__xludf.DUMMYFUNCTION("""COMPUTED_VALUE"""),3774971.0) -> 3774971 | E84: Ryokuoushoku Shakai - Zutto Zutto Zutto [Kloyd's Expert] | F84: Ryokuoushoku Shakai - Zutto Zutto Zutto [Kloyd's Expert] | G84: Ryokuoushoku Shakai | H84: 128
B85: =IFERROR(__xludf.DUMMYFUNCTION("""COMPUTED_VALUE"""),"Finals") -> Finals | C85: =IFERROR(__xludf.DUMMYFUNCTION("""COMPUTED_VALUE"""),"NM4") -> NM4 | D85: =IFERROR(__xludf.DUMMYFUNCTION("""COMPUTED_VALUE"""),3802110.0) -> 3802110 | E85: USAO - Gruequix [Expert] | F85: USAO - Gruequix [Expert] | G85: USAO | H85: 128
B86: =IFERROR(__xludf.DUMMYFUNCTION("""COMPUTED_VALUE"""),"Finals") -> Finals | C86: =IFERROR(__xludf.DUMMYFUNCTION("""COMPUTED_VALUE"""),"NM5") -> NM5 | D86: =IFERROR(__xludf.DUMMYFUNCTION("""COMPUTED_VALUE"""),309900.0) -> 309900 | E86: Prim - Koisuru*Uchuu Sensou!! [Another 220BPM] | F86: Prim - Koisuru*Uchuu Sensou!! [Another 220BPM] | G86: Prim | H86: 220
B87: =IFERROR(__xludf.DUMMYFUNCTION("""COMPUTED_VALUE"""),"Finals") -> Finals | C87: =IFERROR(__xludf.DUMMYFUNCTION("""COMPUTED_VALUE"""),"NM6") -> NM6 | D87: =IFERROR(__xludf.DUMMYFUNCTION("""COMPUTED_VALUE"""),3870932.0) -> 3870932 | E87: Kikuo - Yousei no Kiri [Insane] | F87: Kikuo - Yousei no Kiri [Insane] | G87: Kikuo | H87: 160
B88: =IFERROR(__xludf.DUMMYFUNCTION("""COMPUTED_VALUE"""),"Finals") -> Finals | C88: =IFERROR(__xludf.DUMMYFUNCTION("""COMPUTED_VALUE"""),"HD1") -> HD1 | D88: =IFERROR(__xludf.DUMMYFUNCTION("""COMPUTED_VALUE"""),571620.0) -> 571620 | E88: DJ S3RL - T-T-Techno (feat. Jesskah) [fanzhen's X-Tra] | F88: DJ S3RL - T-T-Techno (feat. Jesskah) [fanzhen's X-Tra] | G88: DJ S3RL | H88: 175
B89: =IFERROR(__xludf.DUMMYFUNCTION("""COMPUTED_VALUE"""),"Finals") -> Finals | C89: =IFERROR(__xludf.DUMMYFUNCTION("""COMPUTED_VALUE"""),"HD2") -> HD2 | D89: =IFERROR(__xludf.DUMMYFUNCTION("""COMPUTED_VALUE"""),3563737.0) -> 3563737 | E89: capsule - A.I. automatic infection [Insane] | F89: capsule - A.I. automatic infection [Insane] | G89: capsule | H89: 170
B90: =IFERROR(__xludf.DUMMYFUNCTION("""COMPUTED_VALUE"""),"Finals") -> Finals | C90: =IFERROR(__xludf.DUMMYFUNCTION("""COMPUTED_VALUE"""),"HD3") -> HD3 | D90: =IFERROR(__xludf.DUMMYFUNCTION("""COMPUTED_VALUE"""),2751338.0) -> 2751338 | E90: Kudou Chitose - CHO-DARI- [EX] | F90: Kudou Chitose - CHO-DARI- [EX] | G90: Kudou Chitose | H90: 80
B91: =IFERROR(__xludf.DUMMYFUNCTION("""COMPUTED_VALUE"""),"Finals") -> Finals | C91: =IFERROR(__xludf.DUMMYFUNCTION("""COMPUTED_VALUE"""),"HR1") -> HR1 | D91: =IFERROR(__xludf.DUMMYFUNCTION("""COMPUTED_VALUE"""),2288966.0) -> 2288966 | E91: BAND-MAID - I can't live without you. [Insane] | F91: BAND-MAID - I can't live without you. [Insane] | G91: BAND-MAID | H91: 180
B92: =IFERROR(__xludf.DUMMYFUNCTION("""COMPUTED_VALUE"""),"Finals") -> Finals | C92: =IFERROR(__xludf.DUMMYFUNCTION("""COMPUTED_VALUE"""),"HR2") -> HR2 | D92: =IFERROR(__xludf.DUMMYFUNCTION("""COMPUTED_VALUE"""),2691754.0) -> 2691754 | E92: Sta & Feryquitous - 2 Minutes Euphoria [Pata-Mon's Insane] | F92: Sta & Feryquitous - 2 Minutes Euphoria [Pata-Mon's Insane] | G92: Sta & Feryquitous | H92: 170
B93: =IFERROR(__xludf.DUMMYFUNCTION("""COMPUTED_VALUE"""),"Finals") -> Finals | C93: =IFERROR(__xludf.DUMMYFUNCTION("""COMPUTED_VALUE"""),"HR3") -> HR3 | D93: =IFERROR(__xludf.DUMMYFUNCTION("""COMPUTED_VALUE"""),2856139.0) -> 2856139 | E93: Eagle - S!ck [Down's Insane] | F93: Eagle - S!ck [Down's Insane] | G93: Eagle | H93: 177
B94: =IFERROR(__xludf.DUMMYFUNCTION("""COMPUTED_VALUE"""),"Finals") -> Finals | C94: =IFERROR(__xludf.DUMMYFUNCTION("""COMPUTED_VALUE"""),"DT1") -> DT1 | D94: =IFERROR(__xludf.DUMMYFUNCTION("""COMPUTED_VALUE"""),765880.0) -> 765880 | E94: Komine Lisa - Resuscitated Hope [Insane] | F94: Komine Lisa - Resuscitated Hope [Insane] | G94: Komine Lisa | H94: 130
B95: =IFERROR(__xludf.DUMMYFUNCTION("""COMPUTED_VALUE"""),"Finals") -> Finals | C95: =IFERROR(__xludf.DUMMYFUNCTION("""COMPUTED_VALUE"""),"DT2") -> DT2 | D95: =IFERROR(__xludf.DUMMYFUNCTION("""COMPUTED_VALUE"""),345642.0) -> 345642 | E95: Memme - NEW Astronomas [Priti's Hyper] | F95: Memme - NEW Astronomas [Priti's Hyper] | G95: Memme | H95: 160
B96: =IFERROR(__xludf.DUMMYFUNCTION("""COMPUTED_VALUE"""),"Finals") -> Finals | C96: =IFERROR(__xludf.DUMMYFUNCTION("""COMPUTED_VALUE"""),"DT3") -> DT3 | D96: =IFERROR(__xludf.DUMMYFUNCTION("""COMPUTED_VALUE"""),2671858.0) -> 2671858 | E96: Camellia - Compute It With Some Devilish Alcoholic Steampunk Engines [F4UZ4N's Hard] | F96: Camellia - Compute It With Some Devilish Alcoholic Steampunk Engines [F4UZ4N's Hard] | G96: Camellia | H96: 165
B97: =IFERROR(__xludf.DUMMYFUNCTION("""COMPUTED_VALUE"""),"Finals") -> Finals | C97: =IFERROR(__xludf.DUMMYFUNCTION("""COMPUTED_VALUE"""),"DT4") -> DT4 | D97: =IFERROR(__xludf.DUMMYFUNCTION("""COMPUTED_VALUE"""),4150885.0) -> 4150885 | E97: KOTOKO - Princess Bride! (Cut Ver.) [Hard] | F97: KOTOKO - Princess Bride! (Cut Ver.) [Hard] | G97: KOTOKO | H97: 155
B98: =IFERROR(__xludf.DUMMYFUNCTION("""COMPUTED_VALUE"""),"Finals") -> Finals | C98: =IFERROR(__xludf.DUMMYFUNCTION("""COMPUTED_VALUE"""),"FM1") -> FM1 | D98: =IFERROR(__xludf.DUMMYFUNCTION("""COMPUTED_VALUE"""),4197268.0) -> 4197268 | E98: Kenshi Yonezu - KICK BACK [STOMPMARK'S INSANE] | F98: Kenshi Yonezu - KICK BACK [STOMPMARK'S INSANE] | G98: Kenshi Yonezu | H98: 204
B99: =IFERROR(__xludf.DUMMYFUNCTION("""COMPUTED_VALUE"""),"Finals") -> Finals | C99: =IFERROR(__xludf.DUMMYFUNCTION("""COMPUTED_VALUE"""),"FM2") -> FM2 | D99: =IFERROR(__xludf.DUMMYFUNCTION("""COMPUTED_VALUE"""),192181.0) -> 192181 | E99: Memme - Extreme Fantasy [Insane] | F99: Memme - Extreme Fantasy [Insane] | G99: Memme | H99: 152
B100: =IFERROR(__xludf.DUMMYFUNCTION("""COMPUTED_VALUE"""),"Finals") -> Finals | C100: =IFERROR(__xludf.DUMMYFUNCTION("""COMPUTED_VALUE"""),"FM3") -> FM3 | D100: =IFERROR(__xludf.DUMMYFUNCTION("""COMPUTED_VALUE"""),3499229.0) -> 3499229 | E100: Mysteka - Hesperos [Mayu's Insane] | F100: Mysteka - Hesperos [Mayu's Insane] | G100: Mysteka | H100: 173
B101: =IFERROR(__xludf.DUMMYFUNCTION("""COMPUTED_VALUE"""),"Finals") -> Finals | C101: =IFERROR(__xludf.DUMMYFUNCTION("""COMPUTED_VALUE"""),"TB1") -> TB1 | D101: =IFERROR(__xludf.DUMMYFUNCTION("""COMPUTED_VALUE"""),1485947.0) -> 1485947 | E101: Pendulum - Hold Your Colour [Iridescence] | F101: Pendulum - Hold Your Colour [Iridescence] | G101: Pendulum | H101: 174
B102: =IFERROR(__xludf.DUMMYFUNCTION("""COMPUTED_VALUE"""),"Grand Finals") -> Grand Finals | C102: =IFERROR(__xludf.DUMMYFUNCTION("""COMPUTED_VALUE"""),"NM1") -> NM1 | D102: =IFERROR(__xludf.DUMMYFUNCTION("""COMPUTED_VALUE"""),2792506.0) -> 2792506 | E102: Airots - Tougen Roman (Epsilon Remix) [Dailycare's Extra] | F102: Airots - Tougen Roman (Epsilon Remix) [Dailycare's Extra] | G102: Airots | H102: 175
...

Sheet _mapids
A1: ALL IDS
A2: {=TRANSPOSE(ADDRESS(ROW(Template!C5),COLUMN(Template!C5),4,1,Settings!F3:F12)&":"&ADDRESS(ROW(Template!C298),COLUMN(Template!C298),4)&T(NOW()))} -> Quals!C5:C298 | B2: ''!C5:C298 | C2: ''!C5:C298 | D2: ''!C5:C298 | E2: 'RO32'!C5:C298 | F2: 'RO16'!C5:C298 | G2: QF!C5:C298 | H2: SF!C5:C298 | I2: F!C5:C298 | J2: GF!C5:C298 | K2: All Links
A3: {=IFERROR(IF(INDIRECT(A2)="",,VALUE(INDIRECT(A2)&T(NOW()))),"")} -> 3924030 | B3: {=IFERROR(IF(INDIRECT(B2)="",,VALUE(INDIRECT(B2)&T(NOW()))),"")} -> #REF! | C3: {=IFERROR(IF(INDIRECT(C2)="",,VALUE(INDIRECT(C2)&T(NOW()))),"")} -> #REF! | D3: {=IFERROR(IF(INDIRECT(D2)="",,VALUE(INDIRECT(D2)&T(NOW()))),"")} -> #REF! | E3: {=IFERROR(IF(INDIRECT(E2)="",,VALUE(INDIRECT(E2)&T(NOW()))),"")} -> #REF! | F3: {=IFERROR(IF(INDIRECT(F2)="",,VALUE(INDIRECT(F2)&T(NOW()))),"")} -> #REF! | G3: {=IFERROR(IF(INDIRECT(G2)="",,VALUE(INDIRECT(G2)&T(NOW()))),"")} -> #REF! | H3: {=IFERROR(IF(INDIRECT(H2)="",,VALUE(INDIRECT(H2)&T(NOW()))),"")} -> #REF! | ... J3: {=IFERROR(IF(INDIRECT(J2)="",,VALUE(INDIRECT(J2)&T(NOW()))),"")} -> #REF! | K3: =IFERROR(__xludf.DUMMYFUNCTION("IFNA(FILTER(FLATTEN(A3:J1001),FLATTEN(A3:J1001)<>""""))"),3924030.0) -> 3924030
A4: 3207049 | K4: =IFERROR(__xludf.DUMMYFUNCTION("""COMPUTED_VALUE"""),3207049.0) -> 3207049
A5: 4113699 | K5: =IFERROR(__xludf.DUMMYFUNCTION("""COMPUTED_VALUE"""),4113699.0) -> 4113699
A6: 3737825 | K6: =IFERROR(__xludf.DUMMYFUNCTION("""COMPUTED_VALUE"""),3737825.0) -> 3737825
A7: 2514122 | K7: =IFERROR(__xludf.DUMMYFUNCTION("""COMPUTED_VALUE"""),2514122.0) -> 2514122
A8: 2619929 | B8: {=IFERROR(IF(INDIRECT(B2)="",,VALUE(INDIRECT(B2)&T(NOW()))),"")} | C8: {=IFERROR(IF(INDIRECT(C2)="",,VALUE(INDIRECT(C2)&T(NOW()))),"")} -> #REF! | D8: {=IFERROR(IF(INDIRECT(D2)="",,VALUE(INDIRECT(D2)&T(NOW()))),"")} | E8: {=IFERROR(IF(INDIRECT(E2)="",,VALUE(INDIRECT(E2)&T(NOW()))),"")} | F8: {=IFERROR(IF(INDIRECT(F2)="",,VALUE(INDIRECT(F2)&T(NOW()))),"")} -> 306038 | G8: {=IFERROR(IF(INDIRECT(G2)="",,VALUE(INDIRECT(G2)&T(NOW()))),"")} -> 3298592 | H8: {=IFERROR(IF(INDIRECT(H2)="",,VALUE(INDIRECT(H2)&T(NOW()))),"")} -> 1405094 | I8: {=IFERROR(IF(INDIRECT(I2)="",,VALUE(INDIRECT(I2)&T(NOW()))),"")} -> 646609 | J8: {=IFERROR(IF(INDIRECT(J2)="",,VALUE(INDIRECT(J2)&T(NOW()))),"")} | K8: =IFERROR(__xludf.DUMMYFUNCTION("""COMPUTED_VALUE"""),2619929.0) -> 2619929
A9: 3958395 | E9: 3823691 | F9: 3563790 | G9: 63604 | H9: 3841174 | I9: 2751338 | J9: 3795759 | K9: =IFERROR(__xludf.DUMMYFUNCTION("""COMPUTED_VALUE"""),306038.0) -> 306038
A10: 1523138 | E10: 2995193 | F10: 3496410 | G10: 2690081 | H10: 703042 | I10: 3182641 | J10: 1863870 | K10: =IFERROR(__xludf.DUMMYFUNCTION("""COMPUTED_VALUE"""),3298592.0) -> 3298592
A11: 4105349 | E11: 2016938 | F11: 3887774 | G11: 1965654 | H11: 2514122 | I11: 1782851 | J11: 1456307 | K11: =IFERROR(__xludf.DUMMYFUNCTION("""COMPUTED_VALUE"""),1405094.0) -> 1405094
A12: 3411549 | E12: 2340750 | F12: 2827293 | G12: 3118794 | H12: 3399446 | I12: 1896582 | J12: 4134134 | K12: =IFERROR(__xludf.DUMMYFUNCTION("""COMPUTED_VALUE"""),646609.0) -> 646609
A13: 2395972 | E13: 3297107 | F13: 2004679 | G13: 3248255 | H13: 2383229 | I13: 3256307 | J13: 34211 | K13: =IFERROR(__xludf.DUMMYFUNCTION("""COMPUTED_VALUE"""),3958395.0) -> 3958395
A14: 3720541 | E14: 2440455 | F14: 3117101 | G14: 1635864 | H14: 1972425 | I14: 3444608 | J14: 1567978 | K14: =IFERROR(__xludf.DUMMYFUNCTION("""COMPUTED_VALUE"""),3823691.0) -> 3823691
A15: 3081261 | E15: 3248876 | F15: 1489274 | G15: 1404975 | H15: 3291796 | I15: 192181 | J15: 1045757 | K15: =IFERROR(__xludf.DUMMYFUNCTION("""COMPUTED_VALUE"""),3563790.0) -> 3563790
A16: 3684386 | E16: 1989991 | F16: 4082310 | G16: 1687599 | H16: 3656173 | I16: 1485947 | J16: 3412490 | K16: =IFERROR(__xludf.DUMMYFUNCTION("""COMPUTED_VALUE"""),63604.0) -> 63604
A17: 3783139 | E17: 3280686 | F17: 155064 | G17: 2072245 | H17: 2992124 | I17: 2239337 | J17: 2015481 | K17: =IFERROR(__xludf.DUMMYFUNCTION("""COMPUTED_VALUE"""),3841174.0) -> 3841174
A18: 2027623 | E18: 3396305 | F18: 4024821 | G18: 1596086 | H18: 3986899 | I18: 2198934 | J18: 1258993 | K18: =IFERROR(__xludf.DUMMYFUNCTION("""COMPUTED_VALUE"""),2751338.0) -> 2751338
A19: 2305346 | E19: 3446761 | F19: 2729314 | G19: 1251955 | H19: 2200110 | I19: 1387177 | J19: 2442178 | K19: =IFERROR(__xludf.DUMMYFUNCTION("""COMPUTED_VALUE"""),3795759.0) -> 3795759
A20: 3310401 | E20: 2044893 | F20: 87319 | G20: 2472143 | H20: 3990086 | I20: 2775823 | J20: 1290855 | K20: =IFERROR(__xludf.DUMMYFUNCTION("""COMPUTED_VALUE"""),1523138.0) -> 1523138
A21: 4121042 | E21: 3044231 | F21: 1913099 | G21: 3221246 | H21: 2666261 | I21: 3206318 | K21: =IFERROR(__xludf.DUMMYFUNCTION("""COMPUTED_VALUE"""),2995193.0) -> 2995193
A22: 908887 | E22: 57384 | F22: 1521209 | G22: 3822120 | H22: 87369 | I22: 1484886 | J22: 3333734 | K22: =IFERROR(__xludf.DUMMYFUNCTION("""COMPUTED_VALUE"""),3496410.0) -> 3496410
A23: 3533589 | E23: 2110801 | F23: 2967720 | G23: 48215 | H23: 667685 | I23: 3774971 | J23: 2775823 | K23: =IFERROR(__xludf.DUMMYFUNCTION("""COMPUTED_VALUE"""),2690081.0) -> 2690081
A24: 2094462 | E24: 2366848 | F24: 1498150 | G24: 3616425 | H24: 1782851 | I24: 2835868 | J24: 2405667 | K24: =IFERROR(__xludf.DUMMYFUNCTION("""COMPUTED_VALUE"""),703042.0) -> 703042
A25: 3035501 | E25: 2694599 | F25: 417898 | G25: 2532230 | H25: 1592512 | I25: 4075902 | J25: 3711739 | K25: =IFERROR(__xludf.DUMMYFUNCTION("""COMPUTED_VALUE"""),3182641.0) -> 3182641
E26: 134141 | F26: 87369 | G26: 2986144 | H26: 3819183 | I26: 3870932 | J26: 2134906 | K26: =IFERROR(__xludf.DUMMYFUNCTION("""COMPUTED_VALUE"""),1863870.0) -> 1863870
E27: 250577 | F27: 2530278 | G27: 1975970 | H27: 2643263 | I27: 261729 | J27: 3326410 | K27: =IFERROR(__xludf.DUMMYFUNCTION("""COMPUTED_VALUE"""),4105349.0) -> 4105349
E28: 2161153 | F28: 892543 | G28: 3912466 | H28: 1403845 | I28: 1290855 | J28: 2348578 | K28: =IFERROR(__xludf.DUMMYFUNCTION("""COMPUTED_VALUE"""),2016938.0) -> 2016938
E29: 2795818 | F29: 3714964 | G29: 1600995 | H29: 2872861 | I29: 2442178 | J29: 929118 | K29: =IFERROR(__xludf.DUMMYFUNCTION("""COMPUTED_VALUE"""),3887774.0) -> 3887774
E30: 3941210 | F30: 2200330 | G30: 2800663 | H30: 2917786 | I30: 1863289 | J30: 2718270 | K30: =IFERROR(__xludf.DUMMYFUNCTION("""COMPUTED_VALUE"""),1965654.0) -> 1965654
E31: 3742030 | F31: 1733441 | G31: 103476 | H31: 2715749 | I31: 757386 | J31: 1744385 | K31: =IFERROR(__xludf.DUMMYFUNCTION("""COMPUTED_VALUE"""),2514122.0) -> 2514122
E32: 846261 | F32: 3601684 | G32: 3870932 | H32: 2044890 | I32: 3010348 | J32: 3186407 | K32: =IFERROR(__xludf.DUMMYFUNCTION("""COMPUTED_VALUE"""),1782851.0) -> 1782851
E33: 2659337 | F33: 315101 | H33: 3454421 | I33: 2906707 | J33: 243487 | K33: =IFERROR(__xludf.DUMMYFUNCTION("""COMPUTED_VALUE"""),1456307.0) -> 1456307
E34: 2277989 | F34: 1761258 | G34: 3913591 | H34: 152180 | I34: 2842836 | J34: 3614024 | K34: =IFERROR(__xludf.DUMMYFUNCTION("""COMPUTED_VALUE"""),3411549.0) -> 3411549
E35: 3743202 | F35: 2701775 | G35: 674080 | H35: 2446833 | I35: 3851000 | J35: 3257641 | K35: =IFERROR(__xludf.DUMMYFUNCTION("""COMPUTED_VALUE"""),2340750.0) -> 2340750
F36: 3460069 | G36: 2514122 | H36: 2942900 | I36: 2058908 | J36: 3182052 | K36: =IFERROR(__xludf.DUMMYFUNCTION("""COMPUTED_VALUE"""),2827293.0) -> 2827293
F37: 3053637 | G37: 3407970 | H37: 4133990 | I37: 804959 | J37: 3071429 | K37: =IFERROR(__xludf.DUMMYFUNCTION("""COMPUTED_VALUE"""),3118794.0) -> 3118794
F38: 3332932 | G38: 2917786 | H38: 2758832 | I38: 2856139 | J38: 1653270 | K38: =IFERROR(__xludf.DUMMYFUNCTION("""COMPUTED_VALUE"""),3399446.0) -> 3399446
F39: 2151207 | G39: 2671048 | H39: 1738876 | J39: 117424 | K39: =IFERROR(__xludf.DUMMYFUNCTION("""COMPUTED_VALUE"""),1896582.0) -> 1896582
F40: 3169863 | G40: 74778 | H40: 28366 | I40: 3499229 | J40: 2855311 | K40: =IFERROR(__xludf.DUMMYFUNCTION("""COMPUTED_VALUE"""),4134134.0) -> 4134134
F41: 2891411 | G41: 3530469 | H41: 3350322 | I41: 4197268 | J41: 3883278 | K41: =IFERROR(__xludf.DUMMYFUNCTION("""COMPUTED_VALUE"""),2395972.0) -> 2395972
F42: 2794904 | G42: 1491793 | H42: 3309941 | I42: 86079 | J42: 1592403 | K42: =IFERROR(__xludf.DUMMYFUNCTION("""COMPUTED_VALUE"""),3297107.0) -> 3297107
F43: 295650 | G43: 3291796 | H43: 2388648 | I43: 2849167 | J43: 26436 | K43: =IFERROR(__xludf.DUMMYFUNCTION("""COMPUTED_VALUE"""),2004679.0) -> 2004679
F44: 1956568 | G44: 3299370 | H44: 722224 | I44: 4150885 | J44: 2111658 | K44: =IFERROR(__xludf.DUMMYFUNCTION("""COMPUTED_VALUE"""),3248255.0) -> 3248255
F45: 3239199 | G45: 3822599 | H45: 3187491 | I45: 3798371 | J45: 424554 | K45: =IFERROR(__xludf.DUMMYFUNCTION("""COMPUTED_VALUE"""),2383229.0) -> 2383229
F46: 3446883 | G46: 785982 | H46: 105978 | I46: 2839573 | J46: 2559136 | K46: =IFERROR(__xludf.DUMMYFUNCTION("""COMPUTED_VALUE"""),3256307.0) -> 3256307
F47: 3616100 | G47: 382887 | H47: 86079 | I47: 3711739 | J47: 2792506 | K47: =IFERROR(__xludf.DUMMYFUNCTION("""COMPUTED_VALUE"""),34211.0) -> 34211
F48: 2853477 | G48: 4215637 | H48: 2277128 | I48: 2835894 | J48: 3686559 | K48: =IFERROR(__xludf.DUMMYFUNCTION("""COMPUTED_VALUE"""),3720541.0) -> 3720541
F49: 577517 | G49: 2277128 | H49: 1717844 | I49: 3404589 | J49: 1938365 | K49: =IFERROR(__xludf.DUMMYFUNCTION("""COMPUTED_VALUE"""),2440455.0) -> 2440455
F50: 3990086 | G50: 3804111 | H50: 1248147 | I50: 345642 | J50: 1699306 | K50: =IFERROR(__xludf.DUMMYFUNCTION("""COMPUTED_VALUE"""),3117101.0) -> 3117101
F51: 1857415 | G51: 2076261 | I51: 2970566 | J51: 789815 | K51: =IFERROR(__xludf.DUMMYFUNCTION("""COMPUTED_VALUE"""),1635864.0) -> 1635864
F52: 2536100 | G52: 1838159 | I52: 1035068 | J52: 1631406 | K52: =IFERROR(__xludf.DUMMYFUNCTION("""COMPUTED_VALUE"""),1972425.0) -> 1972425
I53: 824390 | J53: 2961839 | K53: =IFERROR(__xludf.DUMMYFUNCTION("""COMPUTED_VALUE"""),3444608.0) -> 3444608
G54: 577517 | I54: 2111279 | J54: 1737928 | K54: =IFERROR(__xludf.DUMMYFUNCTION("""COMPUTED_VALUE"""),1567978.0) -> 1567978
G55: 2568756 | I55: 2417645 | J55: 2577703 | K55: =IFERROR(__xludf.DUMMYFUNCTION("""COMPUTED_VALUE"""),3081261.0) -> 3081261
G56: 3341368 | I56: 765880 | J56: 25341 | K56: =IFERROR(__xludf.DUMMYFUNCTION("""COMPUTED_VALUE"""),3248876.0) -> 3248876
G57: 3274886 | I57: 3396297 | J57: 2565268 | K57: =IFERROR(__xludf.DUMMYFUNCTION("""COMPUTED_VALUE"""),1489274.0) -> 1489274
G58: 74779 | I58: 2691754 | J58: 3802071 | K58: =IFERROR(__xludf.DUMMYFUNCTION("""COMPUTED_VALUE"""),1404975.0) -> 1404975
G59: 37750 | I59: 3802110 | J59: 3700933 | K59: =IFERROR(__xludf.DUMMYFUNCTION("""COMPUTED_VALUE"""),3291796.0) -> 3291796
G60: 105978 | I60: 2671858 | J60: 3853742 | K60: =IFERROR(__xludf.DUMMYFUNCTION("""COMPUTED_VALUE"""),192181.0) -> 192181
G61: 3821597 | I61: 2288966 | J61: 3039329 | K61: =IFERROR(__xludf.DUMMYFUNCTION("""COMPUTED_VALUE"""),1045757.0) -> 1045757
I62: 3752605 | J62: 3714369 | K62: =IFERROR(__xludf.DUMMYFUNCTION("""COMPUTED_VALUE"""),3684386.0) -> 3684386
I63: 3953905 | J63: 2690998 | K63: =IFERROR(__xludf.DUMMYFUNCTION("""COMPUTED_VALUE"""),1989991.0) -> 1989991
I64: 309899 | J64: 3461206 | K64: =IFERROR(__xludf.DUMMYFUNCTION("""COMPUTED_VALUE"""),4082310.0) -> 4082310
I65: 309900 | J65: 2279885 | K65: =IFERROR(__xludf.DUMMYFUNCTION("""COMPUTED_VALUE"""),1687599.0) -> 1687599
I66: 3563737 | J66: 847315 | K66: =IFERROR(__xludf.DUMMYFUNCTION("""COMPUTED_VALUE"""),3656173.0) -> 3656173
I67: 571620 | J67: 99407 | K67: =IFERROR(__xludf.DUMMYFUNCTION("""COMPUTED_VALUE"""),1485947.0) -> 1485947
J68: 58701 | K68: =IFERROR(__xludf.DUMMYFUNCTION("""COMPUTED_VALUE"""),3412490.0) -> 3412490
J69: 1707909 | K69: =IFERROR(__xludf.DUMMYFUNCTION("""COMPUTED_VALUE"""),3783139.0) -> 3783139
J70: 3772514 | K70: =IFERROR(__xludf.DUMMYFUNCTION("""COMPUTED_VALUE"""),3280686.0) -> 3280686
J71: 862338 | K71: =IFERROR(__xludf.DUMMYFUNCTION("""COMPUTED_VALUE"""),155064.0) -> 155064
J72: 3711612 | K72: =IFERROR(__xludf.DUMMYFUNCTION("""COMPUTED_VALUE"""),2072245.0) -> 2072245
J73: 2519731 | K73: =IFERROR(__xludf.DUMMYFUNCTION("""COMPUTED_VALUE"""),2992124.0) -> 2992124
J74: 1035068 | K74: =IFERROR(__xludf.DUMMYFUNCTION("""COMPUTED_VALUE"""),2239337.0) -> 2239337
K75: =IFERROR(__xludf.DUMMYFUNCTION("""COMPUTED_VALUE"""),2015481.0) -> 2015481
K76: =IFERROR(__xludf.DUMMYFUNCTION("""COMPUTED_VALUE"""),2027623.0) -> 2027623
K77: =IFERROR(__xludf.DUMMYFUNCTION("""COMPUTED_VALUE"""),3396305.0) -> 3396305
K78: =IFERROR(__xludf.DUMMYFUNCTION("""COMPUTED_VALUE"""),4024821.0) -> 4024821
K79: =IFERROR(__xludf.DUMMYFUNCTION("""COMPUTED_VALUE"""),1596086.0) -> 1596086
K80: =IFERROR(__xludf.DUMMYFUNCTION("""COMPUTED_VALUE"""),3986899.0) -> 3986899
K81: =IFERROR(__xludf.DUMMYFUNCTION("""COMPUTED_VALUE"""),2198934.0) -> 2198934
K82: =IFERROR(__xludf.DUMMYFUNCTION("""COMPUTED_VALUE"""),1258993.0) -> 1258993
K83: =IFERROR(__xludf.DUMMYFUNCTION("""COMPUTED_VALUE"""),2305346.0) -> 2305346
K84: =IFERROR(__xludf.DUMMYFUNCTION("""COMPUTED_VALUE"""),3446761.0) -> 3446761
K85: =IFERROR(__xludf.DUMMYFUNCTION("""COMPUTED_VALUE"""),2729314.0) -> 2729314
K86: =IFERROR(__xludf.DUMMYFUNCTION("""COMPUTED_VALUE"""),1251955.0) -> 1251955
K87: =IFERROR(__xludf.DUMMYFUNCTION("""COMPUTED_VALUE"""),2200110.0) -> 2200110
K88: =IFERROR(__xludf.DUMMYFUNCTION("""COMPUTED_VALUE"""),1387177.0) -> 1387177
I89: 975342 | K89: =IFERROR(__xludf.DUMMYFUNCTION("""COMPUTED_VALUE"""),2442178.0) -> 2442178
K90: =IFERROR(__xludf.DUMMYFUNCTION("""COMPUTED_VALUE"""),3310401.0) -> 3310401
K91: =IFERROR(__xludf.DUMMYFUNCTION("""COMPUTED_VALUE"""),2044893.0) -> 2044893
K92: =IFERROR(__xludf.DUMMYFUNCTION("""COMPUTED_VALUE"""),87319.0) -> 87319
K93: =IFERROR(__xludf.DUMMYFUNCTION("""COMPUTED_VALUE"""),2472143.0) -> 2472143
K94: =IFERROR(__xludf.DUMMYFUNCTION("""COMPUTED_VALUE"""),3990086.0) -> 3990086
K95: =IFERROR(__xludf.DUMMYFUNCTION("""COMPUTED_VALUE"""),2775823.0) -> 2775823
K96: =IFERROR(__xludf.DUMMYFUNCTION("""COMPUTED_VALUE"""),1290855.0) -> 1290855
K97: =IFERROR(__xludf.DUMMYFUNCTION("""COMPUTED_VALUE"""),4121042.0) -> 4121042
K98: =IFERROR(__xludf.DUMMYFUNCTION("""COMPUTED_VALUE"""),3044231.0) -> 3044231
K99: =IFERROR(__xludf.DUMMYFUNCTION("""COMPUTED_VALUE"""),1913099.0) -> 1913099
K100: =IFERROR(__xludf.DUMMYFUNCTION("""COMPUTED_VALUE"""),3221246.0) -> 3221246
...

Sheet _api
A1: SHEET | B1: API | AT1: CUSTOM | AY1: EZ | BC1: HR | BG1: DT | BL1: HT
A2: ids | B2: beatmap_id | C2: beatmapset_id | D2: approved | E2: submit_date | F2: approved_date | G2: last_update | H2: artist | I2: bpm | J2: creator | K2: creator_id | L2: difficultyrating | M2: diff_aim | N2: diff_speed | O2: diff_size | P2: diff_approach | Q2: diff_overall | R2: diff_drain | S2: hit_length | T2: source | U2: genre_id | V2: language_id | W2: title | X2: total_length | Y2: version | Z2: file_md5 | AA2: mode | AB2: tags | AC2: favourite_count | AD2: rating | AE2: playcount | AF2: passcount | AG2: count_normal | AH2: count_slider | AI2: count_spinner | AJ2: max_combo | AK2: storyboard | AL2: video | AM2: download_unavailable | AN2: audio_unavailable | AO2: difficultyrating_ez | AP2: difficultyrating_hr | AQ2: difficultyrating_dt | AR2: difficultyrating_ht | AT2: string | AU2: url | AV2: cover_url | AW2: thumbnail_url | AX2: string_url | AY2: diff_size_ez | AZ2: diff_approach_ez | BA2: diff_overall_ez | BB2: diff_drain_ez | BC2: diff_size_hr | BD2: diff_approach_hr | BE2: diff_overall_hr | BF2: diff_drain_hr | BG2: diff_approach_dt | BH2: diff_overall_dt | BI2: hit_length_dt | BJ2: total_length_dt | BK2: bpm_dt | BL2: diff_approach_ez | BM2: diff_overall_ez | BN2: hit_length_ht | BO2: total_length_ht | BP2: bpm_ht
A3: {='_mapids'!K3:K1007} -> 3924030 | B3: 3924030 | C3: 1658910 | D3: 0 | E3: 44555.702 | G3: 45098.813 | H3: nonoc | I3: 196 | J3: SkyFlame | K3: 3552948 | L3: 5.04539 | M3: 2.42569 | N3: 2.40397 | O3: 3.5 | P3: 9 | Q3: 8 | R3: 5 | S3: 0.0025347222 | T3: Re:ゼロから始める異世界生活 Memory Snow | U3: 4 | V3: 3 | W3: Relive | X3: 0.0027199074 | Y3: Insane | Z3: 5db320ce1b2bcb9cbc579d58cbc7af9e | AA3: 0 | AB3: re:zero kara hajimeru isekai seikatsu rezero starting life in another world different from zero anime ova original video animation japanese rock jrock j-rock full ver. version female vocal movie rem ram emilia subaru byd bite_you_death caren_sk gottagof4st gottagofast ggf stack nyantiaz intiaz no dap moeka momoka shioi | AC3: 77 | AD3: 0 | AE3: 79 | AF3: 31 | AG3: 510 | AH3: 404 | AI3: 4 | AJ3: 1325 | AK3: 0 | AL3: 0 | AM3: 0 | AN3: 0 | AO3: 4.67627 | AP3: 5.25285 | AQ3: 7.25351 | AR3: 4.01735 | AT3: {=IF(B3:B1007="",,{ H3:H1007&" - "&W3:W1007&" ["&Y3:Y1007&"]", "https://osu.ppy.sh/beatmapsets/"&C3:C1007&"#osu/"&B3:B1007, "https://assets.ppy.sh/beatmaps/"&C3:C1007&"/covers/cover.jpg", "https://b.ppy.sh/thumb/"&C3:C1007&"l.jpg" })} -> nonoc - Relive [Insane] | AU3: https://osu.ppy.sh/beatmapsets/1658910#osu/3924030 | AV3: https://assets.ppy.sh/beatmaps/1658910/covers/cover.jpg | AW3: https://b.ppy.sh/thumb/1658910l.jpg | AX3: {=IF(AT3:AT1007="",,HYPERLINK(AU3:AU1007,AT3:AT1007))} -> nonoc - Relive [Insane] | AY3: {=IF(B3:B1007="",,O3:R1007/2)} -> 1.75 | AZ3: 4.5 | BA3: 4 | BB3: 2.5 | BC3: {=IF(B3:B1007="",,IF(O3:O1007*1.3>10,10,O3:O1007*1.3))} -> 4.55 | BD3: {=IF(B3:B1007="",,IF(P3:R1007*1.4>10,10,P3:R1007*1.4))} -> 10 | BE3: 10 | BF3: 7 | BG3: {=IF(B3:B1007="",,IF(P3:P1007<=5,(1800-((1800-P3:P1007*120)*2/3))/120,((1200-((1200-(P3:P1007-5)*150)*2/3))/150)+5))} -> 10.333333 | BH3: {=IF(B3:B1007="",,(79.5-((79.5-6*Q3:Q1007)*2/3))/6)} -> 9.75 | BI3: {=IF(B3:B1007="",,{S3:S1007,X3:X1007}/1.5)} -> 0.0016898148 | BJ3: 0.0018132716 | BK3: {=IF(B3:B1007="",,I3:I1007*1.5)} -> 294 | BL3: {=IF(B3:B1007="",,IF(P3:P1007<=5,(1800-((1800-P3:P1007*120)*3/2))/120,((1200-((1200-(P3:P1007-5)*150)*3/2))/150)+5))} -> 7 | BM3: {=IF(B3:B1007="",,(79.5-((79.5-6*Q3:Q1007)*3/2))/6)} -> 5.375 | BN3: {=IF(B3:B1007="",,{S3:S1007,X3:X1007}/0.75)} -> 0.0033796296 | BO3: 0.0036265432 | BP3: {=IF(B3:B1007="",,I3:I1007*0.75)} -> 147
A4: 3207049 | B4: 306038 | C4: 111611 | D4: 1 | E4: 41503.363 | F4: 41582.639 | G4: 41580.35 | H4: ZUN | I4: 164 | J4: sjoy | K4: 1514083 | L4: 4.9838 | M4: 2.30564 | N4: 2.45935 | O4: 4 | P4: 9 | Q4: 7 | R4: 6 | S4: 0.0022569444 | T4: Touhou | U4: 2 | V4: 5 | W4: Kobito of the Shining Needle ~ Little Princess | X4: 0.0025115741 | Y4: Lunatic | Z4: 722d484df02bcf8052fe0b4888707c18 | AA4: 0 | AB4: chenwu 东方辉针城 ～ double dealing character sukuna shinmyoumaru selisiphoenix eggache0 | AC4: 1630 | AD4: 9.62903 | AE4: 850285 | AF4: 158570 | AG4: 556 | AH4: 288 | AI4: 2 | AJ4: 1269 | AK4: 0 | AL4: 0 | AM4: 0 | AN4: 0 | AO4: 4.58376 | AP4: 5.24778 | AQ4: 7.11657 | AR4: 3.90896 | AT4: ZUN - Kobito of the Shining Needle ~ Little Princess [Lunatic] | AU4: https://osu.ppy.sh/beatmapsets/111611#osu/306038 | AV4: https://assets.ppy.sh/beatmaps/111611/covers/cover.jpg | AW4: https://b.ppy.sh/thumb/111611l.jpg | AX4: ZUN - Kobito of the Shining Needle ~ Little Princess [Lunatic] | AY4: 2 | AZ4: 4.5 | BA4: 3.5 | BB4: 3 | BC4: 5.2 | BD4: 10 | BE4: 9.8 | BF4: 8.4 | BG4: 10.333333 | BH4: 9.0833333 | BI4: 0.0015046296 | BJ4: 0.0016743827 | BK4: 246 | BL4: 7 | BM4: 3.875 | BN4: 0.0030092593 | BO4: 0.0033487654 | BP4: 123
A5: 4113699 | B5: 3207049 | C5: 1570531 | D5: 1 | E5: 44445.739 | F5: 44729.809 | G5: 44724.858 | H5: Trerey-U | I5: 198 | J5: Seiioh | K5: 9655150 | L5: 5.15536 | M5: 2.25413 | N5: 2.64461 | O5: 4 | P5: 9 | Q5: 7.5 | R5: 5.4 | S5: 0.0010532407 | U5: 10 | V5: 5 | W5: ::vexations | X5: 0.0013425926 | Y5: ::insane | Z5: 96a4e5ee5f6054e2dc1f2081601c30ea | AA5: 0 | AB5: formless​:​: nankasuisui uytrere ambient instrumental electronic electronica | AC5: 88 | AD5: 9.27612 | AE5: 27658 | AF5: 6314 | AG5: 270 | AH5: 170 | AI5: 0 | AJ5: 733 | AK5: 0 | AL5: 0 | AM5: 0 | AN5: 0 | AO5: 4.69709 | AP5: 5.40553 | AQ5: 7.74698 | AR5: 4.06395 | AT5: Trerey-U - ::vexations [::insane] | AU5: https://osu.ppy.sh/beatmapsets/1570531#osu/3207049 | AV5: https://assets.ppy.sh/beatmaps/1570531/covers/cover.jpg | AW5: https://b.ppy.sh/thumb/1570531l.jpg | AX5: Trerey-U - ::vexations [::insane] | AY5: 2 | AZ5: 4.5 | BA5: 3.75 | BB5: 2.7 | BC5: 5.2 | BD5: 10 | BE5: 10 | BF5: 7.56 | BG5: 10.333333 | BH5: 9.4166667 | BI5: 0.00070216049 | BJ5: 0.00089506173 | BK5: 297 | BL5: 7 | BM5: 4.625 | BN5: 0.001404321 | BO5: 0.0017901235 | BP5: 148.5
A6: 3737825 | B6: 3823691 | C6: 1859662 | D6: 1 | E6: 44837.073 | F6: 44855.959 | G6: 44846.895 | H6: Len | I6: 192 | J6: Kibbleru | K6: 3193504 | L6: 4.64353 | M6: 2.12282 | N6: 2.3127 | O6: 3.8 | P6: 9 | Q6: 7.8 | R6: 5 | S6: 0.0019560185 | U6: 5 | V6: 3 | W6: GHOST (feat. Such) | X6: 0.0021527778 | Y6: Amateurre's Insane | Z6: cf99a4d37739d2097f5be5ade7034b80 | AA6: 0 | AB6: amateurre japanese pop nnzn ofutone mollyoona yoshie | AC6: 128 | AD6: 9.22449 | AE6: 19774 | AF6: 5612 | AG6: 310 | AH6: 309 | AI6: 2 | AJ6: 1028 | AK6: 0 | AL6: 0 | AM6: 0 | AN6: 0 | AO6: 4.22683 | AP6: 4.87091 | AQ6: 6.74392 | AR6: 3.68842 | AT6: Len - GHOST (feat. Such) [Amateurre's Insane] | AU6: https://osu.ppy.sh/beatmapsets/1859662#osu/3823691 | AV6: https://assets.ppy.sh/beatmaps/1859662/covers/cover.jpg | AW6: https://b.ppy.sh/thumb/1859662l.jpg | AX6: Len - GHOST (feat. Such) [Amateurre's Insane] | AY6: 1.9 | AZ6: 4.5 | BA6: 3.9 | BB6: 2.5 | BC6: 4.94 | BD6: 10 | BE6: 10 | BF6: 7 | BG6: 10.333333 | BH6: 9.6166667 | BI6: 0.0013040123 | BJ6: 0.0014351852 | BK6: 288 | BL6: 7 | BM6: 5.075 | BN6: 0.0026080247 | BO6: 0.0028703704 | BP6: 144
A7: 2514122 | B7: 3563790 | C7: 1743257 | D7: -2 | E7: 44666.989 | G7: 44666.989 | H7: Electronic Boutique | I7: 130 | J7: wafer | K7: 9416836 | L7: 4.74619 | M7: 2.25397 | N7: 2.28907 | O7: 4 | P7: 9 | Q7: 8.6 | R7: 6 | S7: 0.0014236111 | U7: 14 | V7: 5 | W7: Miles | X7: 0.0014236111 | Y7: Minimal | Z7: 91886464e2637084af8f5d992551fddb | AA7: 0 | AB7: electronic instrumental jazz videogame vgm vg video game dj max ray goopert kami no kotoba | AC7: 1 | AD7: 0 | AE7: 89 | AF7: 22 | AG7: 384 | AH7: 157 | AI7: 2 | AJ7: 720 | AK7: 0 | AL7: 0 | AM7: 0 | AN7: 0 | AO7: 4.40166 | AP7: 5.0632 | AQ7: 6.57105 | AR7: 3.78293 | AT7: Electronic Boutique - Miles [Minimal] | AU7: https://osu.ppy.sh/beatmapsets/1743257#osu/3563790 | AV7: https://assets.ppy.sh/beatmaps/1743257/covers/cover.jpg | AW7: https://b.ppy.sh/thumb/1743257l.jpg | AX7: Electronic Boutique - Miles [Minimal] | AY7: 2 | AZ7: 4.5 | BA7: 4.3 | BB7: 3 | BC7: 5.2 | BD7: 10 | BE7: 10 | BF7: 8.4 | BG7: 10.333333 | BH7: 10.15 | BI7: 0.00094907408 | BJ7: 0.00094907408 | BK7: 195 | BL7: 7 | BM7: 6.275 | BN7: 0.0018981482 | BO7: 0.0018981482 | BP7: 97.5
A8: 2619929 | B8: 4113699 | C8: 1975119 | D8: -2 | E8: 45030.232 | G8: 45039.892 | H8: ATARASHII GAKKO! | I8: 130 | J8: dakiwii | K8: 10447058 | L8: 4.8831 | M8: 2.45185 | N8: 2.20755 | O8: 3.9 | P8: 9.3 | Q8: 8 | R8: 6 | S8: 0.0020717593 | U8: 5 | V8: 3 | W8: OTONABLUE | X8: 0.0020833333 | Y8: -ktrihc's the last the fost [Insano waza] | Z8: b7ba93b2d23c610b665e23bb5835c4ef | AA8: 0 | AB8: j-pop japanese pop jpop 新しい学校のリーダーズ atarashii gakko! オトナブルー alt alternate nm4 - nm3 | AC8: 10 | AD8: 0 | AE8: 1414 | AF8: 361 | AG8: 462 | AH8: 288 | AI8: 4 | AJ8: 1056 | AK8: 0 | AL8: 0 | AM8: 0 | AN8: 0 | AO8: 4.50714 | AP8: 5.19348 | AQ8: 6.90162 | AR8: 3.87245 | AT8: ATARASHII GAKKO! - OTONABLUE [-ktrihc's the last the fost [Insano waza]] | AU8: https://osu.ppy.sh/beatmapsets/1975119#osu/4113699 | AV8: https://assets.ppy.sh/beatmaps/1975119/covers/cover.jpg | AW8: https://b.ppy.sh/thumb/1975119l.jpg | AX8: ATARASHII GAKKO! - OTONABLUE [-ktrihc's the last the fost [Insano waza]] | AY8: 1.95 | AZ8: 4.65 | BA8: 4 | BB8: 3 | BC8: 5.07 | BD8: 10 | BE8: 10 | BF8: 8.4 | BG8: 10.533333 | BH8: 9.75 | BI8: 0.0013811728 | BJ8: 0.0013888889 | BK8: 195 | BL8: 7.45 | BM8: 5.375 | BN8: 0.0027623457 | BO8: 0.0027777778 | BP8: 97.5
A9: 306038 | B9: 2995193 | C9: 1435157 | D9: -2 | E9: 44303.69 | G9: 44335.15 | H9: Street | I9: 175 | J9: Hytex | K9: 8536263 | L9: 4.80934 | M9: 2.24259 | N9: 2.35782 | O9: 4 | P9: 9 | Q9: 7.5 | R9: 5 | S9: 0.0013078704 | T9: SOUND VOLTEX EXCEED GEAR | U9: 10 | V9: 5 | W9: Sakura Fubuki | X9: 0.0013078704 | Y9: 99's Insane | Z9: 1908301f3fe1aa60d5f5439052d3aa17 | AA9: 0 | AB9: muse dash sdvx 6 vi dynamix maimai murasaki chunithm air オンゲキ ongeki plus o.n.g.e.k.i. bemani konami sega 桜吹雪 bms of fighters ultimate bofu2015 osu! fa featured artist artcore video game electronic instrumental purplegaze manasser99 ambrew ixcors | AC9: 1 | AD9: 0 | AE9: 87 | AF9: 16 | AG9: 222 | AH9: 135 | AI9: 0 | AJ9: 593 | AK9: 0 | AL9: 0 | AM9: 0 | AN9: 0 | AO9: 4.37351 | AP9: 5.07207 | AQ9: 6.89446 | AR9: 3.814 | AT9: Street - Sakura Fubuki [99's Insane] | AU9: https://osu.ppy.sh/beatmapsets/1435157#osu/2995193 | AV9: https://assets.ppy.sh/beatmaps/1435157/covers/cover.jpg | AW9: https://b.ppy.sh/thumb/1435157l.jpg | AX9: Street - Sakura Fubuki [99's Insane] | AY9: 2 | AZ9: 4.5 | BA9: 3.75 | BB9: 2.5 | BC9: 5.2 | BD9: 10 | BE9: 10 | BF9: 7 | BG9: 10.333333 | BH9: 9.4166667 | BI9: 0.00087191358 | BJ9: 0.00087191358 | BK9: 262.5 | BL9: 7 | BM9: 4.625 | BN9: 0.0017438272 | BO9: 0.0017438272 | BP9: 131.25
A10: 3298592 | B10: 3496410 | C10: 1528914 | D10: 1 | E10: 44401.388 | F10: 44649.366 | G10: 44640.823 | H10: Shimotsuki Haruka, Chata, Katakiri Rekka | I10: 186 | J10: Deca | K10: 9088487 | L10: 5.17999 | M10: 2.62407 | N10: 2.31138 | O10: 4.2 | P10: 9 | Q10: 8 | R10: 5 | S10: 0.0031944444 | U10: 13 | V10: 3 | W10: Suishou ni Utsuru Himegimi | X10: 0.0033796296 | Y10: Collab Insane | Z10: a7ae0a768dae11d897a89f61ee99cb61 | AA10: 0 | AB10: kalibe fuju acylica some hero some_hero heroine elicz1 zelq shimotsuki best works hamotsukin 753 japanese folk | AC10: 57 | AD10: 9.75 | AE10: 8425 | AF10: 1026 | AG10: 628 | AH10: 440 | AI10: 1 | AJ10: 1595 | AK10: 0 | AL10: 0 | AM10: 0 | AN10: 0 | AO10: 4.727 | AP10: 5.53064 | AQ10: 7.32173 | AR10: 4.11481 | AT10: Shimotsuki Haruka, Chata, Katakiri Rekka - Suishou ni Utsuru Himegimi [Collab Insane] | AU10: https://osu.ppy.sh/beatmapsets/1528914#osu/3496410 | AV10: https://assets.ppy.sh/beatmaps/1528914/covers/cover.jpg | AW10: https://b.ppy.sh/thumb/1528914l.jpg | AX10: Shimotsuki Haruka, Chata, Katakiri Rekka - Suishou ni Utsuru Himegimi [Collab Insane] | AY10: 2.1 | AZ10: 4.5 | BA10: 4 | BB10: 2.5 | BC10: 5.46 | BD10: 10 | BE10: 10 | BF10: 7 | BG10: 10.333333 | BH10: 9.75 | BI10: 0.0021296296 | BJ10: 0.0022530864 | BK10: 279 | BL10: 7 | BM10: 5.375 | BN10: 0.0042592593 | BO10: 0.0045061728 | BP10: 139.5
A11: 1405094 | B11: 3737825 | C11: 1544866 | D11: -2 | E11: 44418.116 | G11: 44900.214 | H11: PSYQUI | I11: 180 | J11: JeZag | K11: 3087506 | L11: 4.71109 | M11: 2.15506 | N11: 2.34525 | O11: 4 | P11: 9 | Q11: 8 | R11: 6 | S11: 0.0024884259 | U11: 10 | V11: 5 | W11: Education | X11: 0.0025925926 | Y11: sorciere's Insane | Z11: 8a5798453021f8a74d028f149da3e9bc | AA11: 0 | AB11: electronic instrumental future bass techcore evangelix 01 megarex mrx sorciere | AC11: 64 | AD11: 0 | AE11: 1639 | AF11: 734 | AG11: 330 | AH11: 434 | AI11: 8 | AJ11: 1333 | AK11: 0 | AL11: 0 | AM11: 0 | AN11: 0 | AO11: 4.35314 | AP11: 4.9217 | AQ11: 6.71858 | AR11: 3.75165 | AT11: PSYQUI - Education [sorciere's Insane] | AU11: https://osu.ppy.sh/beatmapsets/1544866#osu/3737825 | AV11: https://assets.ppy.sh/beatmaps/1544866/covers/cover.jpg | AW11: https://b.ppy.sh/thumb/1544866l.jpg | AX11: PSYQUI - Education [sorciere's Insane] | AY11: 2 | AZ11: 4.5 | BA11: 4 | BB11: 3 | BC11: 5.2 | BD11: 10 | BE11: 10 | BF11: 8.4 | BG11: 10.333333 | BH11: 9.75 | BI11: 0.0016589506 | BJ11: 0.0017283951 | BK11: 270 | BL11: 7 | BM11: 5.375 | BN11: 0.0033179012 | BO11: 0.0034567901 | BP11: 135
A12: 646609 | B12: 3887774 | C12: 1758376 | D12: 1 | E12: 44687.729 | F12: 44947.599 | G12: 44940.298 | H12: Noah | I12: 197 | J12: Adinda | K12: 15959751 | L12: 4.84232 | M12: 2.4895 | N12: 2.10918 | O12: 4 | P12: 9 | Q12: 8 | R12: 6 | S12: 0.0022106481 | U12: 11 | V12: 5 | W12: Purification of soul | X12: 0.0022106481 | Y12: Flame Haze's Insane | Z12: 01f1284f1442b986a50be29b4a79a0f9 | AA12: 0 | AB12: metal symphonic rock classical orchestral instrumental doujin m3-49 god bless you existruth syarika flame haze | AC12: 131 | AD12: 9.4434 | AE12: 20539 | AF12: 3103 | AG12: 328 | AH12: 411 | AI12: 1 | AJ12: 1187 | AK12: 0 | AL12: 0 | AM12: 0 | AN12: 0 | AO12: 4.44689 | AP12: 5.12767 | AQ12: 6.79352 | AR12: 3.86378 | AT12: Noah - Purification of soul [Flame Haze's Insane] | AU12: https://osu.ppy.sh/beatmapsets/1758376#osu/3887774 | AV12: https://assets.ppy.sh/beatmaps/1758376/covers/cover.jpg | AW12: https://b.ppy.sh/thumb/1758376l.jpg | AX12: Noah - Purification of soul [Flame Haze's Insane] | AY12: 2 | AZ12: 4.5 | BA12: 4 | BB12: 3 | BC12: 5.2 | BD12: 10 | BE12: 10 | BF12: 8.4 | BG12: 10.333333 | BH12: 9.75 | BI12: 0.0014737654 | BJ12: 0.0014737654 | BK12: 295.5 | BL12: 7 | BM12: 5.375 | BN12: 0.0029475309 | BO12: 0.0029475309 | BP12: 147.75
A13: 3958395 | B13: 2514122 | C13: 1207286 | D13: 1 | E13: 44017.331 | F13: 44103.557 | G13: 44101.026 | H13: Wagakki Band | I13: 200 | J13: IOException | K13: 2688103 | L13: 4.95233 | M13: 2.36544 | N13: 2.37523 | O13: 3 | P13: 9 | Q13: 8 | R13: 5 | S13: 0.0025810185 | T13: カゲロウプロジェクト | U13: 4 | V13: 3 | W13: Kagerou Days | X13: 0.002662037 | Y13: Ducky-'s Insane | Z13: 9ae24c29a400d9effdc56b73935f9caa | AA13: 0 | AB13: ボカロ三昧 heat-haze kagerou project daze jin じん shizen no teki-p teki p tekip 自然の敵p mekakucity actors メカクシティアクターズ vocalo zanmai japanese vocaloid daze rock deadcode ceo ceo_of_osu wafer goopert i_want_to_die ducky- | AC13: 110 | AD13: 9.46486 | AE13: 24616 | AF13: 3312 | AG13: 551 | AH13: 427 | AI13: 1 | AJ13: 1469 | AK13: 0 | AL13: 0 | AM13: 0 | AN13: 0 | AO13: 4.67109 | AP13: 5.08079 | AQ13: 7.21848 | AR13: 3.98046 | AT13: Wagakki Band - Kagerou Days [Ducky-'s Insane] | AU13: https://osu.ppy.sh/beatmapsets/1207286#osu/2514122 | AV13: https://assets.ppy.sh/beatmaps/1207286/covers/cover.jpg | AW13: https://b.ppy.sh/thumb/1207286l.jpg | AX13: Wagakki Band - Kagerou Days [Ducky-'s Insane] | AY13: 1.5 | AZ13: 4.5 | BA13: 4 | BB13: 2.5 | BC13: 3.9 | BD13: 10 | BE13: 10 | BF13: 7 | BG13: 10.333333 | BH13: 9.75 | BI13: 0.001720679 | BJ13: 0.0017746914 | BK13: 300 | BL13: 7 | BM13: 5.375 | BN13: 0.003441358 | BO13: 0.0035493827 | BP13: 150
A14: 3823691 | B14: 2619929 | C14: 1238190 | D14: 1 | E14: 44060.583 | F14: 44180.723 | G14: 44173.576 | H14: Amane | I14: 165 | J14: Luscent | K14: 2688581 | L14: 4.61004 | M14: 2.21621 | N14: 2.19671 | O14: 5 | P14: 8 | Q14: 7 | R14: 5 | S14: 0.0016550926 | T14: 東方地霊殿 ～ Subterranean Animism. | U14: 10 | V14: 5 | W14: BOOZEHOUND | X14: 0.0017939815 | Y14: Down's Insane | Z14: 0db9c676ce97ec1444f954ed03454e1e | AA14: 0 | AB14: 旧地獄街道を行く walking the streets of a former hell kyuu jigoku kaidou wo yuku 東方project 東方 touhou project th11 shanghai alice gengakudan team chireiden rolling contact touhou instrumental electronic 404 aimnotfound dailycare morinaga down heilia | AC14: 88 | AD14: 9.46933 | AE14: 35677 | AF14: 4249 | AG14: 250 | AH14: 302 | AI14: 0 | AJ14: 940 | AK14: 0 | AL14: 0 | AM14: 0 | AN14: 0 | AO14: 4.14613 | AP14: 5.14056 | AQ14: 6.48803 | AR14: 3.67392 | AT14: Amane - BOOZEHOUND [Down's Insane] | AU14: https://osu.ppy.sh/beatmapsets/1238190#osu/2619929 | AV14: https://assets.ppy.sh/beatmaps/1238190/covers/cover.jpg | AW14: https://b.ppy.sh/thumb/1238190l.jpg | AX14: Amane - BOOZEHOUND [Down's Insane] | AY14: 2.5 | AZ14: 4 | BA14: 3.5 | BB14: 2.5 | BC14: 6.5 | BD14: 10 | BE14: 9.8 | BF14: 7 | BG14: 9.6666667 | BH14: 9.0833333 | BI14: 0.0011033951 | BJ14: 0.0011959877 | BK14: 247.5 | BL14: 5.5 | BM14: 3.875 | BN14: 0.0022067901 | BO14: 0.0023919753 | BP14: 123.75
A15: 3563790 | B15: 3958395 | C15: 1918243 | D15: 1 | E15: 44933.665 | F15: 44977.543 | G15: 44969.933 | H15: Numakura Manami | I15: 195 | J15: Andrea | K15: 33599 | L15: 4.83085 | M15: 2.38745 | N15: 2.23069 | O15: 3.6 | P15: 9 | Q15: 8 | R15: 5 | S15: 0.0026388889 | T15: 魔法少女育成計画 | U15: 4 | V15: 3 | W15: Sakebe | X15: 0.0027893519 | Y15: Mrgglock's Insane | Z15: 224f865a277e9f55d539dc2a0abf4563 | AA15: 0 | AB15: osuplayer111 sekai sekaii sekai-nyan mrgglock browiec torriru kxlman kowari pop jpop j-pop rock jrock j-rock anime japanese mahou shoujo ikusei keikaku magical girl raising project まほいく mahoiku full version | AC15: 95 | AD15: 9.44628 | AE15: 13762 | AF15: 2547 | AG15: 452 | AH15: 408 | AI15: 0 | AJ15: 1303 | AK15: 0 | AL15: 0 | AM15: 0 | AN15: 0 | AO15: 4.48163 | AP15: 5.06865 | AQ15: 6.93955 | AR15: 3.82178 | AT15: Numakura Manami - Sakebe [Mrgglock's Insane] | AU15: https://osu.ppy.sh/beatmapsets/1918243#osu/3958395 | AV15: https://assets.ppy.sh/beatmaps/1918243/covers/cover.jpg | AW15: https://b.ppy.sh/thumb/1918243l.jpg | AX15: Numakura Manami - Sakebe [Mrgglock's Insane] | AY15: 1.8 | AZ15: 4.5 | BA15: 4 | BB15: 2.5 | BC15: 4.68 | BD15: 10 | BE15: 10 | BF15: 7 | BG15: 10.333333 | BH15: 9.75 | BI15: 0.0017592593 | BJ15: 0.0018595679 | BK15: 292.5 | BL15: 7 | BM15: 5.375 | BN15: 0.0035185185 | BO15: 0.0037191358 | BP15: 146.25
A16: 63604 | B16: 1523138 | C16: 721320 | D16: 1 | E16: 43116.93 | F16: 43258.097 | G16: 43252.894 | H16: Kajiura Yuki | I16: 155.42 | J16: Asonate | K16: 2907231 | L16: 3.87614 | M16: 2.03268 | N16: 1.6248 | O16: 5 | P16: 8.3 | Q16: 7.7 | R16: 5 | S16: 0.0016782407 | T16: 魔法少女まどか☆マギカ | U16: 3 | V16: 14 | W16: Sis puella magica! | X16: 0.001712963 | Y16: Tea Party | Z16: 280879f5867e46f8f97a4889c8e99269 | AA16: 0 | AB16: itoh eri 伊東恵里 mahou shoujo madoka magica puella magi orchestral vocals calm chill main theme ayyri eiri- | AC16: 353 | AD16: 9.375 | AE16: 107370 | AF16: 24444 | AG16: 257 | AH16: 166 | AI16: 2 | AJ16: 611 | AK16: 0 | AL16: 0 | AM16: 0 | AN16: 0 | AO16: 3.42938 | AP16: 4.44079 | AQ16: 5.40138 | AR16: 3.10616 | AT16: Kajiura Yuki - Sis puella magica! [Tea Party] | AU16: https://osu.ppy.sh/beatmapsets/721320#osu/1523138 | AV16: https://assets.ppy.sh/beatmaps/721320/covers/cover.jpg | AW16: https://b.ppy.sh/thumb/721320l.jpg | AX16: Kajiura Yuki - Sis puella magica! [Tea Party] | AY16: 2.5 | AZ16: 4.15 | BA16: 3.85 | BB16: 2.5 | BC16: 6.5 | BD16: 10 | BE16: 10 | BF16: 7 | BG16: 9.8666667 | BH16: 9.55 | BI16: 0.0011188272 | BJ16: 0.0011419753 | BK16: 233.13 | BL16: 5.95 | BM16: 4.925 | BN16: 0.0022376543 | BO16: 0.0022839506 | BP16: 116.565
A17: 3841174 | B17: 4105349 | C17: 1977605 | D17: 1 | E17: 45033.977 | F17: 45048.85 | G17: 45040.816 | H17: ICHIKO | I17: 157 | J17: Andrea | K17: 33599 | L17: 3.61361 | M17: 1.66524 | N17: 1.78871 | O17: 3.8 | P17: 8 | Q17: 6 | R17: 4 | S17: 0.0025578704 | T17: ゼロの使い魔～三美姫(プリンセッセ)の輪舞(ロンド)～ | U17: 5 | V17: 3 | W17: YOU'RE THE ONE | X17: 0.0028703704 | Y17: ANDREA & ASUKO'S HARD | Z17: 45d2b7dabe3ac5620a65b175f6e9e7f3 | AA17: 0 | AB17: osuplayer111 sekai sekaii sekai-nyan leomine leominexd asukow grazuko full version female vocals zero no tsukaima: princess no rondo anime japanese pop jpop j-pop louise françoise de la baume le blanc de la vallière ルイズ・フランソワーズ・ル・ブラン・ド・ラ・ヴァリエール the familiar of zero: rondo of princesses third season 3rd opening op youre are | AC17: 52 | AD17: 9.31429 | AE17: 1927 | AF17: 485 | AG17: 402 | AH17: 328 | AI17: 0 | AJ17: 1094 | AK17: 0 | AL17: 0 | AM17: 0 | AN17: 0 | AO17: 3.28003 | AP17: 3.75267 | AQ17: 5.08077 | AR17: 2.8875 | AT17: ICHIKO - YOU'RE THE ONE [ANDREA & ASUKO'S HARD] | AU17: https://osu.ppy.sh/beatmapsets/1977605#osu/4105349 | AV17: https://assets.ppy.sh/beatmaps/1977605/covers/cover.jpg | AW17: https://b.ppy.sh/thumb/1977605l.jpg | AX17: ICHIKO - YOU'RE THE ONE [ANDREA & ASUKO'S HARD] | AY17: 1.9 | AZ17: 4 | BA17: 3 | BB17: 2 | BC17: 4.94 | BD17: 10 | BE17: 8.4 | BF17: 5.6 | BG17: 9.6666667 | BH17: 8.4166667 | BI17: 0.0017052469 | BJ17: 0.0019135802 | BK17: 235.5 | BL17: 5.5 | BM17: 2.375 | BN17: 0.0034104938 | BO17: 0.0038271605 | BP17: 117.75
A18: 2751338 | B18: 3411549 | C18: 1670325 | D18: 0 | E18: 44570.445 | G18: 45118.548 | H18: Ardolf | I18: 170 | J18: Ixcors | K18: 11194087 | L18: 3.62419 | M18: 1.56318 | N18: 1.87327 | O18: 3.8 | P18: 8 | Q18: 6.5 | R18: 5 | S18: 0.0020949074 | U18: 10 | V18: 5 | W18: Split EX | X18: 0.0021064815 | Y18: HARD | Z18: 0cf1d5b47d667c45054b6eb7a63cea00 | AA18: 0 | AB18: bqt4 bubblyqt's tournaments 4 ro128 nm2 stream burst electronic instrumental soundtrack videogame ost vg fa featured artist mg mappers' guild uk hardcore indoroid tigerinity ucitysm himitsuhiketsu hybrid chordjack ln long note edm dance fnf friday night funkin' | AC18: 70 | AD18: 0 | AE18: 4 | AF18: 1 | AG18: 319 | AH18: 341 | AI18: 1 | AJ18: 1329 | AK18: 0 | AL18: 0 | AM18: 0 | AN18: 0 | AO18: 3.28624 | AP18: 3.76802 | AQ18: 5.10535 | AR18: 2.89678 | AT18: Ardolf - Split EX [HARD] | AU18: https://osu.ppy.sh/beatmapsets/1670325#osu/3411549 | AV18: https://assets.ppy.sh/beatmaps/1670325/covers/cover.jpg | AW18: https://b.ppy.sh/thumb/1670325l.jpg | AX18: Ardolf - Split EX [HARD] | AY18: 1.9 | AZ18: 4 | BA18: 3.25 | BB18: 2.5 | BC18: 4.94 | BD18: 10 | BE18: 9.1 | BF18: 7 | BG18: 9.6666667 | BH18: 8.75 | BI18: 0.0013966049 | BJ18: 0.001404321 | BK18: 255 | BL18: 5.5 | BM18: 3.125 | BN18: 0.0027932099 | BO18: 0.002808642 | BP18: 127.5
A19: 3795759 | B19: 2395972 | C19: 1061614 | D19: 1 | E19: 43774.701 | F19: 44019.85 | G19: 44011.762 | H19: Hanabusa Sumireko (CV: Arakawa Miho) | I19: 157 | J19: Talulah | K19: 7543834 | L19: 4.90014 | M19: 2.38707 | N19: 2.30184 | O19: 3.6 | P19: 9 | Q19: 8 | R19: 5 | S19: 0.0025694444 | T19: 悪魔のリドル | U19: 3 | V19: 3 | W19: Inochi no Karakuri | X19: 0.0026967593 | Y19: Insane | Z19: 9ed612bd7153a9b00bcaf09289d22e12 | AA19: 0 | AB19: atalanta shizuku- akuma no riddle story of devil anime full version ed ending japanese rock | AC19: 339 | AD19: 9.54242 | AE19: 61605 | AF19: 8739 | AG19: 578 | AH19: 519 | AI19: 2 | AJ19: 1676 | AK19: 0 | AL19: 0 | AM19: 0 | AN19: 0 | AO19: 4.54892 | AP19: 5.13816 | AQ19: 6.97367 | AR19: 3.87443 | AT19: Hanabusa Sumireko (CV: Arakawa Miho) - Inochi no Karakuri [Insane] | AU19: https://osu.ppy.sh/beatmapsets/1061614#osu/2395972 | AV19: https://assets.ppy.sh/beatmaps/1061614/covers/cover.jpg | AW19: https://b.ppy.sh/thumb/1061614l.jpg | AX19: Hanabusa Sumireko (CV: Arakawa Miho) - Inochi no Karakuri [Insane] | AY19: 1.8 | AZ19: 4.5 | BA19: 4 | BB19: 2.5 | BC19: 4.68 | BD19: 10 | BE19: 10 | BF19: 7 | BG19: 10.333333 | BH19: 9.75 | BI19: 0.001712963 | BJ19: 0.0017978395 | BK19: 235.5 | BL19: 7 | BM19: 5.375 | BN19: 0.0034259259 | BO19: 0.003595679 | BP19: 117.75
A20: 1523138 | B20: 3720541 | C20: 1807986 | D20: 1 | E20: 44758.283 | F20: 44814.599 | G20: 44807.592 | H20: SID | I20: 200 | J20: gazimal | K20: 6055351 | L20: 4.86357 | M20: 2.50052 | N20: 2.11829 | O20: 4 | P20: 9 | Q20: 8 | R20: 5 | S20: 0.0024768519 | U20: 4 | V20: 3 | W20: Mousou Nikki 2 | X20: 0.0026273148 | Y20: Miy's Insane | Z20: c2265523d431e94e80292d17be81995b | AA20: 0 | AB20: ii japanese rock j-rock j rock mao sakura advent miy matsuyuki ame rk657 シド マオ shinji 明希 ゆうや male vocals vocalist jrock | AC20: 189 | AD20: 9.208 | AE20: 24499 | AF20: 5094 | AG20: 304 | AH20: 451 | AI20: 0 | AJ20: 1326 | AK20: 0 | AL20: 0 | AM20: 0 | AN20: 0 | AO20: 4.4628 | AP20: 5.15653 | AQ20: 6.76205 | AR20: 3.86866 | AT20: SID - Mousou Nikki 2 [Miy's Insane] | AU20: https://osu.ppy.sh/beatmapsets/1807986#osu/3720541 | AV20: https://assets.ppy.sh/beatmaps/1807986/covers/cover.jpg | AW20: https://b.ppy.sh/thumb/1807986l.jpg | AX20: SID - Mousou Nikki 2 [Miy's Insane] | AY20: 2 | AZ20: 4.5 | BA20: 4 | BB20: 2.5 | BC20: 5.2 | BD20: 10 | BE20: 10 | BF20: 7 | BG20: 10.333333 | BH20: 9.75 | BI20: 0.0016512346 | BJ20: 0.0017515432 | BK20: 300 | BL20: 7 | BM20: 5.375 | BN20: 0.0033024691 | BO20: 0.0035030864 | BP20: 150
A21: 2995193 | B21: 3081261 | C21: 1496416 | D21: 1 | E21: 44366.594 | F21: 44392.446 | G21: 44385.063 | H21: Co shu Nie | I21: 180 | J21: Nymphe | K21: 10507407 | L21: 4.76305 | M21: 2.27419 | N21: 2.28528 | O21: 4.2 | P21: 9 | Q21: 8 | R21: 5 | S21: 0.0012268519 | U21: 4 | V21: 3 | W21: Yume o Kin'iro ni Somete | X21: 0.001400463 | Y21: Insane ft. Kujinn | Z21: 0ca5572542d5f4e9775d9e3f03fcd9e0 | AA21: 0 | AB21: moete keqing iljaaz kujinn reform kiyoshi guarden japanese rock jrock j-rock female vocal litmus nakamura miku matsumoto shunsuke fujita ryosuke golden dream | AC21: 208 | AD21: 8.84892 | AE21: 23914 | AF21: 4816 | AG21: 204 | AH21: 237 | AI21: 0 | AJ21: 708 | AK21: 0 | AL21: 0 | AM21: 0 | AN21: 0 | AO21: 4.28273 | AP21: 5.10728 | AQ21: 6.84338 | AR21: 3.80411 | AT21: Co shu Nie - Yume o Kin'iro ni Somete [Insane ft. Kujinn] | AU21: https://osu.ppy.sh/beatmapsets/1496416#osu/3081261 | AV21: https://assets.ppy.sh/beatmaps/1496416/covers/cover.jpg | AW21: https://b.ppy.sh/thumb/1496416l.jpg | AX21: Co shu Nie - Yume o Kin'iro ni Somete [Insane ft. Kujinn] | AY21: 2.1 | AZ21: 4.5 | BA21: 4 | BB21: 2.5 | BC21: 5.46 | BD21: 10 | BE21: 10 | BF21: 7 | BG21: 10.333333 | BH21: 9.75 | BI21: 0.00081790123 | BJ21: 0.00093364198 | BK21: 270 | BL21: 7 | BM21: 5.375 | BN21: 0.0016358025 | BO21: 0.001867284 | BP21: 135
A22: 3496410 | B22: 3684386 | C22: 1712992 | D22: 1 | E22: 44625.785 | F22: 44945.739 | G22: 44936.858 | H22: S3RL feat. Sara | I22: 175 | J22: Nuvolina | K22: 10974170 | L22: 4.91691 | M22: 2.37273 | N22: 2.33367 | O22: 3.5 | P22: 9 | Q22: 8 | R22: 4.5 | S22: 0.0017708333 | U22: 10 | V22: 2 | W22: Dopamine | X22: 0.002037037 | Y22: Insane | Z22: 718cf23918399ac9244f862077bc658c | AA22: 0 | AB22: electronic english happy hardcore serl log off now log_off_now lon starcastler nowaie dtm9 nowa dtm9_nowa zer0- zero- zero maridius peter ajt smokelind uberfazz andrea osuplayer111 undeadcapulet firika chaos -mo- crissa nozhomi | AC22: 547 | AD22: 9.32812 | AE22: 131014 | AF22: 34651 | AG22: 291 | AH22: 295 | AI22: 0 | AJ22: 931 | AK22: 0 | AL22: 0 | AM22: 0 | AN22: 0 | AO22: 4.48133 | AP22: 5.18784 | AQ22: 7.05193 | AR22: 3.90412 | AT22: S3RL feat. Sara - Dopamine [Insane] | AU22: https://osu.ppy.sh/beatmapsets/1712992#osu/3684386 | AV22: https://assets.ppy.sh/beatmaps/1712992/covers/cover.jpg | AW22: https://b.ppy.sh/thumb/1712992l.jpg | AX22: S3RL feat. Sara - Dopamine [Insane] | AY22: 1.75 | AZ22: 4.5 | BA22: 4 | BB22: 2.25 | BC22: 4.55 | BD22: 10 | BE22: 10 | BF22: 6.3 | BG22: 10.333333 | BH22: 9.75 | BI22: 0.0011805556 | BJ22: 0.0013580247 | BK22: 262.5 | BL22: 7 | BM22: 5.375 | BN22: 0.0023611111 | BO22: 0.0027160494 | BP22: 131.25
A23: 2690081 | B23: 3783139 | C23: 1841846 | D23: 1 | E23: 44807.714 | F23: 44853.168 | G23: 44847.687 | H23: cYsmix | I23: 160 | J23: Delette | K23: 7835664 | L23: 4.55384 | M23: 2.30921 | N23: 2.02875 | O23: 5 | P23: 8 | Q23: 8 | R23: 4 | S23: 0.0012268519 | T23: osu! | U23: 10 | V23: 5 | W23: triangles | X23: 0.0014236111 | Y23: shime's absolutno another | Z23: be6bbea5f122aa8b41ddf23916245836 | AA23: 0 | AB23: featured artist fa mappers' guild mg mpg beatmapping contest maruoko piroshki shmiklak marvollo m_a_r_v_o_l_l_o shime pantydev electronic instrumental absolutno pofig | AC23: 108 | AD23: 8.69298 | AE23: 7759 | AF23: 837 | AG23: 207 | AH23: 186 | AI23: 0 | AJ23: 615 | AK23: 1 | AL23: 0 | AM23: 0 | AN23: 0 | AO23: 4.02814 | AP23: 5.20633 | AQ23: 6.3026 | AR23: 3.64497 | AT23: cYsmix - triangles [shime's absolutno another] | AU23: https://osu.ppy.sh/beatmapsets/1841846#osu/3783139 | AV23: https://assets.ppy.sh/beatmaps/1841846/covers/cover.jpg | AW23: https://b.ppy.sh/thumb/1841846l.jpg | AX23: cYsmix - triangles [shime's absolutno another] | AY23: 2.5 | AZ23: 4 | BA23: 4 | BB23: 2 | BC23: 6.5 | BD23: 10 | BE23: 10 | BF23: 5.6 | BG23: 9.6666667 | BH23: 9.75 | BI23: 0.00081790123 | BJ23: 0.00094907408 | BK23: 240 | BL23: 5.5 | BM23: 5.375 | BN23: 0.0016358025 | BO23: 0.0018981482 | BP23: 120
A24: 703042 | B24: 2027623 | C24: 932567 | D24: 1 | E24: 43523.873 | F24: 43648.458 | G24: 43640.766 | H24: THE ORAL CIGARETTES | I24: 142 | J24: DeviousPanda | K24: 4966334 | L24: 4.75197 | M24: 2.28015 | N24: 2.26871 | O24: 3.8 | P24: 9 | Q24: 7.5 | R24: 5 | S24: 0.0029166667 | T24: revisions リヴィジョンズ | U24: 3 | V24: 3 | W24: Wagamama de Gomakasanaide | X24: 0.0029166667 | Y24: Panda & Melwoine's Insane | Z24: 99ba8837287e306d4fded67610ba7279 | AA24: 0 | AB24: anime opening japanese full version melwoine collab rock j-rock op | AC24: 249 | AD24: 9.57028 | AE24: 109629 | AF24: 13806 | AG24: 862 | AH24: 321 | AI24: 1 | AJ24: 1523 | AK24: 0 | AL24: 0 | AM24: 0 | AN24: 0 | AO24: 4.4545 | AP24: 5.00382 | AQ24: 6.74635 | AR24: 3.7035 | AT24: THE ORAL CIGARETTES - Wagamama de Gomakasanaide [Panda & Melwoine's Insane] | AU24: https://osu.ppy.sh/beatmapsets/932567#osu/2027623 | AV24: https://assets.ppy.sh/beatmaps/932567/covers/cover.jpg | AW24: https://b.ppy.sh/thumb/932567l.jpg | AX24: THE ORAL CIGARETTES - Wagamama de Gomakasanaide [Panda & Melwoine's Insane] | AY24: 1.9 | AZ24: 4.5 | BA24: 3.75 | BB24: 2.5 | BC24: 4.94 | BD24: 10 | BE24: 10 | BF24: 7 | BG24: 10.333333 | BH24: 9.4166667 | BI24: 0.0019444444 | BJ24: 0.0019444444 | BK24: 213 | BL24: 7 | BM24: 4.625 | BN24: 0.0038888889 | BO24: 0.0038888889 | BP24: 106.5
A25: 3182641 | B25: 2305346 | C25: 1089678 | D25: 4 | E25: 43835.839 | F25: 45053.899 | G25: 45052.569 | H25: Juggernaut. | I25: 210 | J25: Fisky | K25: 8352623 | L25: 4.79428 | M25: 2.27612 | N25: 2.31293 | O25: 4 | P25: 8.8 | Q25: 8 | R25: 5 | S25: 0.0013541667 | T25: BOFXV | U25: 10 | V25: 5 | W25: Apocaliptix | X25: 0.0014351852 | Y25: PaRaDogi's Insane | Z25: 9aaddd951890f94f1850e52ce935e6be | AA25: 0 | AB25: bofxv19 bofxv2019 the bms of fighters extreme violence groundbreaking cube disc 4-7 electronic instrumental video game sexy & crazy psytrance psy hardcore symphonic dubstep bass necromancy japan door weapon hanakumo rin dog food _epreus theblank seolv [l_u_k_a_s] lukas moko paradogi kloyd | AC25: 351 | AD25: 9.54369 | AE25: 17641 | AF25: 4107 | AG25: 142 | AH25: 287 | AI25: 2 | AJ25: 851 | AK25: 0 | AL25: 1 | AM25: 0 | AN25: 0 | AO25: 4.35126 | AP25: 5.02113 | AQ25: 7.0222 | AR25: 3.80441 | AT25: Juggernaut. - Apocaliptix [PaRaDogi's Insane] | AU25: https://osu.ppy.sh/beatmapsets/1089678#osu/2305346 | AV25: https://assets.ppy.sh/beatmaps/1089678/covers/cover.jpg | AW25: https://b.ppy.sh/thumb/1089678l.jpg | AX25: Juggernaut. - Apocaliptix [PaRaDogi's Insane] | AY25: 2 | AZ25: 4.4 | BA25: 4 | BB25: 2.5 | BC25: 5.2 | BD25: 10 | BE25: 10 | BF25: 7 | BG25: 10.2 | BH25: 9.75 | BI25: 0.00090277778 | BJ25: 0.00095679012 | BK25: 315 | BL25: 6.7 | BM25: 5.375 | BN25: 0.0018055556 | BO25: 0.0019135802 | BP25: 157.5
A26: 1863870 | B26: 3310401 | C26: 1212359 | D26: 1 | E26: 44024.598 | F26: 44680.182 | G26: 44671.34 | H26: siromaru + cranky | I26: 160 | J26: yf_bmp | K26: 1243669 | L26: 4.94141 | M26: 2.44971 | N26: 2.27273 | O26: 4 | P26: 9.2 | Q26: 7 | R26: 5 | S26: 0.0015509259 | T26: THE BMS OF FIGHTERS 2011 - Intersection of conflict - | U26: 10 | V26: 14 | W26: conflict | X26: 0.001712963 | Y26: Yoshino's Insane | Z26: 8964064ef16f0cfd728bfef737cbca4c | AA26: 0 | AB26: iimo harmonic schranz electronic conlang english bof2011 arcaea sound voltex iii gravity wars maimai finale dx cytus ii deemo voez synchronica taiko no tatsujin chunithm o.n.g.e.k.i ongeki muse dash tapsonic top groove coaster waiwai party!!!! 2 original style rhythmvaders wacca seven's code dance rail respect pump it up orzmic takumi x_light yorita_yoshino setu strengemistake x light yorita yoshino video rhythm game featured artist fa mappers' guild mappers mpg | AC26: 328 | AD26: 9.31849 | AE26: 38323 | AF26: 8272 | AG26: 347 | AH26: 224 | AI26: 1 | AJ26: 872 | AK26: 1 | AL26: 1 | AM26: 0 | AN26: 0 | AO26: 4.52646 | AP26: 5.24798 | AQ26: 6.97444 | AR26: 3.9312 | AT26: siromaru + cranky - conflict [Yoshino's Insane] | AU26: https://osu.ppy.sh/beatmapsets/1212359#osu/3310401 | AV26: https://assets.ppy.sh/beatmaps/1212359/covers/cover.jpg | AW26: https://b.ppy.sh/thumb/1212359l.jpg | AX26: siromaru + cranky - conflict [Yoshino's Insane] | AY26: 2 | AZ26: 4.6 | BA26: 3.5 | BB26: 2.5 | BC26: 5.2 | BD26: 10 | BE26: 9.8 | BF26: 7 | BG26: 10.466667 | BH26: 9.0833333 | BI26: 0.0010339506 | BJ26: 0.0011419753 | BK26: 240 | BL26: 7.3 | BM26: 3.875 | BN26: 0.0020679012 | BO26: 0.0022839506 | BP26: 120
A27: 4105349 | B27: 4121042 | C27: 1909726 | D27: 1 | E27: 44920.197 | F27: 45101.614 | G27: 45091.844 | H27: Dance Gavin Dance | I27: 158 | J27: YeongSeok | K27: 13471105 | L27: 3.65468 | M27: 1.67357 | N27: 1.81786 | O27: 3.6 | P27: 8.5 | Q27: 6.5 | R27: 4 | S27: 0.002349537 | U27: 11 | V27: 2 | W27: Deception | X27: 0.0025462963 | Y27: Sebas' Hard | Z27: 25001b8bd92573a7335ed76fcd54f51c | AA27: 0 | AB27: english mothership rock alt alternative metal virt virt- monsieursebas sebas punk vocal post hardcore dgd | AC27: 69 | AD27: 8.58182 | AE27: 2359 | AF27: 765 | AG27: 215 | AH27: 286 | AI27: 4 | AJ27: 1067 | AK27: 0 | AL27: 0 | AM27: 0 | AN27: 0 | AO27: 3.3133 | AP27: 3.79194 | AQ27: 5.05493 | AR27: 2.91472 | AT27: Dance Gavin Dance - Deception [Sebas' Hard] | AU27: https://osu.ppy.sh/beatmapsets/1909726#osu/4121042 | AV27: https://assets.ppy.sh/beatmaps/1909726/covers/cover.jpg | AW27: https://b.ppy.sh/thumb/1909726l.jpg | AX27: Dance Gavin Dance - Deception [Sebas' Hard] | AY27: 1.8 | AZ27: 4.25 | BA27: 3.25 | BB27: 2 | BC27: 4.68 | BD27: 10 | BE27: 9.1 | BF27: 5.6 | BG27: 10 | BH27: 8.75 | BI27: 0.001566358 | BJ27: 0.0016975309 | BK27: 237 | BL27: 6.25 | BM27: 3.125 | BN27: 0.003132716 | BO27: 0.0033950617 | BP27: 118.5
A28: 2016938 | B28: 908887 | C28: 357800 | D28: -2 | E28: 42267.146 | G28: 42881.931 | H28: void | I28: 170 | J28: ouranhshc | K28: 139493 | L28: 5.06513 | M28: 2.03293 | N28: 2.70613 | O28: 4 | P28: 9 | Q28: 8 | R28: 7 | S28: 0.0013194444 | U28: 1 | V28: 1 | W28: Crisscrosser | X28: 0.0013310185 | Y28: Insane | Z28: 4f599f04b54ab5df5d72c6468ea607dd | AA28: 0 | AC28: 6 | AD28: 0 | AE28: 838 | AF28: 229 | AG28: 449 | AH28: 162 | AI28: 2 | AJ28: 817 | AK28: 0 | AL28: 0 | AM28: 0 | AN28: 0 | AO28: 4.78099 | AP28: 5.19994 | AQ28: 7.46437 | AR28: 3.97247 | AT28: void - Crisscrosser [Insane] | AU28: https://osu.ppy.sh/beatmapsets/357800#osu/908887 | AV28: https://assets.ppy.sh/beatmaps/357800/covers/cover.jpg | AW28: https://b.ppy.sh/thumb/357800l.jpg | AX28: void - Crisscrosser [Insane] | AY28: 2 | AZ28: 4.5 | BA28: 4 | BB28: 3.5 | BC28: 5.2 | BD28: 10 | BE28: 10 | BF28: 9.8 | BG28: 10.333333 | BH28: 9.75 | BI28: 0.00087962963 | BJ28: 0.00088734568 | BK28: 255 | BL28: 7 | BM28: 5.375 | BN28: 0.0017592593 | BO28: 0.0017746914 | BP28: 127.5
